Workbook

Sheet DATA SAME VIN_202605
AO1: =COUNTIF(AO4:AO1008, "?*") -> 551 | AT1: =COUNTIF(AT4:AT1008, TRUE) -> 385 | AU1: =COUNTIF(AU4:AU1008, TRUE) -> 166 | AV1: =COUNTIF(AV4:AV1008, TRUE) -> 55
A2: Date | B2: LINK SESSION | C2: vin | D2: country | E2: model_year | F2: make | G2: model | H2: dsp_code | I2: delivery_station | J2: group_name | K2: account_name | L2: user_name | M2: session_key | N2: inspection_type | O2: inspection_status | P2: condition_report | Q2: inspection_create_datetime | R2: inspection_completion_datetime | S2: time_to_capture | T2: condition_report_completion_datetime | U2: condition_report_latency | V2: grading_standard | W2: total_chargeable_damage | X2: wtg_damages_left_side | Y2: wtg_damages_front_side | Z2: wtg_damages_right_side | AA2: wtg_damages_back_side | AB2: additional_chargeable_damages_left_side | AC2: additional_chargeable_damages_front_side | AD2: additional_chargeable_damages_right_side | AE2: additional_chargeable_damages_back_side | AF2: currency_type | AG2: low lighting | AH2: excessive brightness | AI2: blurred | AJ2: distance capture | AK2: shallow angle | AL2: poor framing | AM2: Note | AO2: Sessions | AP2: Reason | AQ2: Agent | AR2: QA | AS2: RE-CHECK & NOTE | AT2: Review ID Same Vin | AV2: Tick Miss/Repair
AT3: Đúng | AU3: Sai
A4: 0501-1hrs_NA | B4: {=IF(M4:M1008="","","https://agent-admin.paveapi.com/inspectionView/"&M4:M1008&"?activeTab=past-sessions")} -> https://agent-admin.paveapi.com/inspectionView/AMWT-VBAPZIS7EW?activeTab=past-sessions | C4: 1FTBR3X80MKA55750 | D4: US | E4: 2021 | F4: Ford | G4: Transit | H4: CAGT | I4: DFX3 | J4: DSP Accounts | K4: CAGT | L4: CAGT.user | M4: AMWT-VBAPZIS7EW | N4: Wear & Tear | O4: COMPLETE | P4: https://dashboard.paveapi.com/park/AMWT-VBAPZIS7EW/?l=en | Q4: 46144.002 | R4: 46144.007 | S4: 374 | T4: 46144.01 | U4: 1561 | V4: 2 | W4: 3210 | X4: 0 | Y4: 0 | Z4: 3 | AA4: 0 | AB4: 1 | AC4: 0 | AD4: 0 | AE4: 0 | AF4: USD | AG4: FALSE | AH4: FALSE | AI4: FALSE | AJ4: FALSE | AK4: FALSE | AL4: FALSE | AN4: {=IF(C4:C1008="","", IF(ROW(A4:A1008)=4, IF(A4<>"", DATE(2026, VALUE(LEFT(A4,2)), VALUE(MID(A4,3,2))), ""), IF(A4:A1008<>"", DATE(2026, VALUE(LEFT(A4:A1008,2)), VALUE(MID(A4:A1008,3,2))), LOOKUP(ROW(A4:A1008), ROW(A4:A1008)/(A4:A1008<>""), DATE(2026, VALUE(LEFT(A4:A1008,2)), VALUE(MID(A4:A1008,3,2))) ) ) ) )} -> 46143 | AO4: {=IF(M4:M1008<>"", M4:M1008, "")} -> AMWT-VBAPZIS7EW | AP4: QA Wrong damage | AR4: thien.ht | AS4: View 4: (3) Damage OLD xác định sai ( trầy nông) | AT4: FALSE | AU4: TRUE | AV4: FALSE
B5: https://agent-admin.paveapi.com/inspectionView/AMWT-4OBMFH3IF8?activeTab=past-sessions | C5: 1FTBR3X80MKA55750 | D5: US | E5: 2021 | F5: Ford | G5: Transit | H5: CAGT | I5: DFX3 | J5: DSP Accounts | K5: CAGT | L5: CAGT.user | M5: AMWT-4OBMFH3IF8 | N5: Wear & Tear | O5: COMPLETE | P5: https://dashboard.paveapi.com/park/AMWT-4OBMFH3IF8/?l=en | Q5: 46144.034 | R5: 46144.041 | S5: 546 | T5: 46144.045 | U5: 1164 | V5: 2 | W5: 2425 | X5: 0 | Y5: 0 | Z5: 3 | AA5: 0 | AB5: 0 | AC5: 0 | AD5: 0 | AE5: 0 | AF5: USD | AG5: FALSE | AH5: FALSE | AI5: FALSE | AJ5: FALSE | AK5: FALSE | AL5: FALSE | AM5: View 4: Remove wrong damage. / Correct one. | AN5: 46143 | AO5: AMWT-4OBMFH3IF8 | AT5: TRUE | AU5: FALSE | AV5: FALSE
B6: https://agent-admin.paveapi.com/inspectionView/AMWT-NL4VGUG6LA?activeTab=past-sessions | C6: 1FTBR3X83LKA48273 | D6: US | E6: 2020 | F6: Ford | G6: TRANSIT | H6: GOCZ | I6: WSV1 | J6: DSP Accounts | K6: GOCZ | L6: GOCZ.user | M6: AMWT-NL4VGUG6LA | N6: Fleet Improvement Fund | O6: COMPLETE | P6: https://dashboard.paveapi.com/park/AMWT-NL4VGUG6LA/?l=en | Q6: 46143.882 | R6: 46143.884 | S6: 109 | T6: 46143.891 | U6: 928 | V6: 2 | W6: 3860 | X6: 1 | Y6: 1 | Z6: 1 | AA6: 3 | AB6: 0 | AC6: 0 | AD6: 1 | AE6: 0 | AF6: USD | AG6: FALSE | AH6: FALSE | AI6: FALSE | AJ6: FALSE | AK6: FALSE | AL6: FALSE | AM6: / Correct one. | AN6: 46143 | AO6: AMWT-NL4VGUG6LA | AT6: TRUE | AU6: FALSE | AV6: FALSE
B7: https://agent-admin.paveapi.com/inspectionView/AMWT-BMUFW4BSCS?activeTab=past-sessions | C7: 1FTBR3X83LKA48273 | D7: US | E7: 2020 | F7: Ford | G7: TRANSIT | H7: GOCZ | I7: WSV1 | J7: DSP Accounts | K7: GOCZ | L7: GOCZ.user | M7: AMWT-BMUFW4BSCS | N7: Fleet Improvement Fund | O7: COMPLETE | P7: https://dashboard.paveapi.com/park/AMWT-BMUFW4BSCS/?l=en | Q7: 46143.912 | R7: 46143.914 | S7: 113 | T7: 46143.929 | U7: 1958 | V7: 3 | W7: 2675 | X7: 0 | Y7: 1 | Z7: 0 | AA7: 1 | AB7: 0 | AC7: 0 | AD7: 0 | AE7: 0 | AF7: USD | AG7: FALSE | AH7: FALSE | AI7: FALSE | AJ7: FALSE | AK7: FALSE | AL7: FALSE | AM7: View 4,7,8: Repaired. / Correct one. | AN7: 46143 | AO7: AMWT-BMUFW4BSCS | AT7: TRUE | AU7: FALSE | AV7: FALSE
B8: https://agent-admin.paveapi.com/inspectionView/AMWT-HMGVZGKD5B?activeTab=past-sessions | C8: 1FTBR3X83LKB04163 | D8: US | E8: 2020 | F8: Ford | G8: TRANSIT | H8: FRSN | I8: DSJ5 | J8: DSP Accounts | K8: FRSN | L8: SA2020 | M8: AMWT-HMGVZGKD5B | N8: Wear & Tear | O8: COMPLETE | P8: https://dashboard.paveapi.com/park/AMWT-HMGVZGKD5B/?l=en | Q8: 46143.926 | R8: 46143.927 | S8: 108 | T8: 46143.938 | U8: 4199 | V8: 4 | W8: 1755 | X8: 0 | Y8: 2 | Z8: 1 | AA8: 2 | AB8: 0 | AC8: 0 | AD8: 0 | AE8: 0 | AF8: USD | AG8: FALSE | AH8: FALSE | AI8: FALSE | AJ8: FALSE | AK8: FALSE | AL8: FALSE | AN8: 46143 | AO8: AMWT-HMGVZGKD5B | AS8: View 5: (2) Damage OLD kích thước nhỏ / Hình tối -> skip | AT8: FALSE | AU8: TRUE | AV8: FALSE
B9: https://agent-admin.paveapi.com/inspectionView/AMWT-FNK0WP6LGZ?activeTab=past-sessions | C9: 1FTBR3X83LKB04163 | D9: US | E9: 2020 | F9: Ford | G9: Transit | H9: FRSN | I9: DSJ5 | J9: DSP Accounts | K9: FRSN | L9: SA2020 | M9: AMWT-FNK0WP6LGZ | N9: Fleet Improvement Fund | O9: COMPLETE | P9: https://dashboard.paveapi.com/park/AMWT-FNK0WP6LGZ/?l=en | Q9: 46143.937 | R9: 46143.938 | S9: 91 | T9: 46143.951 | U9: 1263 | V9: 5 | W9: 970 | X9: 0 | Y9: 1 | Z9: 1 | AA9: 2 | AB9: 0 | AC9: 0 | AD9: 0 | AE9: 0 | AF9: USD | AG9: FALSE | AH9: FALSE | AI9: FALSE | AJ9: FALSE | AK9: FALSE | AL9: FALSE | AM9: View 5: Remove false positive damage. / Correct one. | AN9: 46143 | AO9: AMWT-FNK0WP6LGZ | AT9: TRUE | AU9: FALSE | AV9: FALSE
B10: https://agent-admin.paveapi.com/inspectionView/AMUO-MF9LWCXEZ8?activeTab=past-sessions | C10: 1FTBR3X85LKA87351 | D10: US | E10: 2020 | F10: Ford | G10: Transit | H10: AMZL | I10: AMZL | J10: Last Mile Rentals | K10: AMZL | M10: AMUO-MF9LWCXEZ8 | N10: Merchants_LMR_rtinsp | O10: COMPLETE | P10: https://dashboard.paveapi.com/park/AMUO-MF9LWCXEZ8/?l=en | Q10: 46143.542 | R10: 46143.544 | S10: 62 | T10: 46143.551 | U10: 788 | V10: 1 | W10: 14107.5 | X10: 6 | Y10: 7 | Z10: 11 | AA10: 2 | AB10: 2 | AC10: 0 | AD10: 0 | AE10: 0 | AF10: USD | AG10: FALSE | AH10: FALSE | AI10: FALSE | AJ10: FALSE | AK10: FALSE | AL10: FALSE | AN10: 46143 | AO10: AMUO-MF9LWCXEZ8 | AT10: TRUE | AU10: FALSE | AV10: FALSE
B11: https://agent-admin.paveapi.com/inspectionView/AMUO-NZVU2F1CVE?activeTab=past-sessions | C11: 1FTBR3X85LKA87351 | D11: US | E11: 2020 | F11: Ford | G11: Transit | H11: AMZL | I11: AMZL | J11: Last Mile Rentals | K11: AMZL | M11: AMUO-NZVU2F1CVE | N11: Merchants_LMR_rtinsp | O11: COMPLETE | P11: https://dashboard.paveapi.com/park/AMUO-NZVU2F1CVE/?l=en | Q11: 46143.554 | R11: 46143.555 | S11: 55 | T11: 46143.564 | U11: 1146 | V11: 1 | W11: 11022.5 | X11: 5 | Y11: 5 | Z11: 8 | AA11: 2 | AB11: 2 | AC11: 0 | AD11: 0 | AE11: 0 | AF11: USD | AG11: FALSE | AH11: FALSE | AI11: FALSE | AJ11: FALSE | AK11: FALSE | AL11: FALSE | AM11: View 4,5,7: Remove false positive damages. / Correct one. | AN11: 46143 | AO11: AMUO-NZVU2F1CVE | AT11: TRUE | AU11: FALSE | AV11: FALSE
B12: https://agent-admin.paveapi.com/inspectionView/AMWT-W31OGJODIC?activeTab=past-sessions | C12: 1FTBR3X88LKA47281 | D12: US | E12: 2020 | F12: Ford | G12: Transit | H12: AMZL | I12: AMZL | J12: Fleet Management Companies | K12: AMZL | L12: raffiautobody | M12: AMWT-W31OGJODIC | N12: Vehicle Pre-Repair | O12: COMPLETE | P12: https://dashboard.paveapi.com/park/AMWT-W31OGJODIC/?l=en | Q12: 46143.821 | R12: 46143.823 | S12: 167 | T12: 46143.831 | U12: 957 | V12: 3 | W12: 6295 | X12: 5 | Y12: 0 | Z12: 4 | AA12: 0 | AB12: 0 | AC12: 0 | AD12: 0 | AE12: 0 | AF12: USD | AG12: FALSE | AH12: FALSE | AI12: FALSE | AJ12: FALSE | AK12: FALSE | AL12: FALSE | AN12: 46143 | AO12: AMWT-W31OGJODIC | AT12: TRUE | AU12: FALSE | AV12: FALSE
B13: https://agent-admin.paveapi.com/inspectionView/AMWT-BYCPD7THNO?activeTab=past-sessions | C13: 1FTBR3X88LKA47281 | D13: US | E13: 2020 | F13: Ford | G13: TRANSIT | H13: AMZL | I13: AMZL | J13: Fleet Management Companies | K13: AMZL | L13: raffiautobody | M13: AMWT-BYCPD7THNO | N13: Vehicle Pre-Repair | O13: COMPLETE | P13: https://dashboard.paveapi.com/park/AMWT-BYCPD7THNO/?l=en | Q13: 46143.851 | R13: 46143.852 | S13: 96 | T13: 46143.858 | U13: 708 | V13: 2 | W13: 5595 | X13: 4 | Y13: 0 | Z13: 4 | AA13: 0 | AB13: 0 | AC13: 0 | AD13: 0 | AE13: 0 | AF13: USD | AG13: FALSE | AH13: FALSE | AI13: FALSE | AJ13: FALSE | AK13: FALSE | AL13: FALSE | AM13: View 4: Remove wrong damage. / Correct one. | AN13: 46143 | AO13: AMWT-BYCPD7THNO | AT13: TRUE | AU13: FALSE | AV13: FALSE
B14: https://agent-admin.paveapi.com/inspectionView/AMWT-ACX2LE9CUE?activeTab=past-sessions | C14: 1FTBR3X89LKA28805 | D14: US | E14: 2020 | F14: Ford | G14: Transit | H14: KRUS | I14: DXH1 | J14: DSP Accounts | K14: KRUS | L14: KRUS | M14: AMWT-ACX2LE9CUE | N14: Fleet Improvement Fund | O14: COMPLETE | P14: https://dashboard.paveapi.com/park/AMWT-ACX2LE9CUE/?l=en | Q14: 46143.865 | R14: 46143.866 | S14: 92 | T14: 46143.869 | U14: 475 | V14: 2 | W14: 3550 | X14: 0 | Y14: 1 | Z14: 3 | AA14: 0 | AB14: 1 | AC14: 0 | AD14: 2 | AE14: 0 | AF14: USD | AG14: FALSE | AH14: FALSE | AI14: FALSE | AJ14: FALSE | AK14: FALSE | AL14: FALSE | AN14: 46143 | AO14: AMWT-ACX2LE9CUE | AP14: QA Wrong damage | AR14: vi.votuan | AS14: View 7: (5, 6) Damage OLD đã sửa chữa | AT14: FALSE | AU14: TRUE | AV14: TRUE
B15: https://agent-admin.paveapi.com/inspectionView/AMWT-DQYDI0XVDF?activeTab=past-sessions | C15: 1FTBR3X89LKA28805 | D15: US | E15: 2020 | F15: Ford | G15: TRANSIT | H15: KRUS | I15: DXH1 | J15: DSP Accounts | K15: KRUS | L15: KRUS | M15: AMWT-DQYDI0XVDF | N15: Fleet Improvement Fund | O15: COMPLETE | P15: https://dashboard.paveapi.com/park/AMWT-DQYDI0XVDF/?l=en | Q15: 46143.873 | R15: 46143.877 | S15: 313 | T15: 46143.895 | U15: 1923 | V15: 2 | W15: 2075 | X15: 0 | Y15: 1 | Z15: 1 | AA15: 0 | AB15: 1 | AC15: 0 | AD15: 2 | AE15: 0 | AF15: USD | AG15: FALSE | AH15: FALSE | AI15: FALSE | AJ15: FALSE | AK15: FALSE | AL15: FALSE | AM15: View 7: Remove wrong damages. / Correct one. | AN15: 46143 | AO15: AMWT-DQYDI0XVDF | AT15: TRUE | AU15: FALSE | AV15: FALSE
B16: https://agent-admin.paveapi.com/inspectionView/AMWT-KJMUSXZ7TY?activeTab=past-sessions | C16: 1FTBR3X89LKA28805 | D16: US | E16: 2020 | F16: Ford | G16: TRANSIT | H16: KRUS | I16: DXH1 | J16: DSP Accounts | K16: KRUS | L16: KRUS | M16: AMWT-KJMUSXZ7TY | N16: Fleet Improvement Fund | O16: COMPLETE | P16: https://dashboard.paveapi.com/park/AMWT-KJMUSXZ7TY/?l=en | Q16: 46143.906 | R16: 46143.911 | S16: 390 | T16: 46143.928 | U16: 1929 | V16: 2 | W16: 2075 | X16: 0 | Y16: 1 | Z16: 1 | AA16: 0 | AB16: 1 | AC16: 0 | AD16: 2 | AE16: 0 | AF16: USD | AG16: FALSE | AH16: FALSE | AI16: FALSE | AJ16: FALSE | AK16: FALSE | AL16: FALSE | AN16: 46143 | AO16: AMWT-KJMUSXZ7TY | AT16: TRUE | AU16: FALSE | AV16: FALSE
B17: https://agent-admin.paveapi.com/inspectionView/AMWT-JBR590RVH4?activeTab=past-sessions | C17: 1FTYR3XM7KKB12644 | D17: US | E17: 2019 | F17: Ford | G17: Transit | H17: AMZL | I17: AMZL | J17: DSP Accounts | K17: AMZL | L17: Hussein94577 | M17: AMWT-JBR590RVH4 | N17: Fleet Improvement Fund | O17: COMPLETE | P17: https://dashboard.paveapi.com/park/AMWT-JBR590RVH4/?l=en | Q17: 46143.835 | R17: 46143.837 | S17: 181 | T17: 46143.84 | U17: 252511 | V17: 3 | W17: 2310 | X17: 2 | Y17: 1 | Z17: 0 | AA17: 0 | AB17: 1 | AC17: 0 | AD17: 0 | AE17: 0 | AF17: USD | AG17: FALSE | AH17: FALSE | AI17: FALSE | AJ17: FALSE | AK17: FALSE | AL17: FALSE | AM17: / Correct one. | AN17: 46143 | AO17: AMWT-JBR590RVH4 | AT17: TRUE | AU17: FALSE | AV17: FALSE
B18: https://agent-admin.paveapi.com/inspectionView/AMWT-BYBSVJ7MTV?activeTab=past-sessions | C18: 1FTYR3XM7KKB12644 | D18: US | E18: 2019 | F18: Ford | G18: Transit | H18: AMZL | I18: AMZL | J18: DSP Accounts | K18: AMZL | L18: Hussein94577 | M18: AMWT-BYBSVJ7MTV | N18: Fleet Improvement Fund | O18: COMPLETE | P18: https://dashboard.paveapi.com/park/AMWT-BYBSVJ7MTV/?l=en | Q18: 46143.863 | R18: 46143.865 | S18: 188 | T18: 46143.869 | U18: 254995 | V18: 3 | W18: 2310 | X18: 2 | Y18: 1 | Z18: 0 | AA18: 0 | AB18: 1 | AC18: 0 | AD18: 0 | AE18: 0 | AF18: USD | AG18: FALSE | AH18: FALSE | AI18: FALSE | AJ18: FALSE | AK18: FALSE | AL18: FALSE | AN18: 46143 | AO18: AMWT-BYBSVJ7MTV | AT18: TRUE | AU18: FALSE | AV18: FALSE
B19: https://agent-admin.paveapi.com/inspectionView/AMWT-MLBRUSHOFS?activeTab=past-sessions | C19: 1FTYR3XM7KKB12644 | D19: US | E19: 2019 | F19: Ford | G19: TRANSIT | H19: AMZL | I19: AMZL | J19: DSP Accounts | K19: AMZL | L19: Hussein94577 | M19: AMWT-MLBRUSHOFS | N19: Fleet Improvement Fund | O19: COMPLETE | P19: https://dashboard.paveapi.com/park/AMWT-MLBRUSHOFS/?l=en | Q19: 46143.879 | R19: 46143.881 | S19: 180 | T19: 46143.894 | U19: 1739 | V19: 4 | W19: 2235 | X19: 2 | Y19: 1 | Z19: 0 | AA19: 0 | AB19: 0 | AC19: 0 | AD19: 0 | AE19: 0 | AF19: USD | AG19: FALSE | AH19: FALSE | AI19: FALSE | AJ19: FALSE | AK19: FALSE | AL19: FALSE | AM19: View 4: Repaired. / Correct one. | AN19: 46143 | AO19: AMWT-MLBRUSHOFS | AT19: TRUE | AU19: FALSE | AV19: FALSE
B20: https://agent-admin.paveapi.com/inspectionView/AMWT-PJECSLAH7G?activeTab=past-sessions | C20: 3C6URVJG3LE136769 | D20: US | E20: 2020 | F20: Ram | G20: PROMASTER | H20: MVRK | I20: DNJ4 | J20: DSP Accounts | K20: MVRK | L20: MVRK.user | M20: AMWT-PJECSLAH7G | N20: Fleet Improvement Fund | O20: COMPLETE | P20: https://dashboard.paveapi.com/park/AMWT-PJECSLAH7G/?l=en | Q20: 46143.746 | R20: 46143.755 | S20: 700 | T20: 46143.758 | U20: 6953 | V20: 1 | W20: 12490 | X20: 9 | Y20: 3 | Z20: 12 | AA20: 0 | AB20: 1 | AC20: 0 | AD20: 1 | AE20: 0 | AF20: USD | AG20: FALSE | AH20: FALSE | AI20: FALSE | AJ20: FALSE | AK20: FALSE | AL20: FALSE | AN20: 46143 | AO20: AMWT-PJECSLAH7G | AP20: QA Wrong damage | AR20: nguyen.nguyentran | AS20: View 4: (1 2, 3, 4, 5, 6, 7, 9, 10) Damage OLD đã sửa chữa View 5: (1) Damage OLD xác định sai View 7: (1, 4, 5, 7) Damage OLD xác định sai | AT20: FALSE | AU20: TRUE | AV20: TRUE
B21: https://agent-admin.paveapi.com/inspectionView/AMWT-Q25QUFQA7Z?activeTab=past-sessions | C21: 3C6URVJG3LE136769 | D21: US | E21: 2020 | F21: Ram | G21: ProMaster | H21: MVRK | I21: DNJ4 | J21: DSP Accounts | K21: MVRK | L21: MVRK.user | M21: AMWT-Q25QUFQA7Z | N21: Fleet Improvement Fund | O21: COMPLETE | P21: https://dashboard.paveapi.com/park/AMWT-Q25QUFQA7Z/?l=en | Q21: 46143.777 | R21: 46143.788 | S21: 959 | T21: 46143.798 | U21: 2445 | V21: 2 | W21: 8980 | X21: 4 | Y21: 2 | Z21: 10 | AA21: 0 | AB21: 0 | AC21: 0 | AD21: 0 | AE21: 0 | AF21: USD | AG21: FALSE | AH21: FALSE | AI21: FALSE | AJ21: FALSE | AK21: FALSE | AL21: FALSE | AM21: View 4,5: Remove wrong damages. / Correct one. View 7: Remove wrong damages and adjust wrong name (26) / Correct one. | AN21: 46143 | AO21: AMWT-Q25QUFQA7Z | AT21: TRUE | AU21: FALSE | AV21: FALSE
B22: https://agent-admin.paveapi.com/inspectionView/AMWT-IMURJEZWXO?activeTab=past-sessions | C22: 3C6URVJG3LE136769 | D22: US | E22: 2020 | F22: Ram | G22: ProMaster | H22: MVRK | I22: DNJ4 | J22: DSP Accounts | K22: MVRK | L22: MVRK.user | M22: AMWT-IMURJEZWXO | N22: Fleet Improvement Fund | O22: COMPLETE | P22: https://dashboard.paveapi.com/park/AMWT-IMURJEZWXO/?l=en | Q22: 46143.86 | R22: 46143.861 | S22: 108 | T22: 46143.867 | U22: 2252 | V22: 2 | W22: 5512 | X22: 2 | Y22: 2 | Z22: 4 | AA22: 0 | AB22: 0 | AC22: 0 | AD22: 0 | AE22: 0 | AF22: USD | AG22: FALSE | AH22: FALSE | AI22: FALSE | AJ22: FALSE | AK22: FALSE | AL22: FALSE | AM22: View 4,7: Repaired. / Correct one. | AN22: 46143 | AO22: AMWT-IMURJEZWXO | AT22: TRUE | AU22: FALSE | AV22: FALSE
B23: https://agent-admin.paveapi.com/inspectionView/AMWT-OFS8PILHQT?activeTab=past-sessions | C23: 3C6URVJG3LE136769 | D23: US | E23: 2020 | F23: Ram | G23: ProMaster | H23: MVRK | I23: DNJ4 | J23: DSP Accounts | K23: MVRK | L23: MVRK.user | M23: AMWT-OFS8PILHQT | N23: Fleet Improvement Fund | O23: COMPLETE | P23: https://dashboard.paveapi.com/park/AMWT-OFS8PILHQT/?l=en | Q23: 46143.875 | R23: 46143.876 | S23: 126 | T23: 46143.885 | U23: 1435 | V23: 2 | W23: 4137 | X23: 2 | Y23: 2 | Z23: 3 | AA23: 0 | AB23: 0 | AC23: 0 | AD23: 0 | AE23: 0 | AF23: USD | AG23: FALSE | AH23: FALSE | AI23: FALSE | AJ23: FALSE | AK23: FALSE | AL23: FALSE | AM23: View 7: DSP covered the damage. | AN23: 46143 | AO23: AMWT-OFS8PILHQT | AT23: TRUE | AU23: FALSE | AV23: FALSE
B24: https://agent-admin.paveapi.com/inspectionView/AMWT-VR4XPMOLN5?activeTab=past-sessions | C24: 3C6URVJG3LE136769 | D24: US | E24: 2020 | F24: Ram | G24: ProMaster | H24: MVRK | I24: DNJ4 | J24: DSP Accounts | K24: MVRK | L24: MVRK.user | M24: AMWT-VR4XPMOLN5 | N24: Fleet Improvement Fund | O24: COMPLETE | P24: https://dashboard.paveapi.com/park/AMWT-VR4XPMOLN5/?l=en | Q24: 46143.89 | R24: 46143.892 | S24: 83 | T24: 46143.944 | U24: 5052 | V24: 3 | W24: 3330 | X24: 0 | Y24: 2 | Z24: 3 | AA24: 0 | AB24: 0 | AC24: 0 | AD24: 0 | AE24: 0 | AF24: USD | AG24: FALSE | AH24: FALSE | AI24: FALSE | AJ24: FALSE | AK24: FALSE | AL24: FALSE | AM24: View 4,7: Repaired. / Correct one. | AN24: 46143 | AO24: AMWT-VR4XPMOLN5 | AT24: TRUE | AU24: FALSE | AV24: FALSE
B25: https://agent-admin.paveapi.com/inspectionView/AMWT-M5TYMRIXHD?activeTab=past-sessions | C25: 3C6URVJG3LE136769 | D25: US | E25: 2020 | F25: Ram | G25: PROMASTER | H25: MVRK | I25: DNJ4 | J25: DSP Accounts | K25: MVRK | L25: MVRK.user | M25: AMWT-M5TYMRIXHD | N25: Fleet Improvement Fund | O25: COMPLETE | P25: https://dashboard.paveapi.com/park/AMWT-M5TYMRIXHD/?l=en | Q25: 46143.914 | R25: 46143.915 | S25: 120 | T25: 46143.952 | U25: 3746 | V25: 3 | W25: 3330 | X25: 0 | Y25: 2 | Z25: 3 | AA25: 0 | AB25: 0 | AC25: 0 | AD25: 0 | AE25: 0 | AF25: USD | AG25: FALSE | AH25: FALSE | AI25: FALSE | AJ25: FALSE | AK25: FALSE | AL25: FALSE | AN25: 46143 | AO25: AMWT-M5TYMRIXHD | AT25: TRUE | AU25: FALSE | AV25: FALSE
B26: https://agent-admin.paveapi.com/inspectionView/AMRR-PAO74CSSAJ?activeTab=past-sessions | C26: 3C6URVJG7LE140520 | D26: US | E26: 2020 | F26: Ram | G26: ProMaster | H26: MLKT | I26: WSC2 | J26: DSP Accounts | K26: MLKT | L26: lpolanco.mklt | M26: AMRR-PAO74CSSAJ | N26: Redeployment/Retirement | O26: COMPLETE | P26: https://dashboard.paveapi.com/park/AMRR-PAO74CSSAJ/?l=en | Q26: 46143.492 | R26: 46143.493 | S26: 124 | T26: 46143.496 | U26: 857 | V26: 2 | W26: 4060 | X26: 3 | Y26: 0 | Z26: 2 | AA26: 0 | AB26: 0 | AC26: 0 | AD26: 0 | AE26: 0 | AF26: USD | AG26: FALSE | AH26: FALSE | AI26: FALSE | AJ26: FALSE | AK26: FALSE | AL26: FALSE | AN26: 46143 | AO26: AMRR-PAO74CSSAJ | AT26: TRUE | AU26: FALSE | AV26: FALSE
B27: https://agent-admin.paveapi.com/inspectionView/AMWT-CCI6FFYO7W?activeTab=past-sessions | C27: 3C6URVJG7LE140520 | D27: US | E27: 2020 | F27: Ram | G27: PROMASTER | H27: MLKT | I27: WSC2 | J27: DSP Accounts | K27: MLKT | L27: lpolanco.mklt | M27: AMWT-CCI6FFYO7W | N27: Wear & Tear | O27: COMPLETE | P27: https://dashboard.paveapi.com/park/AMWT-CCI6FFYO7W/?l=en | Q27: 46143.495 | R27: 46143.497 | S27: 161 | T27: 46143.501 | U27: 1262 | V27: 2 | W27: 3360 | X27: 2 | Y27: 0 | Z27: 2 | AA27: 0 | AB27: 0 | AC27: 0 | AD27: 0 | AE27: 0 | AF27: USD | AG27: FALSE | AH27: FALSE | AI27: FALSE | AJ27: FALSE | AK27: FALSE | AL27: FALSE | AM27: View 4: Remove false positive damage. / Correct one. | AN27: 46143 | AO27: AMWT-CCI6FFYO7W | AT27: TRUE | AU27: FALSE | AV27: FALSE
B28: https://agent-admin.paveapi.com/inspectionView/AMWT-MIS6K6ORQ0?activeTab=past-sessions | C28: 7FCEHDB70NN005199 | D28: US | E28: 2022 | F28: Rivian | G28: Delivery | H28: CFDL | I28: DCL5 | J28: DSP Accounts | K28: CFDL | L28: JeffZ | M28: AMWT-MIS6K6ORQ0 | N28: Wear & Tear | O28: COMPLETE | P28: https://dashboard.paveapi.com/park/AMWT-MIS6K6ORQ0/?l=en | Q28: 46143.761 | R28: 46143.763 | S28: 139 | T28: 46143.766 | U28: 452 | V28: 2 | W28: 2215 | X28: 1 | Y28: 1 | Z28: 0 | AA28: 0 | AB28: 0 | AC28: 0 | AD28: 0 | AE28: 0 | AF28: USD | AG28: FALSE | AH28: FALSE | AI28: FALSE | AJ28: FALSE | AK28: FALSE | AL28: FALSE | AN28: 46143 | AO28: AMWT-MIS6K6ORQ0 | AS28: Hình tối | AT28: FALSE | AU28: TRUE | AV28: FALSE
B29: https://agent-admin.paveapi.com/inspectionView/AMWT-V5GYMWQ1SJ?activeTab=past-sessions | C29: 7FCEHDB70NN005199 | D29: US | E29: 2022 | F29: Rivian | G29: Delivery | H29: CFDL | I29: DCL5 | J29: DSP Accounts | K29: CFDL | L29: JeffZ | M29: AMWT-V5GYMWQ1SJ | N29: Wear & Tear | O29: COMPLETE | P29: https://dashboard.paveapi.com/park/AMWT-V5GYMWQ1SJ/?l=en | Q29: 46143.78 | R29: 46143.781 | S29: 130 | T29: 46143.784 | U29: 433 | V29: 5 | W29: 0 | X29: 0 | Y29: 0 | Z29: 0 | AA29: 0 | AB29: 0 | AC29: 0 | AD29: 0 | AE29: 0 | AF29: USD | AG29: FALSE | AH29: FALSE | AI29: FALSE | AJ29: FALSE | AK29: FALSE | AL29: FALSE | AM29: View 4,5: Remove false positive damages. / Correct one. | AN29: 46143 | AO29: AMWT-V5GYMWQ1SJ | AT29: TRUE | AU29: FALSE | AV29: FALSE
B30: https://agent-admin.paveapi.com/inspectionView/AMWT-9S6TPCCG8I?activeTab=past-sessions | C30: 7FCEHDB73NN000806 | D30: US | E30: 2022 | F30: Rivian | G30: Delivery | H30: SGLT | I30: DTU7 | J30: DSP Accounts | K30: SGLT | L30: SGLT.user | M30: AMWT-9S6TPCCG8I | N30: Fleet Improvement Fund | O30: COMPLETE | P30: https://dashboard.paveapi.com/park/AMWT-9S6TPCCG8I/?l=en | Q30: 46143.627 | R30: 46143.63 | S30: 182 | T30: 46143.632 | U30: 515 | V30: 2 | W30: 2100 | X30: 0 | Y30: 0 | Z30: 12 | AA30: 0 | AB30: 0 | AC30: 0 | AD30: 3 | AE30: 0 | AF30: USD | AG30: FALSE | AH30: FALSE | AI30: FALSE | AJ30: FALSE | AK30: FALSE | AL30: FALSE | AN30: 46143 | AO30: AMWT-9S6TPCCG8I | AP30: QA Wrong damage | AR30: uyen.tran | AS30: View 7: Damage OLD đã sửa chữa | AT30: FALSE | AU30: TRUE | AV30: TRUE
B31: https://agent-admin.paveapi.com/inspectionView/AMWT-RBSXDSQNMQ?activeTab=past-sessions | C31: 7FCEHDB73NN000806 | D31: US | E31: 2022 | F31: Rivian | G31: Delivery | H31: SGLT | I31: DTU7 | J31: DSP Accounts | K31: SGLT | L31: SGLT.user | M31: AMWT-RBSXDSQNMQ | N31: Fleet Improvement Fund | O31: COMPLETE | P31: https://dashboard.paveapi.com/park/AMWT-RBSXDSQNMQ/?l=en | Q31: 46143.636 | R31: 46143.637 | S31: 83 | T31: 46143.644 | U31: 801 | V31: 5 | W31: 0 | X31: 0 | Y31: 0 | Z31: 0 | AA31: 0 | AB31: 0 | AC31: 0 | AD31: 0 | AE31: 0 | AF31: USD | AG31: FALSE | AH31: FALSE | AI31: FALSE | AJ31: FALSE | AK31: FALSE | AL31: FALSE | AM31: View 7: Remove wrong damages. / Correct one. | AN31: 46143 | AO31: AMWT-RBSXDSQNMQ | AT31: TRUE | AU31: FALSE | AV31: FALSE
B32: https://agent-admin.paveapi.com/inspectionView/AMWT-AUCGARQFGH?activeTab=past-sessions | C32: 7FCEHEB21RN017183 | D32: US | E32: 2024 | F32: Rivian | G32: Delivery | H32: KJQY | I32: DRO2 | J32: DSP Accounts | K32: KJQY | L32: mitch.kjqy | M32: AMWT-AUCGARQFGH | N32: Fleet Improvement Fund | O32: COMPLETE | P32: https://dashboard.paveapi.com/park/AMWT-AUCGARQFGH/?l=en | Q32: 46143.436 | R32: 46143.437 | S32: 77 | T32: 46143.44 | U32: 404 | V32: 2 | W32: 4835 | X32: 2 | Y32: 3 | Z32: 13 | AA32: 0 | AB32: 2 | AC32: 0 | AD32: 3 | AE32: 0 | AF32: USD | AG32: FALSE | AH32: FALSE | AI32: FALSE | AJ32: FALSE | AK32: FALSE | AL32: FALSE | AN32: 46143 | AO32: AMWT-AUCGARQFGH | AT32: TRUE | AU32: FALSE | AV32: FALSE
B33: https://agent-admin.paveapi.com/inspectionView/AMWT-0C0GCQESDA?activeTab=past-sessions | C33: 7FCEHEB21RN017183 | D33: US | E33: 2024 | F33: Rivian | G33: DELIVERY | H33: KJQY | I33: DRO2 | J33: DSP Accounts | K33: KJQY | L33: mitch.kjqy | M33: AMWT-0C0GCQESDA | N33: Fleet Improvement Fund | O33: COMPLETE | P33: https://dashboard.paveapi.com/park/AMWT-0C0GCQESDA/?l=en | Q33: 46143.46 | R33: 46143.461 | S33: 77 | T33: 46143.465 | U33: 541 | V33: 3 | W33: 4662.5 | X33: 2 | Y33: 3 | Z33: 9 | AA33: 0 | AB33: 2 | AC33: 0 | AD33: 3 | AE33: 0 | AF33: USD | AG33: FALSE | AH33: FALSE | AI33: FALSE | AJ33: FALSE | AK33: FALSE | AL33: FALSE | AM33: View 7: Repaired. / Correct one. | AN33: 46143 | AO33: AMWT-0C0GCQESDA | AT33: TRUE | AU33: FALSE | AV33: FALSE
B34: https://agent-admin.paveapi.com/inspectionView/AMWT-KLPD5NL05J?activeTab=past-sessions | C34: 7FCEHEB22TN042939 | D34: US | E34: 2026 | F34: RIVIAN | G34: EDV | H34: ANKR | I34: DNJ7 | J34: DSP Accounts | K34: ANKR | M34: AMWT-KLPD5NL05J | N34: Wear & Tear | O34: COMPLETE | P34: https://dashboard.paveapi.com/park/AMWT-KLPD5NL05J/?l=en | Q34: 46143.531 | R34: 46143.533 | S34: 29 | T34: 46143.535 | U34: 463 | V34: 5 | W34: 0 | X34: 0 | Y34: 0 | Z34: 0 | AA34: 0 | AB34: 0 | AC34: 0 | AD34: 0 | AE34: 0 | AF34: USD | AG34: FALSE | AH34: FALSE | AI34: FALSE | AJ34: FALSE | AK34: FALSE | AL34: FALSE | AN34: 46143 | AO34: AMWT-KLPD5NL05J | AP34: QA Miss Damage | AR34: phu.nguyenhoang | AS34: View 8: BROKEN MAJOR - LIGHT TAIL LEFT | AT34: FALSE | AU34: TRUE | AV34: TRUE
B35: https://agent-admin.paveapi.com/inspectionView/AMWT-UXBCEOEFN1?activeTab=past-sessions | C35: 7FCEHEB22TN042939 | D35: US | E35: 2026 | F35: RIVIAN | G35: EDV | H35: ANKR | I35: DNJ7 | J35: DSP Accounts | K35: ANKR | M35: AMWT-UXBCEOEFN1 | N35: Fleet Improvement Fund | O35: COMPLETE | P35: https://dashboard.paveapi.com/park/AMWT-UXBCEOEFN1/?l=en | Q35: 46143.534 | R35: 46143.534 | S35: 46 | T35: 46143.541 | U35: 714 | V35: 5 | W35: 0 | X35: 0 | Y35: 0 | Z35: 0 | AA35: 0 | AB35: 0 | AC35: 0 | AD35: 0 | AE35: 0 | AF35: USD | AG35: FALSE | AH35: FALSE | AI35: FALSE | AJ35: FALSE | AK35: FALSE | AL35: FALSE | AN35: 46143 | AO35: AMWT-UXBCEOEFN1 | AT35: TRUE | AU35: FALSE | AV35: FALSE
B36: https://agent-admin.paveapi.com/inspectionView/AMWT-JDL0BNOD12?activeTab=past-sessions | C36: 5PVNJ7AV3N5T50187 | M36: AMWT-JDL0BNOD12 | AN36: 46143 | AO36: AMWT-JDL0BNOD12 | AP36: QA Miss Damage | AR36: tan.pham | AS36: View 5 : MISSING MAJOR - RIGHT SIDE FRONT CAB CORNER MOLDING | AT36: FALSE | AU36: TRUE | AV36: TRUE
A37: 0502-1hrs_NA | B37: https://agent-admin.paveapi.com/inspectionView/AMWT-1LAEWCDCAR?activeTab=past-sessions | C37: 1FTBR3X82MKA55958 | D37: US | E37: 2021 | F37: Ford | G37: Transit | H37: AUML | I37: HCH4 | J37: DSP Accounts | K37: AUML | L37: AUML.user | M37: AMWT-1LAEWCDCAR | N37: Wear & Tear | O37: COMPLETE | P37: https://dashboard.paveapi.com/park/AMWT-1LAEWCDCAR/?l=en | Q37: 46144.641 | R37: 46144.643 | S37: 155 | T37: 46144.646 | U37: 9216388 | V37: 3 | W37: 3387.5 | X37: 1 | Y37: 0 | Z37: 2 | AA37: 0 | AB37: 0 | AC37: 0 | AD37: 0 | AE37: 0 | AF37: USD | AG37: FALSE | AH37: FALSE | AI37: FALSE | AJ37: FALSE | AK37: FALSE | AL37: FALSE | AN37: 46144 | AO37: AMWT-1LAEWCDCAR | AT37: TRUE | AU37: FALSE | AV37: FALSE
B38: https://agent-admin.paveapi.com/inspectionView/AMWT-3E9EQPWOBS?activeTab=past-sessions | C38: 1FTBR3X82MKA55958 | D38: US | E38: 2021 | F38: Ford | G38: Transit | H38: AUML | I38: HCH4 | J38: DSP Accounts | K38: AUML | L38: AUML.user | M38: AMWT-3E9EQPWOBS | N38: Wear & Tear | O38: COMPLETE | P38: https://dashboard.paveapi.com/park/AMWT-3E9EQPWOBS/?l=en | Q38: 46144.644 | R38: 46144.645 | S38: 79 | T38: 46144.651 | U38: 14665 | V38: 3 | W38: 2437.5 | X38: 1 | Y38: 0 | Z38: 1 | AA38: 0 | AB38: 0 | AC38: 0 | AD38: 0 | AE38: 0 | AF38: USD | AG38: FALSE | AH38: FALSE | AI38: FALSE | AJ38: FALSE | AK38: FALSE | AL38: FALSE | AM38: View 7: Remove false positive damages. / Correct one. | AN38: 46144 | AO38: AMWT-3E9EQPWOBS | AT38: TRUE | AU38: FALSE | AV38: FALSE
B39: https://agent-admin.paveapi.com/inspectionView/AMWT-HZC42UEZLC?activeTab=past-sessions | C39: 3C6MRVJG7ME535539 | D39: US | E39: 2021 | F39: Ram | G39: ProMaster | H39: MNNA | I39: DCM5 | J39: DSP Accounts | K39: MNNA | L39: MESDispatch | M39: AMWT-HZC42UEZLC | N39: Wear & Tear | O39: COMPLETE | P39: https://dashboard.paveapi.com/park/AMWT-HZC42UEZLC/?l=en | Q39: 46144.726 | R39: 46144.729 | S39: 234 | T39: 46144.735 | U39: 905 | V39: 2 | W39: 4997.5 | X39: 1 | Y39: 2 | Z39: 4 | AA39: 2 | AB39: 0 | AC39: 0 | AD39: 0 | AE39: 0 | AF39: USD | AG39: FALSE | AH39: FALSE | AI39: FALSE | AJ39: FALSE | AK39: FALSE | AL39: FALSE | AN39: 46144 | AO39: AMWT-HZC42UEZLC | AP39: Agent + QA Wrong damage | AQ39: anh.le | AR39: huy.tran | AS39: View 7: (2, 3, 4) Damage OLD đã sửa chữa View 8: Hình tối -> skip | AT39: FALSE | AU39: TRUE | AV39: FALSE
B40: https://agent-admin.paveapi.com/inspectionView/AMWT-CLLIKUKPNM?activeTab=past-sessions | C40: 3C6MRVJG7ME535539 | D40: US | E40: 2021 | F40: Ram | G40: ProMaster | H40: MNNA | I40: DCM5 | J40: DSP Accounts | K40: MNNA | L40: MESDispatch | M40: AMWT-CLLIKUKPNM | N40: Wear & Tear | O40: COMPLETE | P40: https://dashboard.paveapi.com/park/AMWT-CLLIKUKPNM/?l=en | Q40: 46144.742 | R40: 46144.745 | S40: 209 | T40: 46144.749 | U40: 668 | V40: 4 | W40: 1137.5 | X40: 1 | Y40: 1 | Z40: 1 | AA40: 0 | AB40: 0 | AC40: 0 | AD40: 0 | AE40: 0 | AF40: USD | AG40: FALSE | AH40: FALSE | AI40: FALSE | AJ40: FALSE | AK40: FALSE | AL40: FALSE | AM40: View 5, 7, 8: Remove false positive damages. / Correct one. | AN40: 46144 | AO40: AMWT-CLLIKUKPNM | AP40: QA Wrong damage | AR40: huyhien.nguyen | AS40: View 5: (2) Xóa sai damage | AT40: FALSE | AU40: TRUE | AV40: FALSE
B41: https://agent-admin.paveapi.com/inspectionView/AMWT-6EQZRBLF94?activeTab=past-sessions | C41: 3C6MRVJGXME544767 | D41: US | E41: 2021 | F41: Ram | G41: ProMaster | H41: NOLG | I41: DGT8 | J41: DSP Accounts | K41: NOLG | L41: yogebear | M41: AMWT-6EQZRBLF94 | N41: Wear & Tear | O41: COMPLETE | P41: https://dashboard.paveapi.com/park/AMWT-6EQZRBLF94/?l=en | Q41: 46144.808 | R41: 46144.809 | S41: 93 | T41: 46144.812 | U41: 408 | V41: 2 | W41: 3667.5 | X41: 0 | Y41: 4 | Z41: 3 | AA41: 1 | AB41: 0 | AC41: 0 | AD41: 1 | AE41: 0 | AF41: USD | AG41: FALSE | AH41: FALSE | AI41: TRUE | AJ41: FALSE | AK41: FALSE | AL41: FALSE | AN41: 46144 | AO41: AMWT-6EQZRBLF94 | AP41: QA Wrong damage | AR41: nhi.le | AS41: View 5: (3, 4) Damage OLD xác định sai | AT41: FALSE | AU41: TRUE | AV41: FALSE
B42: https://agent-admin.paveapi.com/inspectionView/AMWT-EPQ03UNK2O?activeTab=past-sessions | C42: 3C6MRVJGXME544767 | D42: US | E42: 2021 | F42: Ram | G42: ProMaster | H42: NOLG | I42: DGT8 | J42: DSP Accounts | K42: NOLG | L42: yogebear | M42: AMWT-EPQ03UNK2O | N42: Fleet Improvement Fund | O42: COMPLETE | P42: https://dashboard.paveapi.com/park/AMWT-EPQ03UNK2O/?l=en | Q42: 46144.81 | R42: 46144.811 | S42: 82 | T42: 46144.819 | U42: 877 | V42: 2 | W42: 2545 | X42: 0 | Y42: 4 | Z42: 1 | AA42: 1 | AB42: 0 | AC42: 0 | AD42: 1 | AE42: 0 | AF42: USD | AG42: FALSE | AH42: FALSE | AI42: TRUE | AJ42: FALSE | AK42: FALSE | AL42: FALSE | AM42: View 7: Remove false positive damages. / Correct one. | AN42: 46144 | AO42: AMWT-EPQ03UNK2O | AT42: TRUE | AU42: FALSE | AV42: FALSE
B43: https://agent-admin.paveapi.com/inspectionView/AMUO-HYBJTG5MJE?activeTab=past-sessions | C43: 3C6URVJG5LE144369 | D43: US | E43: 2020 | F43: Ram | G43: ProMaster | H43: AMFU | I43: WIL5 | J43: Last Mile Rentals | K43: AMFU | M43: AMUO-HYBJTG5MJE | N43: Merchants_LMR_rtinsp | O43: COMPLETE | P43: https://dashboard.paveapi.com/park/AMUO-HYBJTG5MJE/?l=en | Q43: 46144.586 | R43: 46144.59 | S43: 280 | T43: 46144.595 | U43: 869 | V43: 4 | W43: 2035 | X43: 1 | Y43: 2 | Z43: 0 | AA43: 1 | AB43: 0 | AC43: 0 | AD43: 0 | AE43: 0 | AF43: USD | AG43: FALSE | AH43: FALSE | AI43: FALSE | AJ43: FALSE | AK43: FALSE | AL43: FALSE | AN43: 46144 | AO43: AMUO-HYBJTG5MJE | AT43: TRUE | AU43: FALSE | AV43: FALSE
B44: https://agent-admin.paveapi.com/inspectionView/AMUO-NTFAESA63L?activeTab=past-sessions | C44: 3C6URVJG5LE144369 | D44: US | E44: 2020 | F44: Ram | G44: ProMaster | H44: AMFU | I44: WIL5 | J44: Last Mile Rentals | K44: AMFU | M44: AMUO-NTFAESA63L | N44: Merchants_LMR_rtinsp | O44: COMPLETE | P44: https://dashboard.paveapi.com/park/AMUO-NTFAESA63L/?l=en | Q44: 46144.595 | R44: 46144.602 | S44: 464 | T44: 46144.61 | U44: 1329 | V44: 4 | W44: 1410 | X44: 1 | Y44: 1 | Z44: 0 | AA44: 1 | AB44: 0 | AC44: 0 | AD44: 0 | AE44: 0 | AF44: USD | AG44: FALSE | AH44: FALSE | AI44: TRUE | AJ44: FALSE | AK44: FALSE | AL44: FALSE | AM44: View 5: Remove false positive damages. / Correct one. | AN44: 46144 | AO44: AMUO-NTFAESA63L | AS44: Hình tối & còn dent mà hơi nhỏ nên xóa cũng ok | AT44: TRUE | AU44: FALSE | AV44: FALSE
B45: https://agent-admin.paveapi.com/inspectionView/AMWT-HFRFXRXH1R?activeTab=past-sessions | C45: 3C6URVJG6KE554547 | D45: US | E45: 2019 | F45: Ram | G45: ProMaster | H45: AZOO | I45: DMP4 | J45: DSP Accounts | K45: AZOO | L45: AZOO.user | M45: AMWT-HFRFXRXH1R | N45: Fleet Improvement Fund | O45: COMPLETE | P45: https://dashboard.paveapi.com/park/AMWT-HFRFXRXH1R/?l=en | Q45: 46144.849 | R45: 46144.851 | S45: 121 | T45: 46144.859 | U45: 1753 | V45: 1 | W45: 13202.5 | X45: 8 | Y45: 6 | Z45: 13 | AA45: 9 | AB45: 3 | AC45: 0 | AD45: 2 | AE45: 1 | AF45: USD | AG45: FALSE | AH45: FALSE | AI45: FALSE | AJ45: FALSE | AK45: FALSE | AL45: FALSE | AN45: 46144 | AO45: AMWT-HFRFXRXH1R | AP45: Agent + QA Wrong damage | AQ45: vi.votuan | AR45: tho.nh | AS45: View 5: (1, 3, 4) Damage OLD đặt sai vị trí View 4: (10) Damage OLD xác định sai | AT45: FALSE | AU45: TRUE | AV45: FALSE
B46: https://agent-admin.paveapi.com/inspectionView/AMWT-TBZ9ITU8SO?activeTab=past-sessions | C46: 3C6URVJG6KE554547 | D46: US | E46: 2019 | F46: Ram | G46: ProMaster | H46: AZOO | I46: DMP4 | J46: DSP Accounts | K46: AZOO | L46: AZOO.user | M46: AMWT-TBZ9ITU8SO | N46: Fleet Improvement Fund | O46: COMPLETE | P46: https://dashboard.paveapi.com/park/AMWT-TBZ9ITU8SO/?l=en | Q46: 46144.887 | R46: 46144.889 | S46: 112 | T46: 46144.9 | U46: 5287 | V46: 1 | W46: 12515 | X46: 5 | Y46: 3 | Z46: 13 | AA46: 9 | AB46: 3 | AC46: 0 | AD46: 0 | AE46: 1 | AF46: USD | AG46: FALSE | AH46: FALSE | AI46: FALSE | AJ46: FALSE | AK46: FALSE | AL46: FALSE | AM46: View 4, 7: Remove false positive damages. View 5: Repaired. / Correct one. | AN46: 46144 | AO46: AMWT-TBZ9ITU8SO | AT46: TRUE | AU46: FALSE | AV46: FALSE
B47: https://agent-admin.paveapi.com/inspectionView/AMWT-DYHAGKERUB?activeTab=past-sessions | C47: 3C7WRVMG2NE117407 | D47: US | E47: 2022 | F47: Ram | G47: ProMaster | H47: LITE | I47: DMO4 | J47: DSP Accounts | K47: LITE | L47: LITE.user | M47: AMWT-DYHAGKERUB | N47: Fleet Improvement Fund | O47: COMPLETE | P47: https://dashboard.paveapi.com/park/AMWT-DYHAGKERUB/?l=en | Q47: 46144.778 | R47: 46144.78 | S47: 131 | T47: 46144.782 | U47: 446084 | V47: 3 | W47: 2387.5 | X47: 1 | Y47: 1 | Z47: 2 | AA47: 0 | AB47: 2 | AC47: 0 | AD47: 3 | AE47: 0 | AF47: USD | AG47: FALSE | AH47: FALSE | AI47: TRUE | AJ47: FALSE | AK47: FALSE | AL47: FALSE | AN47: 46144 | AO47: AMWT-DYHAGKERUB | AP47: QA Wrong damage | AR47: vi.votuan | AS47: View 5: (1) Damage OLD xác định sai | AT47: FALSE | AU47: TRUE | AV47: FALSE
B48: https://agent-admin.paveapi.com/inspectionView/AMWT-IFVDBHYQY7?activeTab=past-sessions | C48: 3C7WRVMG2NE117407 | D48: US | E48: 2022 | F48: Ram | G48: ProMaster | H48: LITE | I48: DMO4 | J48: DSP Accounts | K48: LITE | L48: LITE.user | M48: AMWT-IFVDBHYQY7 | N48: Fleet Improvement Fund | O48: COMPLETE | P48: https://dashboard.paveapi.com/park/AMWT-IFVDBHYQY7/?l=en | Q48: 46144.781 | R48: 46144.783 | S48: 136 | T48: 46144.788 | U48: 446743 | V48: 3 | W48: 1700 | X48: 1 | Y48: 0 | Z48: 2 | AA48: 0 | AB48: 2 | AC48: 0 | AD48: 3 | AE48: 0 | AF48: USD | AG48: FALSE | AH48: FALSE | AI48: TRUE | AJ48: FALSE | AK48: FALSE | AL48: FALSE | AM48: View 5: Remove false positive damages. / Correct one. | AN48: 46144 | AO48: AMWT-IFVDBHYQY7 | AT48: TRUE | AU48: FALSE | AV48: FALSE
B49: https://agent-admin.paveapi.com/inspectionView/AMWT-ZMD7R4MTK4?activeTab=past-sessions | C49: 7FCEHEB21RN017197 | D49: US | E49: 2024 | F49: Rivian | G49: DELIVERY | H49: KJQY | I49: DRO2 | J49: DSP Accounts | K49: KJQY | L49: mitch.kjqy | M49: AMWT-ZMD7R4MTK4 | N49: Fleet Improvement Fund | O49: COMPLETE | P49: https://dashboard.paveapi.com/park/AMWT-ZMD7R4MTK4/?l=en | Q49: 46144.45 | R49: 46144.451 | S49: 63 | T49: 46144.453 | U49: 406 | V49: 2 | W49: 4160 | X49: 1 | Y49: 0 | Z49: 6 | AA49: 2 | AB49: 1 | AC49: 0 | AD49: 1 | AE49: 0 | AF49: USD | AG49: FALSE | AH49: FALSE | AI49: FALSE | AJ49: FALSE | AK49: FALSE | AL49: FALSE | AN49: 46144 | AO49: AMWT-ZMD7R4MTK4 | AP49: QA Wrong damage | AR49: mai.luungoc | AS49: View 7: (11) Damage OLD đã sửa chữa | AT49: FALSE | AU49: TRUE | AV49: TRUE
B50: https://agent-admin.paveapi.com/inspectionView/AMWT-24KSPBEQEN?activeTab=past-sessions | C50: 7FCEHEB21RN017197 | D50: US | E50: 2024 | F50: Rivian | G50: Delivery | H50: KJQY | I50: DRO2 | J50: DSP Accounts | K50: KJQY | L50: mitch.kjqy | M50: AMWT-24KSPBEQEN | N50: Fleet Improvement Fund | O50: COMPLETE | P50: https://dashboard.paveapi.com/park/AMWT-24KSPBEQEN/?l=en | Q50: 46144.456 | R50: 46144.458 | S50: 107 | T50: 46144.46 | U50: 455 | V50: 2 | W50: 3472.5 | X50: 1 | Y50: 0 | Z50: 5 | AA50: 1 | AB50: 1 | AC50: 0 | AD50: 1 | AE50: 0 | AF50: USD | AG50: FALSE | AH50: FALSE | AI50: FALSE | AJ50: FALSE | AK50: FALSE | AL50: FALSE | AM50: View 7: Remove wrong damage. View 8: Repaired. / Correct one. | AN50: 46144 | AO50: AMWT-24KSPBEQEN | AT50: TRUE | AU50: FALSE | AV50: FALSE
B51: https://agent-admin.paveapi.com/inspectionView/AMWT-IO9MXZFRQT?activeTab=past-sessions | C51: 7FCEHEB56PN001746 | D51: US | E51: 2023 | F51: Rivian | G51: Delivery | H51: SRPL | I51: DUT5 | J51: DSP Accounts | K51: SRPL | L51: SRPL.user | M51: AMWT-IO9MXZFRQT | N51: Fleet Improvement Fund | O51: COMPLETE | P51: https://dashboard.paveapi.com/park/AMWT-IO9MXZFRQT/?l=en | Q51: 46144.976 | R51: 46144.978 | S51: 123 | T51: 46144.981 | U51: 429 | V51: 2 | W51: 2372.5 | X51: 0 | Y51: 2 | Z51: 2 | AA51: 2 | AB51: 0 | AC51: 0 | AD51: 0 | AE51: 0 | AF51: USD | AG51: FALSE | AH51: FALSE | AI51: FALSE | AJ51: FALSE | AK51: FALSE | AL51: FALSE | AM51: / Correct one. | AN51: 46144 | AO51: AMWT-IO9MXZFRQT | AT51: TRUE | AU51: FALSE | AV51: FALSE
B52: https://agent-admin.paveapi.com/inspectionView/AMWT-TBONCIABAH?activeTab=past-sessions | C52: 7FCEHEB56PN001746 | D52: US | E52: 2023 | F52: Rivian | G52: Delivery | H52: SRPL | I52: DUT5 | J52: DSP Accounts | K52: SRPL | L52: SRPL.user | M52: AMWT-TBONCIABAH | N52: Fleet Improvement Fund | O52: COMPLETE | P52: https://dashboard.paveapi.com/park/AMWT-TBONCIABAH/?l=en | Q52: 46145.01 | R52: 46145.013 | S52: 146 | T52: 46145.017 | U52: 684 | V52: 2 | W52: 1672.5 | X52: 0 | Y52: 2 | Z52: 1 | AA52: 2 | AB52: 0 | AC52: 0 | AD52: 0 | AE52: 0 | AF52: USD | AG52: FALSE | AH52: FALSE | AI52: FALSE | AJ52: FALSE | AK52: FALSE | AL52: FALSE | AM52: View 7: Repaired. / Correct one. | AN52: 46144 | AO52: AMWT-TBONCIABAH | AT52: TRUE | AU52: FALSE | AV52: FALSE
B53: https://agent-admin.paveapi.com/inspectionView/AMWT-KNDZBKZGK1?activeTab=past-sessions | C53: 7FCEHEB70PN010539 | D53: US | E53: 2023 | F53: Rivian | G53: Delivery | H53: NOLG | I53: DGT8 | J53: DSP Accounts | K53: NOLG | L53: yogebear | M53: AMWT-KNDZBKZGK1 | N53: Wear & Tear | O53: COMPLETE | P53: https://dashboard.paveapi.com/park/AMWT-KNDZBKZGK1/?l=en | Q53: 46144.708 | R53: 46144.709 | S53: 131 | T53: 46144.713 | U53: 626 | V53: 1 | W53: 10865 | X53: 5 | Y53: 2 | Z53: 3 | AA53: 7 | AB53: 0 | AC53: 1 | AD53: 0 | AE53: 0 | AF53: USD | AG53: FALSE | AH53: FALSE | AI53: FALSE | AJ53: FALSE | AK53: FALSE | AL53: FALSE | AN53: 46144 | AO53: AMWT-KNDZBKZGK1 | AS53: Hình tối | AT53: TRUE | AU53: FALSE | AV53: FALSE
B54: https://agent-admin.paveapi.com/inspectionView/AMWT-MVZG7I2NR3?activeTab=past-sessions | C54: 7FCEHEB70PN010539 | D54: US | E54: 2023 | F54: Rivian | G54: Delivery | H54: NOLG | I54: DGT8 | J54: DSP Accounts | K54: NOLG | L54: yogebear | M54: AMWT-MVZG7I2NR3 | N54: Fleet Improvement Fund | O54: COMPLETE | P54: https://dashboard.paveapi.com/park/AMWT-MVZG7I2NR3/?l=en | Q54: 46144.71 | R54: 46144.72 | S54: 909 | T54: 46144.726 | U54: 1530 | V54: 1 | W54: 10290 | X54: 5 | Y54: 1 | Z54: 3 | AA54: 7 | AB54: 0 | AC54: 1 | AD54: 0 | AE54: 0 | AF54: USD | AG54: FALSE | AH54: FALSE | AI54: FALSE | AJ54: FALSE | AK54: FALSE | AL54: FALSE | AM54: View 5: Remove false positive damages. / Correct one. | AN54: 46144 | AO54: AMWT-MVZG7I2NR3 | AT54: TRUE | AU54: FALSE | AV54: FALSE
A55: 0503-1hrs_NA | B55: https://agent-admin.paveapi.com/inspectionView/AMWT-65PKOOTTNO?activeTab=past-sessions | C55: 1FTBR3X84LKA28016 | D55: US | E55: 2020 | F55: Ford | G55: Transit | H55: OPLS | I55: DCK6 | J55: DSP Accounts | K55: OPLS | L55: OPLS | M55: AMWT-65PKOOTTNO | N55: Fleet Improvement Fund | O55: COMPLETE | P55: https://dashboard.paveapi.com/park/AMWT-65PKOOTTNO/?l=en | Q55: 46145.927 | R55: 46145.929 | S55: 93 | T55: 46145.931 | U55: 384 | V55: 4 | W55: 2460 | X55: 0 | Y55: 0 | Z55: 2 | AA55: 2 | AB55: 0 | AC55: 0 | AD55: 0 | AE55: 0 | AF55: USD | AG55: FALSE | AH55: FALSE | AI55: FALSE | AJ55: FALSE | AK55: FALSE | AL55: FALSE | AN55: 46145 | AO55: AMWT-65PKOOTTNO | AT55: TRUE | AU55: FALSE | AV55: FALSE
B56: https://agent-admin.paveapi.com/inspectionView/AMWT-G70IWS3SER?activeTab=past-sessions | C56: 1FTBR3X84LKA28016 | D56: US | E56: 2020 | F56: Ford | G56: Transit | H56: OPLS | I56: DCK6 | J56: DSP Accounts | K56: OPLS | L56: OPLS | M56: AMWT-G70IWS3SER | N56: Wear & Tear | O56: COMPLETE | P56: https://dashboard.paveapi.com/park/AMWT-G70IWS3SER/?l=en | Q56: 46145.929 | R56: 46145.93 | S56: 100 | T56: 46145.937 | U56: 750 | V56: 4 | W56: 1825 | X56: 0 | Y56: 0 | Z56: 1 | AA56: 2 | AB56: 0 | AC56: 0 | AD56: 0 | AE56: 0 | AF56: USD | AG56: FALSE | AH56: FALSE | AI56: FALSE | AJ56: FALSE | AK56: FALSE | AL56: FALSE | AM56: View 7: Remove false positive damage. / Correct one. | AN56: 46145 | AO56: AMWT-G70IWS3SER | AT56: TRUE | AU56: FALSE | AV56: FALSE
B57: https://agent-admin.paveapi.com/inspectionView/AMWT-XVJ7ZTURWM?activeTab=past-sessions | C57: 1FTBR3X84MKA59235 | D57: US | E57: 2021 | F57: Ford | G57: TRANSIT | H57: PNTA | I57: DFH7 | J57: DSP Accounts | K57: PNTA | L57: PNTA.user | M57: AMWT-XVJ7ZTURWM | N57: Wear & Tear | O57: COMPLETE | P57: https://dashboard.paveapi.com/park/AMWT-XVJ7ZTURWM/?l=en | Q57: 46145.847 | R57: 46145.87 | S57: 1974 | T57: 46145.872 | U57: 2262 | V57: 2 | W57: 1697.5 | X57: 0 | Y57: 1 | Z57: 1 | AA57: 0 | AB57: 0 | AC57: 0 | AD57: 1 | AE57: 0 | AF57: USD | AG57: FALSE | AH57: FALSE | AI57: FALSE | AJ57: FALSE | AK57: FALSE | AL57: FALSE | AN57: 46145 | AO57: AMWT-XVJ7ZTURWM | AT57: TRUE | AU57: FALSE | AV57: FALSE
B58: https://agent-admin.paveapi.com/inspectionView/AMWT-WQNLGAS5VX?activeTab=past-sessions | C58: 1FTBR3X84MKA59235 | D58: US | E58: 2021 | F58: Ford | G58: TRANSIT | H58: PNTA | I58: DFH7 | J58: DSP Accounts | K58: PNTA | L58: PNTA.user | M58: AMWT-WQNLGAS5VX | N58: Wear & Tear | O58: COMPLETE | P58: https://dashboard.paveapi.com/park/AMWT-WQNLGAS5VX/?l=en | Q58: 46145.776 | R58: 46145.893 | S58: 10035 | T58: 46145.898 | U58: 14217 | V58: 4 | W58: 1122.5 | X58: 0 | Y58: 0 | Z58: 1 | AA58: 0 | AB58: 0 | AC58: 0 | AD58: 1 | AE58: 0 | AF58: USD | AG58: FALSE | AH58: FALSE | AI58: FALSE | AJ58: FALSE | AK58: FALSE | AL58: FALSE | AM58: View 5: Remove false positive damage. / Correct one. | AN58: 46145 | AO58: AMWT-WQNLGAS5VX | AT58: TRUE | AU58: FALSE | AV58: FALSE
B59: https://agent-admin.paveapi.com/inspectionView/AMWT-KD1OZKI85R?activeTab=past-sessions | C59: 7FCEHEB74PN007935 | D59: US | E59: 2023 | F59: Rivian | G59: Delivery | H59: TCKL | I59: DGT8 | J59: DSP Accounts | K59: TCKL | L59: TCKL.SHuynh | M59: AMWT-KD1OZKI85R | N59: Wear & Tear | O59: COMPLETE | P59: https://dashboard.paveapi.com/park/AMWT-KD1OZKI85R/?l=en | Q59: 46145.798 | R59: 46145.8 | S59: 96 | T59: 46145.802 | U59: 2421 | V59: 2 | W59: 8830 | X59: 5 | Y59: 0 | Z59: 6 | AA59: 1 | AB59: 2 | AC59: 0 | AD59: 0 | AE59: 0 | AF59: USD | AG59: FALSE | AH59: FALSE | AI59: FALSE | AJ59: FALSE | AK59: FALSE | AL59: FALSE | AM59: / Correct one. | AN59: 46145 | AO59: AMWT-KD1OZKI85R | AT59: TRUE | AU59: FALSE | AV59: FALSE
B60: https://agent-admin.paveapi.com/inspectionView/AMWT-U712MDYVGU?activeTab=past-sessions | C60: 7FCEHEB74PN007935 | D60: US | E60: 2023 | F60: Rivian | G60: Delivery | H60: TCKL | I60: DGT8 | J60: DSP Accounts | K60: TCKL | L60: TCKL.SHuynh | M60: AMWT-U712MDYVGU | N60: Wear & Tear | O60: COMPLETE | P60: https://dashboard.paveapi.com/park/AMWT-U712MDYVGU/?l=en | Q60: 46145.808 | R60: 46145.811 | S60: 266 | T60: 46145.815 | U60: 10234 | V60: 2 | W60: 8047.5 | X60: 4 | Y60: 0 | Z60: 4 | AA60: 1 | AB60: 2 | AC60: 0 | AD60: 0 | AE60: 0 | AF60: USD | AG60: FALSE | AH60: FALSE | AI60: FALSE | AJ60: FALSE | AK60: FALSE | AL60: FALSE | AM60: View 7: Repaired. / Correct one. | AN60: 46145 | AO60: AMWT-U712MDYVGU | AT60: TRUE | AU60: FALSE | AV60: FALSE
A61: 0504-1hrs_NA | B61: https://agent-admin.paveapi.com/inspectionView/AMWT-YM64GOJNZN?activeTab=past-sessions | C61: 1FTBR3X85MKA76769 | D61: US | E61: 2021 | F61: Ford | G61: Transit | H61: GTEL | I61: DJW8 | J61: DSP Accounts | K61: GTEL | L61: terrinava | M61: AMWT-YM64GOJNZN | N61: Wear & Tear | O61: COMPLETE | P61: https://dashboard.paveapi.com/park/AMWT-YM64GOJNZN/?l=en | Q61: 46146.858 | R61: 46146.861 | S61: 211 | T61: 46146.863 | U61: 582 | V61: 2 | W61: 8810 | X61: 2 | Y61: 2 | Z61: 2 | AA61: 2 | AB61: 0 | AC61: 0 | AD61: 0 | AE61: 0 | AF61: USD | AG61: FALSE | AH61: FALSE | AI61: FALSE | AJ61: FALSE | AK61: FALSE | AL61: FALSE | AN61: 46146 | AO61: AMWT-YM64GOJNZN | AP61: QA Wrong damage | AR61: anh.le | AS61: View 4: (7) Damage OLD xác định sai View 5: (2) Damage OLD xác định sai | AT61: FALSE | AU61: TRUE | AV61: FALSE
B62: https://agent-admin.paveapi.com/inspectionView/AMWT-RRREK4NMH0?activeTab=past-sessions | C62: 1FTBR3X85MKA76769 | D62: US | E62: 2021 | F62: Ford | G62: TRANSIT | H62: GTEL | I62: DJW8 | J62: DSP Accounts | K62: GTEL | L62: terrinava | M62: AMWT-RRREK4NMH0 | N62: Wear & Tear | O62: COMPLETE | P62: https://dashboard.paveapi.com/park/AMWT-RRREK4NMH0/?l=en | Q62: 46146.883 | R62: 46146.885 | S62: 163 | T62: 46146.89 | U62: 883 | V62: 2 | W62: 4035 | X62: 1 | Y62: 1 | Z62: 2 | AA62: 2 | AB62: 0 | AC62: 0 | AD62: 0 | AE62: 0 | AF62: USD | AG62: FALSE | AH62: FALSE | AI62: FALSE | AJ62: FALSE | AK62: FALSE | AL62: FALSE | AM62: View 4,5: Remove wrong damages. / Correct one. | AN62: 46146 | AO62: AMWT-RRREK4NMH0 | AT62: TRUE | AU62: FALSE | AV62: FALSE
B63: https://agent-admin.paveapi.com/inspectionView/AMWT-JFZN3JCUID?activeTab=past-sessions | C63: 3C6FRVJG0ME503699 | D63: US | E63: 2021 | F63: Ram | G63: ProMaster | H63: TIRG | I63: DLT3 | J63: DSP Accounts | K63: TIRG | L63: TIRG | M63: AMWT-JFZN3JCUID | N63: Wear & Tear | O63: COMPLETE | P63: https://dashboard.paveapi.com/park/AMWT-JFZN3JCUID/?l=en | Q63: 46146.698 | R63: 46146.7 | S63: 81 | T63: 46146.707 | U63: 807 | V63: 1 | W63: 17782.5 | X63: 24 | Y63: 2 | Z63: 10 | AA63: 5 | AB63: 1 | AC63: 0 | AD63: 0 | AE63: 0 | AF63: USD | AG63: FALSE | AH63: FALSE | AI63: FALSE | AJ63: FALSE | AK63: FALSE | AL63: FALSE | AM63: / Correct one. | AN63: 46146 | AO63: AMWT-JFZN3JCUID | AT63: TRUE | AU63: FALSE | AV63: FALSE
B64: https://agent-admin.paveapi.com/inspectionView/AMWT-MKFBORZ1PD?activeTab=past-sessions | C64: 3C6FRVJG0ME503699 | D64: US | E64: 2021 | F64: Ram | G64: ProMaster | H64: TIRG | I64: DLT3 | J64: DSP Accounts | K64: TIRG | L64: TIRG | M64: AMWT-MKFBORZ1PD | N64: Wear & Tear | O64: COMPLETE | P64: https://dashboard.paveapi.com/park/AMWT-MKFBORZ1PD/?l=en | Q64: 46146.7 | R64: 46146.701 | S64: 63 | T64: 46146.719 | U64: 1709 | V64: 1 | W64: 17645 | X64: 23 | Y64: 2 | Z64: 10 | AA64: 5 | AB64: 1 | AC64: 0 | AD64: 0 | AE64: 0 | AF64: USD | AG64: FALSE | AH64: FALSE | AI64: FALSE | AJ64: FALSE | AK64: FALSE | AL64: FALSE | AM64: View 4: Repaired. / Correct one. | AN64: 46146 | AO64: AMWT-MKFBORZ1PD | AT64: TRUE | AU64: FALSE | AV64: FALSE
B65: https://agent-admin.paveapi.com/inspectionView/AMWT-06WCEA29OY?activeTab=past-sessions | C65: 3C6MRVJG0ME557057 | D65: US | E65: 2021 | F65: Ram | G65: ProMaster | H65: AMVF | I65: DWA9 | J65: Last Mile Rentals | K65: AMVF | L65: darthur.lmr | M65: AMWT-06WCEA29OY | N65: Last Mile Rental (W&T) | O65: COMPLETE | P65: https://dashboard.paveapi.com/park/AMWT-06WCEA29OY/?l=en | Q65: 46146.741 | R65: 46146.745 | S65: 297 | T65: 46146.75 | U65: 775 | V65: 3 | W65: 3597.5 | X65: 3 | Y65: 1 | Z65: 2 | AA65: 0 | AB65: 0 | AC65: 0 | AD65: 0 | AE65: 0 | AF65: USD | AG65: FALSE | AH65: FALSE | AI65: FALSE | AJ65: FALSE | AK65: FALSE | AL65: FALSE | AN65: 46146 | AO65: AMWT-06WCEA29OY | AS65: Xóa damage ID trước đánh nghi ngờ | AT65: TRUE | AU65: FALSE | AV65: FALSE
B66: https://agent-admin.paveapi.com/inspectionView/AMWT-MOHELJ1N50?activeTab=past-sessions | C66: 3C6MRVJG0ME557057 | D66: US | E66: 2021 | F66: Ram | G66: ProMaster | H66: AMVF | I66: DWA9 | J66: DSP Accounts | K66: AMVF | L66: STAV | M66: AMWT-MOHELJ1N50 | N66: Wear & Tear | O66: COMPLETE | P66: https://dashboard.paveapi.com/park/AMWT-MOHELJ1N50/?l=en | Q66: 46146.763 | R66: 46146.766 | S66: 132 | T66: 46146.77 | U66: 657 | V66: 3 | W66: 3022.5 | X66: 3 | Y66: 0 | Z66: 2 | AA66: 0 | AB66: 0 | AC66: 0 | AD66: 0 | AE66: 0 | AF66: USD | AG66: FALSE | AH66: FALSE | AI66: FALSE | AJ66: FALSE | AK66: FALSE | AL66: FALSE | AM66: View 5: Remove false positive damage. / Correct one. | AN66: 46146 | AO66: AMWT-MOHELJ1N50 | AT66: TRUE | AU66: FALSE | AV66: FALSE
B67: https://agent-admin.paveapi.com/inspectionView/AMWT-4LDWNCYSZP?activeTab=past-sessions | C67: 3C6MRVJG2ME556444 | D67: US | E67: 2021 | F67: Ram | G67: ProMaster | H67: SDLG | I67: DLX5 | J67: DSP Accounts | K67: SDLG | L67: SDLG.user | M67: AMWT-4LDWNCYSZP | N67: Fleet Improvement Fund | O67: COMPLETE | P67: https://dashboard.paveapi.com/park/AMWT-4LDWNCYSZP/?l=en | Q67: 46146.953 | R67: 46146.955 | S67: 126 | T67: 46146.96 | U67: 2177 | V67: 1 | W67: 10562.5 | X67: 3 | Y67: 2 | Z67: 6 | AA67: 8 | AB67: 1 | AC67: 0 | AD67: 0 | AE67: 0 | AF67: USD | AG67: FALSE | AH67: FALSE | AI67: FALSE | AJ67: FALSE | AK67: FALSE | AL67: FALSE | AM67: / Correct one. | AN67: 46146 | AO67: AMWT-4LDWNCYSZP | AT67: TRUE | AU67: FALSE | AV67: FALSE
B68: https://agent-admin.paveapi.com/inspectionView/AMWT-TKWIHAYHF3?activeTab=past-sessions | C68: 3C6MRVJG2ME556444 | D68: US | E68: 2021 | F68: Ram | G68: ProMaster | H68: SDLG | I68: DLX5 | J68: DSP Accounts | K68: SDLG | L68: SDLG.user | M68: AMWT-TKWIHAYHF3 | N68: Fleet Improvement Fund | O68: COMPLETE | P68: https://dashboard.paveapi.com/park/AMWT-TKWIHAYHF3/?l=en | Q68: 46146.962 | R68: 46146.964 | S68: 163 | T68: 46146.973 | U68: 3296 | V68: 1 | W68: 10462.5 | X68: 3 | Y68: 1 | Z68: 6 | AA68: 8 | AB68: 1 | AC68: 0 | AD68: 0 | AE68: 0 | AF68: USD | AG68: FALSE | AH68: FALSE | AI68: FALSE | AJ68: FALSE | AK68: FALSE | AL68: FALSE | AM68: View 5: Repaired. / Correct one. | AN68: 46146 | AO68: AMWT-TKWIHAYHF3 | AT68: TRUE | AU68: FALSE | AV68: FALSE
B69: https://agent-admin.paveapi.com/inspectionView/AMWT-LJL7ZY5EDR?activeTab=past-sessions | C69: 7FCEHDB73NN005004 | D69: US | E69: 2022 | F69: Rivian | G69: Delivery | H69: NOLG | I69: DGT8 | J69: DSP Accounts | K69: NOLG | L69: yogebear | M69: AMWT-LJL7ZY5EDR | N69: Wear & Tear | O69: COMPLETE | P69: https://dashboard.paveapi.com/park/AMWT-LJL7ZY5EDR/?l=en | Q69: 46146.52 | R69: 46146.521 | S69: 96 | T69: 46146.525 | U69: 501 | V69: 1 | W69: 9602.5 | X69: 17 | Y69: 4 | Z69: 5 | AA69: 1 | AB69: 3 | AC69: 0 | AD69: 3 | AE69: 0 | AF69: USD | AG69: FALSE | AH69: FALSE | AI69: FALSE | AJ69: FALSE | AK69: FALSE | AL69: FALSE | AM69: / Correct one. | AN69: 46146 | AO69: AMWT-LJL7ZY5EDR | AT69: TRUE | AU69: FALSE | AV69: FALSE
B70: https://agent-admin.paveapi.com/inspectionView/AMWT-WAHN2QZRMK?activeTab=past-sessions | C70: 7FCEHDB73NN005004 | D70: US | E70: 2022 | F70: Rivian | G70: Delivery | H70: NOLG | I70: DGT8 | J70: DSP Accounts | K70: NOLG | L70: yogebear | M70: AMWT-WAHN2QZRMK | N70: Fleet Improvement Fund | O70: COMPLETE | P70: https://dashboard.paveapi.com/park/AMWT-WAHN2QZRMK/?l=en | Q70: 46146.523 | R70: 46146.525 | S70: 153 | T70: 46146.536 | U70: 1219 | V70: 1 | W70: 9380 | X70: 17 | Y70: 4 | Z70: 5 | AA70: 1 | AB70: 2 | AC70: 0 | AD70: 3 | AE70: 0 | AF70: USD | AG70: FALSE | AH70: FALSE | AI70: FALSE | AJ70: FALSE | AK70: FALSE | AL70: FALSE | AM70: View 4: Repaired. / Correct one. | AN70: 46146 | AO70: AMWT-WAHN2QZRMK | AT70: TRUE | AU70: FALSE | AV70: FALSE
B71: https://agent-admin.paveapi.com/inspectionView/AMWT-NOUFAZVKSY?activeTab=past-sessions | C71: 7FCEHEB73PN006663 | D71: US | E71: 2023 | F71: Rivian | G71: Delivery | H71: MURR | I71: DWO1 | J71: DSP Accounts | K71: MURR | L71: MURR.user | M71: AMWT-NOUFAZVKSY | N71: Fleet Improvement Fund | O71: COMPLETE | P71: https://dashboard.paveapi.com/park/AMWT-NOUFAZVKSY/?l=en | Q71: 46146.551 | R71: 46146.553 | S71: 154 | T71: 46146.558 | U71: 666 | V71: 2 | W71: 7350 | X71: 5 | Y71: 1 | Z71: 3 | AA71: 1 | AB71: 1 | AC71: 0 | AD71: 0 | AE71: 0 | AF71: USD | AG71: FALSE | AH71: FALSE | AI71: FALSE | AJ71: FALSE | AK71: FALSE | AL71: FALSE | AM71: / Correct one. | AN71: 46146 | AO71: AMWT-NOUFAZVKSY | AT71: TRUE | AU71: FALSE | AV71: FALSE
B72: https://agent-admin.paveapi.com/inspectionView/AMWT-17N75NVUWD?activeTab=past-sessions | C72: 7FCEHEB73PN006663 | D72: US | E72: 2023 | F72: Rivian | G72: Delivery | H72: MURR | I72: DWO1 | J72: DSP Accounts | K72: MURR | L72: MURR.user | M72: AMWT-17N75NVUWD | N72: Fleet Improvement Fund | O72: COMPLETE | P72: https://dashboard.paveapi.com/park/AMWT-17N75NVUWD/?l=en | Q72: 46146.583 | R72: 46146.585 | S72: 158 | T72: 46146.597 | U72: 1245 | V72: 2 | W72: 7235 | X72: 5 | Y72: 0 | Z72: 3 | AA72: 1 | AB72: 1 | AC72: 0 | AD72: 0 | AE72: 0 | AF72: USD | AG72: FALSE | AH72: FALSE | AI72: FALSE | AJ72: FALSE | AK72: FALSE | AL72: FALSE | AM72: View 5: Repaired. / Correct one. | AN72: 46146 | AO72: AMWT-17N75NVUWD | AT72: TRUE | AU72: FALSE | AV72: FALSE
B73: https://agent-admin.paveapi.com/inspectionView/AMWT-OIN0Y7FT2G?activeTab=past-sessions | C73: 7FCEHEB73PN009398 | D73: US | E73: 2023 | F73: Rivian | G73: Delivery | H73: TOPF | I73: DUT7 | J73: DSP Accounts | K73: TOPF | L73: TOPF.user | M73: AMWT-OIN0Y7FT2G | N73: Fleet Improvement Fund | O73: COMPLETE | P73: https://dashboard.paveapi.com/park/AMWT-OIN0Y7FT2G/?l=en | Q73: 46146.629 | R73: 46146.632 | S73: 207 | T73: 46146.635 | U73: 617 | V73: 2 | W73: 3507.5 | X73: 0 | Y73: 0 | Z73: 4 | AA73: 1 | AB73: 0 | AC73: 0 | AD73: 0 | AE73: 0 | AF73: USD | AG73: FALSE | AH73: FALSE | AI73: FALSE | AJ73: FALSE | AK73: FALSE | AL73: FALSE | AM73: / Correct one. | AN73: 46146 | AO73: AMWT-OIN0Y7FT2G | AT73: TRUE | AU73: FALSE | AV73: FALSE
B74: https://agent-admin.paveapi.com/inspectionView/AMWT-IWS3BFRSOV?activeTab=past-sessions | C74: 7FCEHEB73PN009398 | D74: US | E74: 2023 | F74: Rivian | G74: Delivery | H74: TOPF | I74: DUT7 | J74: DSP Accounts | K74: TOPF | L74: TOPF.user | M74: AMWT-IWS3BFRSOV | N74: Fleet Improvement Fund | O74: COMPLETE | P74: https://dashboard.paveapi.com/park/AMWT-IWS3BFRSOV/?l=en | Q74: 46146.634 | R74: 46146.637 | S74: 171 | T74: 46146.648 | U74: 1752 | V74: 2 | W74: 3285 | X74: 0 | Y74: 0 | Z74: 3 | AA74: 1 | AB74: 0 | AC74: 0 | AD74: 0 | AE74: 0 | AF74: USD | AG74: FALSE | AH74: FALSE | AI74: FALSE | AJ74: FALSE | AK74: FALSE | AL74: FALSE | AM74: View 7: Repaired. / Correct one. | AN74: 46146 | AO74: AMWT-IWS3BFRSOV | AT74: TRUE | AU74: FALSE | AV74: FALSE
B75: https://agent-admin.paveapi.com/inspectionView/AMWT-RQY1OW0KCR?activeTab=past-sessions | C75: 7FCEHEB78PN013933 | D75: US | E75: 2023 | F75: Rivian | G75: Delivery | H75: LGCC | I75: DDT9 | J75: DSP Accounts | K75: LGCC | L75: jnobs15 | M75: AMWT-RQY1OW0KCR | N75: Fleet Improvement Fund | O75: COMPLETE | P75: https://dashboard.paveapi.com/park/AMWT-RQY1OW0KCR/?l=en | Q75: 46146.595 | R75: 46146.597 | S75: 197 | T75: 46146.601 | U75: 7523 | V75: 2 | W75: 3620 | X75: 1 | Y75: 1 | Z75: 6 | AA75: 1 | AB75: 0 | AC75: 0 | AD75: 0 | AE75: 0 | AF75: USD | AG75: FALSE | AH75: FALSE | AI75: FALSE | AJ75: FALSE | AK75: FALSE | AL75: FALSE | AM75: / Correct one. | AN75: 46146 | AO75: AMWT-RQY1OW0KCR | AT75: TRUE | AU75: FALSE | AV75: FALSE
B76: https://agent-admin.paveapi.com/inspectionView/AMWT-ZWH6CLF7P6?activeTab=past-sessions | C76: 7FCEHEB78PN013933 | D76: US | E76: 2023 | F76: Rivian | G76: Delivery | H76: LGCC | I76: DDT9 | J76: DSP Accounts | K76: LGCC | L76: jnobs15 | M76: AMWT-ZWH6CLF7P6 | N76: Fleet Improvement Fund | O76: COMPLETE | P76: https://dashboard.paveapi.com/park/AMWT-ZWH6CLF7P6/?l=en | Q76: 46146.621 | R76: 46146.625 | S76: 303 | T76: 46146.631 | U76: 1699 | V76: 2 | W76: 2882.5 | X76: 1 | Y76: 1 | Z76: 6 | AA76: 0 | AB76: 0 | AC76: 0 | AD76: 0 | AE76: 0 | AF76: USD | AG76: FALSE | AH76: FALSE | AI76: FALSE | AJ76: FALSE | AK76: FALSE | AL76: FALSE | AM76: View 8: Repaired. / Correct one. | AN76: 46146 | AO76: AMWT-ZWH6CLF7P6 | AT76: TRUE | AU76: FALSE | AV76: FALSE
B77: https://agent-admin.paveapi.com/inspectionView/AMWT-A1FWRTS2HX?activeTab=past-sessions | C77: 7FCEHEB79PN015027 | D77: US | E77: 2023 | F77: Rivian | G77: Delivery | H77: NOLG | I77: DGT8 | J77: DSP Accounts | K77: NOLG | L77: yogebear | M77: AMWT-A1FWRTS2HX | N77: Wear & Tear | O77: COMPLETE | P77: https://dashboard.paveapi.com/park/AMWT-A1FWRTS2HX/?l=en | Q77: 46146.497 | R77: 46146.498 | S77: 125 | T77: 46146.503 | U77: 675 | V77: 1 | W77: 13160 | X77: 7 | Y77: 1 | Z77: 13 | AA77: 3 | AB77: 1 | AC77: 0 | AD77: 2 | AE77: 0 | AF77: USD | AG77: FALSE | AH77: FALSE | AI77: FALSE | AJ77: FALSE | AK77: FALSE | AL77: FALSE | AN77: 46146 | AO77: AMWT-A1FWRTS2HX | AP77: QA Wrong damage | AR77: phong.nguyen | AS77: View 8: (2) Damage OLD đã sửa chữa | AT77: FALSE | AU77: TRUE | AV77: TRUE
B78: https://agent-admin.paveapi.com/inspectionView/AMWT-LEBKDQEQ8V?activeTab=past-sessions | C78: 7FCEHEB79PN015027 | D78: US | E78: 2023 | F78: Rivian | G78: Delivery | H78: NOLG | I78: DGT8 | J78: DSP Accounts | K78: NOLG | L78: yogebear | M78: AMWT-LEBKDQEQ8V | N78: Fleet Improvement Fund | O78: COMPLETE | P78: https://dashboard.paveapi.com/park/AMWT-LEBKDQEQ8V/?l=en | Q78: 46146.499 | R78: 46146.5 | S78: 109 | T78: 46146.537 | U78: 3404 | V78: 1 | W78: 11235 | X78: 7 | Y78: 1 | Z78: 13 | AA78: 1 | AB78: 1 | AC78: 0 | AD78: 2 | AE78: 0 | AF78: USD | AG78: FALSE | AH78: FALSE | AI78: FALSE | AJ78: FALSE | AK78: FALSE | AL78: FALSE | AM78: View 8: Remove wrong damages. / Correct one. | AN78: 46146 | AO78: AMWT-LEBKDQEQ8V | AP78: QA Wrong damage | AR78: thanh.dlq | AS78: View 7: (16, 17, 18) Damage NEW không nên add Note: same vin 60 phút không add thêm damage | AT78: FALSE | AU78: TRUE | AV78: FALSE
B79: https://agent-admin.paveapi.com/inspectionView/AMWK-PZLBZODR1U?activeTab=past-sessions | C79: WF0EXXTTREMR03195 | M79: AMWK-PZLBZODR1U | AN79: 46146 | AO79: AMWK-PZLBZODR1U | AP79: QA Wrong damage | AR79: tu.nbt | AS79: View 4: (4, 5, 22) Damage OLD đã sửa chữa | AT79: FALSE | AU79: TRUE | AV79: TRUE
B80: https://agent-admin.paveapi.com/inspectionView/AMWT-Z1GJAKQKVD?activeTab=past-sessions | C80: 7FCEHEB74PN015176 | D80: US | E80: 2023 | F80: Rivian | G80: Delivery | H80: NOLG | I80: DGT8 | J80: DSP Accounts | K80: NOLG | L80: yogebear | M80: AMWT-Z1GJAKQKVD | N80: Wear & Tear | O80: COMPLETE | P80: https://dashboard.paveapi.com/park/AMWT-Z1GJAKQKVD/?l=en | Q80: 46146.546 | R80: 46146.547 | S80: 127 | T80: 46146.55 | U80: 519 | V80: 2 | W80: 7295 | X80: 5 | Y80: 5 | Z80: 12 | AA80: 0 | AB80: 1 | AC80: 0 | AD80: 1 | AE80: 0 | AF80: USD | AG80: FALSE | AH80: FALSE | AI80: FALSE | AJ80: FALSE | AK80: FALSE | AL80: FALSE | AN80: 46146 | AO80: AMWT-Z1GJAKQKVD | AP80: QA Miss Damage | AR80: phu.nguyenhoang | AS80: View 4: DENTED_MEDIUM_NOT_THROUGH_PAINT - CENTER_PANEL_LEFT View 8: DENTED_MEDIUM_NOT_THROUGH_PAINT - PILLAR_COVER_REAR_RIGHT - TK ID: AMWT-M9URZ8QUDM | AT80: FALSE | AU80: TRUE | AV80: TRUE
B81: https://agent-admin.paveapi.com/inspectionView/AMWT-M9URZ8QUDM?activeTab=past-sessions | C81: 7FCEHEB74PN015176 | D81: US | E81: 2023 | F81: Rivian | G81: Delivery | H81: NOLG | I81: DGT8 | J81: DSP Accounts | K81: NOLG | L81: yogebear | M81: AMWT-M9URZ8QUDM | N81: Fleet Improvement Fund | O81: COMPLETE | P81: https://dashboard.paveapi.com/park/AMWT-M9URZ8QUDM/?l=en | Q81: 46146.548 | R81: 46146.55 | S81: 155 | T81: 46146.559 | U81: 1046 | V81: 2 | W81: 7295 | X81: 5 | Y81: 5 | Z81: 12 | AA81: 0 | AB81: 1 | AC81: 0 | AD81: 1 | AE81: 0 | AF81: USD | AG81: FALSE | AH81: FALSE | AI81: FALSE | AJ81: FALSE | AK81: FALSE | AL81: FALSE | AN81: 46146 | AO81: AMWT-M9URZ8QUDM | AT81: FALSE | AU81: TRUE | AV81: FALSE
B82: https://agent-admin.paveapi.com/inspectionView/AMWT-3H4TUAUPYH?activeTab=past-sessions | C82: 7FCEHEB77PN015205 | D82: US | E82: 2023 | F82: Rivian | G82: Delivery | H82: NOLG | I82: DGT8 | J82: DSP Accounts | K82: NOLG | L82: yogebear | M82: AMWT-3H4TUAUPYH | N82: Wear & Tear | O82: COMPLETE | P82: https://dashboard.paveapi.com/park/AMWT-3H4TUAUPYH/?l=en | Q82: 46146.553 | R82: 46146.554 | S82: 118 | T82: 46146.56 | U82: 763 | V82: 2 | W82: 4495 | X82: 1 | Y82: 0 | Z82: 27 | AA82: 0 | AB82: 0 | AC82: 0 | AD82: 0 | AE82: 0 | AF82: USD | AG82: FALSE | AH82: FALSE | AI82: FALSE | AJ82: FALSE | AK82: FALSE | AL82: FALSE | AN82: 46146 | AO82: AMWT-3H4TUAUPYH | AP82: QA Miss Damage | AR82: tu.nbt | AS82: View 4: DENTED_MEDIUM_NOT_THROUGH_PAINT - DOOR_FRONT_LEFT | AT82: FALSE | AU82: TRUE | AV82: TRUE
B83: https://agent-admin.paveapi.com/inspectionView/AMWT-LDFQHVPNFC?activeTab=past-sessions | C83: 7FCEHEB77PN015205 | D83: US | E83: 2023 | F83: Rivian | G83: Delivery | H83: NOLG | I83: DGT8 | J83: DSP Accounts | K83: NOLG | L83: yogebear | M83: AMWT-LDFQHVPNFC | N83: Fleet Improvement Fund | O83: COMPLETE | P83: https://dashboard.paveapi.com/park/AMWT-LDFQHVPNFC/?l=en | Q83: 46146.555 | R83: 46146.557 | S83: 139 | T83: 46146.587 | U83: 2891 | V83: 2 | W83: 4495 | X83: 1 | Y83: 0 | Z83: 27 | AA83: 0 | AB83: 0 | AC83: 0 | AD83: 0 | AE83: 0 | AF83: USD | AG83: FALSE | AH83: FALSE | AI83: FALSE | AJ83: FALSE | AK83: FALSE | AL83: FALSE | AN83: 46146 | AO83: AMWT-LDFQHVPNFC | AT83: FALSE | AU83: TRUE | AV83: FALSE
B84: https://agent-admin.paveapi.com/inspectionView/AMWT-S3REC7U1W1?activeTab=past-sessions | C84: 3C6LRVDG4PE565190 | D84: US | E84: 2023 | F84: Ram | G84: ProMaster | H84: AMZL | I84: AMZL | J84: DSP Accounts | K84: AMZL | L84: yogebear | M84: AMWT-S3REC7U1W1 | N84: Wear & Tear | O84: COMPLETE | P84: https://dashboard.paveapi.com/park/AMWT-S3REC7U1W1/?l=en | Q84: 46146.593 | R84: 46146.595 | S84: 113 | T84: 46146.597 | U84: 438 | V84: 4 | W84: 1885 | X84: 1 | Y84: 1 | Z84: 1 | AA84: 0 | AB84: 0 | AC84: 0 | AD84: 0 | AE84: 0 | AF84: USD | AG84: FALSE | AH84: FALSE | AI84: FALSE | AJ84: FALSE | AK84: FALSE | AL84: FALSE | AN84: 46146 | AO84: AMWT-S3REC7U1W1 | AP84: QA Miss Damage | AR84: tinh.nguyenmaiviet | AS84: View 4: DENTED_MAJOR_NOT_THROUGH_PAINT - BUMPER_REAR_UNIQUE | AT84: FALSE | AU84: TRUE | AV84: TRUE
B85: https://agent-admin.paveapi.com/inspectionView/AMWT-7GXYGONCCC?activeTab=past-sessions | C85: 3C6LRVDG4PE565190 | D85: US | E85: 2023 | F85: Ram | G85: ProMaster | H85: AMZL | I85: AMZL | J85: DSP Accounts | K85: AMZL | L85: yogebear | M85: AMWT-7GXYGONCCC | N85: Fleet Improvement Fund | O85: COMPLETE | P85: https://dashboard.paveapi.com/park/AMWT-7GXYGONCCC/?l=en | Q85: 46146.595 | R85: 46146.596 | S85: 77 | T85: 46146.608 | U85: 1189 | V85: 4 | W85: 1885 | X85: 1 | Y85: 1 | Z85: 1 | AA85: 0 | AB85: 0 | AC85: 0 | AD85: 0 | AE85: 0 | AF85: USD | AG85: FALSE | AH85: FALSE | AI85: FALSE | AJ85: FALSE | AK85: FALSE | AL85: FALSE | AN85: 46146 | AO85: AMWT-7GXYGONCCC | AT85: FALSE | AU85: TRUE | AV85: FALSE
B86: https://agent-admin.paveapi.com/inspectionView/AMWT-MKAYCBYXNI?activeTab=past-sessions | C86: 7FCEHEB75PN014893 | D86: US | E86: 2023 | F86: Rivian | G86: Delivery | H86: NOLG | I86: DGT8 | J86: DSP Accounts | K86: NOLG | L86: yogebear | M86: AMWT-MKAYCBYXNI | N86: Wear & Tear | O86: COMPLETE | P86: https://dashboard.paveapi.com/park/AMWT-MKAYCBYXNI/?l=en | Q86: 46146.56 | R86: 46146.562 | S86: 156 | T86: 46146.566 | U86: 670 | V86: 2 | W86: 8565 | X86: 6 | Y86: 1 | Z86: 16 | AA86: 2 | AB86: 2 | AC86: 0 | AD86: 4 | AE86: 0 | AF86: USD | AG86: FALSE | AH86: FALSE | AI86: FALSE | AJ86: FALSE | AK86: FALSE | AL86: FALSE | AN86: 46146 | AO86: AMWT-MKAYCBYXNI | AP86: QA Wrong damage | AR86: duy.nguyenquoc | AS86: View 4: (2) Damage OLD sai label - QUARTER_PANEL_LEFT -> CENTER_PANEL_LEFT | AT86: FALSE | AU86: TRUE | AV86: TRUE
B87: https://agent-admin.paveapi.com/inspectionView/AMWT-GTOAEVPE7H?activeTab=past-sessions | C87: 7FCEHEB75PN014893 | D87: US | E87: 2023 | F87: Rivian | G87: Delivery | H87: NOLG | I87: DGT8 | J87: DSP Accounts | K87: NOLG | L87: yogebear | M87: AMWT-GTOAEVPE7H | N87: Fleet Improvement Fund | O87: COMPLETE | P87: https://dashboard.paveapi.com/park/AMWT-GTOAEVPE7H/?l=en | Q87: 46146.562 | R87: 46146.564 | S87: 119 | T87: 46146.619 | U87: 4976 | V87: 2 | W87: 8565 | X87: 6 | Y87: 1 | Z87: 16 | AA87: 2 | AB87: 2 | AC87: 0 | AD87: 4 | AE87: 0 | AF87: USD | AG87: FALSE | AH87: FALSE | AI87: FALSE | AJ87: FALSE | AK87: FALSE | AL87: FALSE | AN87: 46146 | AO87: AMWT-GTOAEVPE7H | AT87: FALSE | AU87: TRUE | AV87: FALSE
A88: 0505-1hrs_NA | B88: https://agent-admin.paveapi.com/inspectionView/AMWT-IC2A5U5CNF?activeTab=past-sessions | C88: 1FTYR3XM5KKB29247 | D88: US | E88: 2019 | F88: Ford | G88: Transit | H88: ONCI | I88: DSM4 | J88: DSP Accounts | K88: ONCI | L88: Rene94577 | M88: AMWT-IC2A5U5CNF | N88: Wear & Tear | O88: COMPLETE | P88: https://dashboard.paveapi.com/park/AMWT-IC2A5U5CNF/?l=en | Q88: 46147.73 | R88: 46147.732 | S88: 107 | T88: 46147.736 | U88: 581 | V88: 3 | W88: 3570 | X88: 2 | Y88: 2 | Z88: 3 | AA88: 2 | AB88: 0 | AC88: 0 | AD88: 0 | AE88: 0 | AF88: USD | AG88: FALSE | AH88: FALSE | AI88: FALSE | AJ88: FALSE | AK88: FALSE | AL88: FALSE | AM88: / Correct one. | AN88: 46147 | AO88: AMWT-IC2A5U5CNF | AT88: TRUE | AU88: FALSE | AV88: FALSE
B89: https://agent-admin.paveapi.com/inspectionView/AMWT-WOD2UYUTNL?activeTab=past-sessions | C89: 1FTYR3XM5KKB29247 | D89: US | E89: 2019 | F89: Ford | G89: Transit | H89: ONCI | I89: DSM4 | J89: DSP Accounts | K89: ONCI | L89: Rene94577 | M89: AMWT-WOD2UYUTNL | N89: Wear & Tear | O89: COMPLETE | P89: https://dashboard.paveapi.com/park/AMWT-WOD2UYUTNL/?l=en | Q89: 46147.766 | R89: 46147.769 | S89: 191 | T89: 46147.773 | U89: 2047 | V89: 3 | W89: 3125 | X89: 1 | Y89: 2 | Z89: 3 | AA89: 0 | AB89: 0 | AC89: 0 | AD89: 0 | AE89: 0 | AF89: USD | AG89: FALSE | AH89: FALSE | AI89: FALSE | AJ89: FALSE | AK89: FALSE | AL89: FALSE | AM89: View 4, 8: Repaired. / Correct one. | AN89: 46147 | AO89: AMWT-WOD2UYUTNL | AT89: TRUE | AU89: FALSE | AV89: FALSE
B90: https://agent-admin.paveapi.com/inspectionView/AMUO-Y27TKEXG0J?activeTab=past-sessions | C90: 3C6MRVJG0ME549346 | D90: US | E90: 2021 | F90: Ram | G90: ProMaster | H90: GOAT | I90: DAE8 | J90: Last Mile Rentals | K90: GOAT | M90: AMUO-Y27TKEXG0J | N90: Merchants_LMR_rtinsp | O90: COMPLETE | P90: https://dashboard.paveapi.com/park/AMUO-Y27TKEXG0J/?l=en | Q90: 46147.613 | R90: 46147.615 | S90: 127 | T90: 46147.621 | U90: 1197 | V90: 2 | W90: 7712.5 | X90: 4 | Y90: 1 | Z90: 2 | AA90: 1 | AB90: 0 | AC90: 0 | AD90: 1 | AE90: 0 | AF90: USD | AG90: FALSE | AH90: FALSE | AI90: FALSE | AJ90: FALSE | AK90: FALSE | AL90: FALSE | AN90: 46147 | AO90: AMUO-Y27TKEXG0J | AP90: Agent + QA Wrong damage | AQ90: tinh.nguyenmaiviet | AR90: thien.nguyen | AS90: View 7: (3) Damage NEW sai kích thước | AT90: FALSE | AU90: TRUE | AV90: FALSE
B91: https://agent-admin.paveapi.com/inspectionView/AMWT-LVBHMWGKLU?activeTab=past-sessions | C91: 3C6MRVJG0ME549346 | D91: US | E91: 2021 | F91: Ram | G91: PROMASTER | H91: GOAT | I91: DAE8 | J91: DSP Accounts | K91: GOAT | L91: GOAT.user | M91: AMWT-LVBHMWGKLU | N91: Wear & Tear | O91: COMPLETE | P91: https://dashboard.paveapi.com/park/AMWT-LVBHMWGKLU/?l=en | Q91: 46147.616 | R91: 46147.619 | S91: 256 | T91: 46147.629 | U91: 1886 | V91: 2 | W91: 6312.5 | X91: 4 | Y91: 1 | Z91: 1 | AA91: 1 | AB91: 0 | AC91: 0 | AD91: 1 | AE91: 0 | AF91: USD | AG91: FALSE | AH91: FALSE | AI91: FALSE | AJ91: FALSE | AK91: FALSE | AL91: FALSE | AM91: View 7: Remove false positive damage. / Correct one. | AN91: 46147 | AO91: AMWT-LVBHMWGKLU | AT91: TRUE | AU91: FALSE | AV91: FALSE
B92: https://agent-admin.paveapi.com/inspectionView/AMWT-LR5JA6FNVY?activeTab=past-sessions | C92: 3C6MRVJGXME551251 | D92: CA | E92: 2021 | F92: Ram | G92: ProMaster | H92: DELE | I92: DVC4 | J92: DSP Accounts | K92: DELE | L92: ajay.deleezy | M92: AMWT-LR5JA6FNVY | N92: Fleet Improvement Fund | O92: COMPLETE | P92: https://dashboard.paveapi.com/park/AMWT-LR5JA6FNVY/?l=en | Q92: 46147.951 | R92: 46147.954 | S92: 172 | T92: 46147.957 | U92: 1127 | V92: 2 | W92: 6317.5 | X92: 0 | Y92: 0 | Z92: 6 | AA92: 3 | AB92: 0 | AC92: 0 | AD92: 0 | AE92: 1 | AF92: CAD | AG92: FALSE | AH92: FALSE | AI92: FALSE | AJ92: FALSE | AK92: FALSE | AL92: FALSE | AN92: 46147 | AO92: AMWT-LR5JA6FNVY | AP92: QA Wrong damage | AR92: oanh.ngo | AS92: View 7: (1, 6, 7) Damage OLD đã sửa chữa View 8: (1, 2, 3, 4) Damage OLD đã sửa chữa | AT92: FALSE | AU92: TRUE | AV92: TRUE
B93: https://agent-admin.paveapi.com/inspectionView/AMWT-CFE8COZGPY?activeTab=past-sessions | C93: 3C6MRVJGXME551251 | D93: CA | E93: 2021 | F93: Ram | G93: ProMaster | H93: DELE | I93: DVC4 | J93: DSP Accounts | K93: DELE | L93: ajay.deleezy | M93: AMWT-CFE8COZGPY | N93: Fleet Improvement Fund | O93: COMPLETE | P93: https://dashboard.paveapi.com/park/AMWT-CFE8COZGPY/?l=en | Q93: 46147.98 | R93: 46147.983 | S93: 195 | T93: 46147.991 | U93: 1418 | V93: 4 | W93: 1822.5 | X93: 0 | Y93: 0 | Z93: 3 | AA93: 0 | AB93: 0 | AC93: 0 | AD93: 0 | AE93: 0 | AF93: CAD | AG93: FALSE | AH93: FALSE | AI93: FALSE | AJ93: FALSE | AK93: FALSE | AL93: FALSE | AM93: View 7, 8: Remove wrong damages. / Correct one. | AN93: 46147 | AO93: AMWT-CFE8COZGPY | AT93: TRUE | AU93: FALSE | AV93: FALSE
B94: https://agent-admin.paveapi.com/inspectionView/AMRR-4DDVKKFOPE?activeTab=past-sessions | C94: 3C6URVJG5LE145361 | D94: US | E94: 2020 | F94: Ram | G94: ProMaster | H94: AMZL | I94: AMZL | J94: DSP Accounts | K94: AMZL | L94: DMSH.user | M94: AMRR-4DDVKKFOPE | N94: Redeployment/Retirement | O94: COMPLETE | P94: https://dashboard.paveapi.com/park/AMRR-4DDVKKFOPE/?l=en | Q94: 46147.585 | R94: 46147.587 | S94: 152 | T94: 46147.589 | U94: 602 | V94: 1 | W94: 12965 | X94: 13 | Y94: 1 | Z94: 4 | AA94: 3 | AB94: 2 | AC94: 0 | AD94: 1 | AE94: 0 | AF94: USD | AG94: FALSE | AH94: FALSE | AI94: FALSE | AJ94: FALSE | AK94: FALSE | AL94: FALSE | AN94: 46147 | AO94: AMRR-4DDVKKFOPE | AP94: QA Wrong damage | AR94: nhu.nguyen | AS94: View 4: (11, 14) Damage OLD xác định sai | AT94: FALSE | AU94: TRUE | AV94: FALSE
B95: https://agent-admin.paveapi.com/inspectionView/AMRR-V7LDMEYCL1?activeTab=past-sessions | C95: 3C6URVJG5LE145361 | D95: US | E95: 2020 | F95: Ram | G95: PROMASTER | H95: AMZL | I95: AMZL | J95: DSP Accounts | K95: AMZL | L95: DMSH.user | M95: AMRR-V7LDMEYCL1 | N95: Redeployment/Retirement | O95: COMPLETE | P95: https://dashboard.paveapi.com/park/AMRR-V7LDMEYCL1/?l=en | Q95: 46147.594 | R95: 46147.595 | S95: 100 | T95: 46147.608 | U95: 1298 | V95: 1 | W95: 11927.5 | X95: 11 | Y95: 1 | Z95: 3 | AA95: 3 | AB95: 2 | AC95: 0 | AD95: 0 | AE95: 0 | AF95: USD | AG95: FALSE | AH95: FALSE | AI95: FALSE | AJ95: FALSE | AK95: FALSE | AL95: FALSE | AM95: View 4, 7: Remove false positive damages. / Correct one. | AN95: 46147 | AO95: AMRR-V7LDMEYCL1 | AT95: TRUE | AU95: FALSE | AV95: FALSE
B96: https://agent-admin.paveapi.com/inspectionView/AMWT-UQ3MOCVCYX?activeTab=past-sessions | C96: 3C6URVJGXLE117006 | D96: US | E96: 2020 | F96: Ram | G96: ProMaster | H96: RADS | I96: DCL7 | J96: DSP Accounts | K96: RADS | L96: RADS.user | M96: AMWT-UQ3MOCVCYX | N96: Fleet Improvement Fund | O96: COMPLETE | P96: https://dashboard.paveapi.com/park/AMWT-UQ3MOCVCYX/?l=en | Q96: 46147.576 | R96: 46147.58 | S96: 159 | T96: 46147.589 | U96: 5293 | V96: 3 | W96: 4500 | X96: 1 | Y96: 1 | Z96: 0 | AA96: 2 | AB96: 1 | AC96: 1 | AD96: 0 | AE96: 0 | AF96: USD | AG96: FALSE | AH96: FALSE | AI96: FALSE | AJ96: FALSE | AK96: FALSE | AL96: FALSE | AN96: 46147 | AO96: AMWT-UQ3MOCVCYX | AP96: Agent + QA Wrong damage | AQ96: quang.nguyenthanh | AR96: duy.nguyenquoc | AS96: View 4: (9) Damage OLD đã sửa chữa | AT96: FALSE | AU96: TRUE | AV96: TRUE
B97: https://agent-admin.paveapi.com/inspectionView/AMWT-CY1SEV5MCI?activeTab=past-sessions | C97: 3C6URVJGXLE117006 | D97: US | E97: 2020 | F97: Ram | G97: ProMaster | H97: RADS | I97: DCL7 | J97: DSP Accounts | K97: RADS | L97: RADS.user | M97: AMWT-CY1SEV5MCI | N97: Wear & Tear | O97: COMPLETE | P97: https://dashboard.paveapi.com/park/AMWT-CY1SEV5MCI/?l=en | Q97: 46147.58 | R97: 46147.581 | S97: 64 | T97: 46147.595 | U97: 5845 | V97: 4 | W97: 2125 | X97: 0 | Y97: 1 | Z97: 0 | AA97: 1 | AB97: 1 | AC97: 1 | AD97: 0 | AE97: 0 | AF97: USD | AG97: FALSE | AH97: FALSE | AI97: FALSE | AJ97: FALSE | AK97: FALSE | AL97: FALSE | AM97: View 4, 8: Remove false positive damages. / Correct one. | AN97: 46147 | AO97: AMWT-CY1SEV5MCI | AT97: TRUE | AU97: FALSE | AV97: FALSE
B98: https://agent-admin.paveapi.com/inspectionView/AMWT-ZQS4P2ATOA?activeTab=past-sessions | C98: 7FCEHEB26SN029707 | D98: US | E98: 2025 | F98: Rivian | G98: Delivery | H98: RRLG | I98: DBM5 | J98: DSP Accounts | K98: RRLG | L98: URSA | M98: AMWT-ZQS4P2ATOA | N98: Fleet Improvement Fund | O98: COMPLETE | P98: https://dashboard.paveapi.com/park/AMWT-ZQS4P2ATOA/?l=en | Q98: 46147.767 | R98: 46147.769 | S98: 135 | T98: 46147.771 | U98: 412 | V98: 2 | W98: 7450 | X98: 3 | Y98: 2 | Z98: 3 | AA98: 1 | AB98: 0 | AC98: 0 | AD98: 0 | AE98: 0 | AF98: USD | AG98: FALSE | AH98: FALSE | AI98: FALSE | AJ98: FALSE | AK98: FALSE | AL98: FALSE | AM98: / Correct one. | AN98: 46147 | AO98: AMWT-ZQS4P2ATOA | AT98: TRUE | AU98: FALSE | AV98: FALSE
B99: https://agent-admin.paveapi.com/inspectionView/AMWT-R8OE1ZURCA?activeTab=past-sessions | C99: 7FCEHEB26SN029707 | D99: US | E99: 2025 | F99: Rivian | G99: Delivery | H99: RRLG | I99: DBM5 | J99: DSP Accounts | K99: RRLG | L99: URSA | M99: AMWT-R8OE1ZURCA | N99: Fleet Improvement Fund | O99: COMPLETE | P99: https://dashboard.paveapi.com/park/AMWT-R8OE1ZURCA/?l=en | Q99: 46147.776 | R99: 46147.778 | S99: 180 | T99: 46147.783 | U99: 725 | V99: 3 | W99: 3250 | X99: 1 | Y99: 2 | Z99: 0 | AA99: 1 | AB99: 0 | AC99: 0 | AD99: 0 | AE99: 0 | AF99: USD | AG99: FALSE | AH99: FALSE | AI99: FALSE | AJ99: FALSE | AK99: FALSE | AL99: FALSE | AM99: View 4, 7: Repaired. / Correct one. | AN99: 46147 | AO99: AMWT-R8OE1ZURCA | AT99: TRUE | AU99: FALSE | AV99: FALSE
B100: https://agent-admin.paveapi.com/inspectionView/AMWT-ZAABQNLXZJ?activeTab=past-sessions | C100: 7FCEHEB26SN029707 | D100: US | E100: 2025 | F100: Rivian | G100: DELIVERY | H100: RRLG | I100: DBM5 | J100: DSP Accounts | K100: RRLG | L100: RRLG.David | M100: AMWT-ZAABQNLXZJ | N100: Wear & Tear | O100: COMPLETE | P100: https://dashboard.paveapi.com/park/AMWT-ZAABQNLXZJ/?l=en | Q100: 46147.795 | R100: 46147.797 | S100: 123 | T100: 46147.802 | U100: 22020 | V100: 3 | W100: 2675 | X100: 1 | Y100: 2 | Z100: 0 | AA100: 0 | AB100: 0 | AC100: 0 | AD100: 0 | AE100: 0 | AF100: USD | AG100: FALSE | AH100: FALSE | AI100: FALSE | AJ100: FALSE | AK100: FALSE | AL100: FALSE | AM100: View 8: Remove false positive damages. / Correct one. | AN100: 46147 | AO100: AMWT-ZAABQNLXZJ | AT100: TRUE | AU100: FALSE | AV100: FALSE
...

Sheet CONFIG
B1: Name | C1: User account | D1: Role
B2: Cao Đức Hiếu | C2: hieu.cao | D2: QA
B3: Huỳnh Thị Mỹ Kim | C3: kim.huynh | D3: QA | F3: ALL Miss Damage
B4: Nguyễn Lê Như Ý | C4: y.nguyen | D4: QA | F4: ALL Wrong Damage
B5: Hồ Thị Hải Yến | C5: yen.ho | D5: QA | F5: CC/AD Miss Damage
B6: Phạm Hà Duy Tân | C6: tan.pham | D6: QA | F6: CC/AD Wrong damage
B7: Lê Khả Nhi | C7: nhi.le | D7: QA | F7: Checker Miss Damage
B8: Mai Hà Bảo Trâm | C8: tram.mai | D8: QA | F8: Checker Wrong damage
B9: Hồ Tấn Phúc | C9: phuc.ho | D9: QA | F9: Checker + CC/AD Miss Damage
B10: Nguyễn Hoàng Duy Khang | C10: khang.nguyen | D10: QA | F10: Checker + CC/AD Wrong damage
B11: Bùi Nhật Anh | C11: anh.bui | D11: QA | F11: Inspector + CC/AD Miss Damage
B12: Thái Thị Thanh Linh | C12: linh.thai | D12: QA | F12: Inspector + CC/AD Wrong damage
B13: Nguyễn Phạm Thanh Bình | C13: binh.nguyen | D13: QA | F13: Inspector + Checker Miss Damage
B14: Nguyễn Thị Hòa | C14: hoa.nguyenthi | D14: QA | F14: Inspector + Checker Wrong damage
... B18: Huỳnh Tuyết Ngân | C18: ngan.huynhtuyet | D18: QA | F18: Other
B19: Nguyễn Mai Khánh Tâm | C19: tam.nguyenmaikhanh | D19: QA
B20: Lê Thị Quỳnh Như | C20: nhu.le | D20: QA
B21: Nguyễn Hữu Thiện | C21: thien.nguyen | D21: QA
B22: Nguyễn Thị Ánh Mỹ | C22: my.nguyen | D22: QA
B23: Nguyễn Văn Trưởng | C23: truong.nguyen | D23: QA
B24: Bùi Trọng Sơn | C24: son.bui | D24: QA
B25: Nguyễn Anh Vũ | C25: vu.nguyen | D25: QA
B26: Phan Xuân Thịnh | C26: thinh.phanxuan | D26: QA
B27: Võ Anh Kiệt | C27: kiet.voanh | D27: QA
B28: Ân Hồng Kim Ý | C28: y.anhongkim | D28: QA
B29: Lương Thị Ngân | C29: ngan.luongthi | D29: QA
B30: Lư Quang Trực | C30: truc.luquang | D30: QA
... B116: Trịnh Mỹ Nhân | C116: nhan.trinh | D116: TT

Sheet PERF_TEMPLATE
E1: DAMAGE FAILED | T1: PERSON RESPONSIBLE | Z1: ACCURACY
A2: Date | C2: Sessions | D2: {={"LINK SESSION"; IF(C3:C1210 = "", "", "https://agent-admin.paveapi.com/inspectionView/" & C3:C1210 & "?activeTab=past-sessions")}} -> LINK SESSION | E2: Left Side | H2: Front Side | K2: Right Side | N2: Back Side | Q2: Other Side | T2: Inspect | U2: Check | V2: Cross-Check/Admin | W2: RE-CHECK & NOTE | X2: Reason | Y2: Total Dmg Missing (Session) | Z2: Inspect | AB2: Check | AD2: Cross-Check/Admin | AF2: Total Damage | AH2: AUDITOR
E3: Inspect | F3: Check | G3: Cross-Check/Admin | H3: Inspect | I3: Check | J3: Cross-Check/Admin | K3: Inspect | L3: Check | M3: Cross-Check/Admin | N3: Inspect | O3: Check | P3: Cross-Check/Admin | Q3: Inspect | R3: Check | S3: Cross-Check/Admin | Z3: =IFERROR(__xludf.DUMMYFUNCTION("{""Mistakes"";ARRAYFORMULA(IF((T4:T1210 <> """") * (T4:T1210 <> ""developer"") * (X4:X1210 <> """"), IF(REGEXMATCH(X4:X1210, ""Inspector|ALL|Other""), N(E4:E1210) + N(H4:H1210) + N(K4:K1210) + N(N4:N1210) + N(Q4:Q1210), 0), """"))}"),"Mistakes") -> Mistakes | AA3: =IFERROR(__xludf.DUMMYFUNCTION("{""%"";ARRAYFORMULA(IF((T4:T1210 = """") + (X4:X1210 = """"), """", IF(T4:T1210 = ""developer"", """", IFERROR(IF(REGEXMATCH($X$4:$X1210, ""(ALL|Inspector).*Miss Damage""), 1 - Z4:Z1210 / ((($AF$4:$AF1210 + $AG$4:$AG1210 + ABS($AF$4:$AF1210 - $AG$4:$AG121"&"0)) / 2) + $Y$4:$Y1210), 1 - Z4:Z1210 / (($AF$4:$AF1210 + $AG$4:$AG1210 + ABS($AF$4:$AF1210 - $AG$4:$AG1210)) / 2)), 1))))}"),"%") -> % | AB3: =IFERROR(__xludf.DUMMYFUNCTION("{""Mistakes""; ARRAYFORMULA(IF((U4:U1210 = """") + ($X$4:$X1210 = """"), """", IF(REGEXMATCH($X$4:$X1210, ""Checker|ALL|Other""), N(F4:F1210) + N(I4:I1210) + N(L4:L1210) + N(O4:O1210) + N(R4:R1210), 0)))}"),"Mistakes") -> Mistakes | AC3: =IFERROR(__xludf.DUMMYFUNCTION("{""%""; ARRAYFORMULA(IF((U4:U1210 = """") + ($X$4:$X1210 = """"), """", IFERROR(IF(REGEXMATCH($X$4:$X1210, ""(ALL|Checker).*Miss Damage""), 1 - AB4:AB1210 / ((($AF$4:$AF1210 + $AG$4:$AG1210 + ABS($AF$4:$AF1210 - $AG$4:$AG1210)) / 2) + $Y$4:$Y1210), 1 - AB"&"4:AB1210 / ((($AF$4:$AF1210 + $AG$4:$AG1210 + ABS($AF$4:$AF1210 - $AG$4:$AG1210)) / 2))), 1)))}"),"%") -> % | AD3: =IFERROR(__xludf.DUMMYFUNCTION("{""Mistakes""; ARRAYFORMULA(IF((V4:V1210 = """") + (X4:X1210 = """"), """", IF(REGEXMATCH(X4:X1210, ""CC/AD|ALL|Other""), N(G4:G1210) + N(J4:J1210) + N(M4:M1210) + N(P4:P1210) + N(S4:S1210), 0)))}"),"Mistakes") -> Mistakes | AE3: =IFERROR(__xludf.DUMMYFUNCTION("{""%"";ARRAYFORMULA(IF((V4:V1210 = """") + ($X$4:$X1210 = """"), """", IFERROR(IF(REGEXMATCH($X$4:$X1210, ""ALL Miss Damage|.*CC/AD Miss Damage""), 1 - AD4:AD1210 / ((($AF$4:$AF1210 + $AG$4:$AG1210 + ABS($AF$4:$AF1210 - $AG$4:$AG1210)) / 2) + $Y$4:$Y1210)"&", 1 - AD4:AD1210 / (($AF$4:$AF1210 + $AG$4:$AG1210 + ABS($AF$4:$AF1210 - $AG$4:$AG1210)) / 2)), 1)))}"),"%") -> % | AF3: BEFORE | AG3: FINAL
A4: 0501-1hrs_NA | B4: 46143 | C4: AMWT-VBAPZIS7EW | D4: https://agent-admin.paveapi.com/inspectionView/AMWT-VBAPZIS7EW?activeTab=past-sessions | F4: 1 | L4: 1 | T4: developer | U4: thien.ht | W4: View 4: (3) Damage OLD xác định sai ( trầy nông) View 7: Missing Major Dent ở Front Door (ví dụ) | X4: Checker Wrong damage, Checker Miss Damage | Y4: 1 | Z4: =IFERROR(__xludf.DUMMYFUNCTION("""COMPUTED_VALUE"""),"") | AA4: =IFERROR(__xludf.DUMMYFUNCTION("""COMPUTED_VALUE"""),"") | AB4: =IFERROR(__xludf.DUMMYFUNCTION("""COMPUTED_VALUE"""),2.0) -> 2 | AC4: =IFERROR(__xludf.DUMMYFUNCTION("""COMPUTED_VALUE"""),0.9130434782608696) -> 0.91304348 | AD4: =IFERROR(__xludf.DUMMYFUNCTION("""COMPUTED_VALUE"""),"") | AE4: =IFERROR(__xludf.DUMMYFUNCTION("""COMPUTED_VALUE"""),"") | AF4: 22 | AG4: 4
B5: 46143 | C5: AMWT-4OBMFH3IF8 | D5: https://agent-admin.paveapi.com/inspectionView/AMWT-4OBMFH3IF8?activeTab=past-sessions | T5: developer | U5: thinh.phanxuan | V5: trinh.ho | Z5: =IFERROR(__xludf.DUMMYFUNCTION("""COMPUTED_VALUE"""),"") | AA5: =IFERROR(__xludf.DUMMYFUNCTION("""COMPUTED_VALUE"""),"") | AB5: =IFERROR(__xludf.DUMMYFUNCTION("""COMPUTED_VALUE"""),"") | AC5: =IFERROR(__xludf.DUMMYFUNCTION("""COMPUTED_VALUE"""),"") | AD5: =IFERROR(__xludf.DUMMYFUNCTION("""COMPUTED_VALUE"""),"") | AE5: =IFERROR(__xludf.DUMMYFUNCTION("""COMPUTED_VALUE"""),"") | AF5: 4 | AG5: 3
A6: 0507-1hrs_NA | B6: 46149 | C6: AMWT-LMLUSZZIS2 | D6: https://agent-admin.paveapi.com/inspectionView/AMWT-LMLUSZZIS2?activeTab=past-sessions | P6: 1 | T6: developer | V6: hoang.nguyentuyen | W6: View 8: (2) Damage NEW xác định sai | X6: CC/AD Wrong damage | Z6: =IFERROR(__xludf.DUMMYFUNCTION("""COMPUTED_VALUE"""),"") | AA6: =IFERROR(__xludf.DUMMYFUNCTION("""COMPUTED_VALUE"""),"") | AB6: =IFERROR(__xludf.DUMMYFUNCTION("""COMPUTED_VALUE"""),"") | AC6: =IFERROR(__xludf.DUMMYFUNCTION("""COMPUTED_VALUE"""),"") | AD6: =IFERROR(__xludf.DUMMYFUNCTION("""COMPUTED_VALUE"""),1.0) -> 1 | AE6: =IFERROR(__xludf.DUMMYFUNCTION("""COMPUTED_VALUE"""),0.9285714285714286) -> 0.92857143 | AF6: 14 | AG6: 6
Z7: =IFERROR(__xludf.DUMMYFUNCTION("""COMPUTED_VALUE"""),"") | AA7: =IFERROR(__xludf.DUMMYFUNCTION("""COMPUTED_VALUE"""),"") | AB7: =IFERROR(__xludf.DUMMYFUNCTION("""COMPUTED_VALUE"""),"") | AC7: =IFERROR(__xludf.DUMMYFUNCTION("""COMPUTED_VALUE"""),"") | AD7: =IFERROR(__xludf.DUMMYFUNCTION("""COMPUTED_VALUE"""),"") | AE7: =IFERROR(__xludf.DUMMYFUNCTION("""COMPUTED_VALUE"""),"")
Z8: =IFERROR(__xludf.DUMMYFUNCTION("""COMPUTED_VALUE"""),"") | AA8: =IFERROR(__xludf.DUMMYFUNCTION("""COMPUTED_VALUE"""),"") | AB8: =IFERROR(__xludf.DUMMYFUNCTION("""COMPUTED_VALUE"""),"") | AC8: =IFERROR(__xludf.DUMMYFUNCTION("""COMPUTED_VALUE"""),"") | AD8: =IFERROR(__xludf.DUMMYFUNCTION("""COMPUTED_VALUE"""),"") | AE8: =IFERROR(__xludf.DUMMYFUNCTION("""COMPUTED_VALUE"""),"")
Z9: =IFERROR(__xludf.DUMMYFUNCTION("""COMPUTED_VALUE"""),"") | AA9: =IFERROR(__xludf.DUMMYFUNCTION("""COMPUTED_VALUE"""),"") | AB9: =IFERROR(__xludf.DUMMYFUNCTION("""COMPUTED_VALUE"""),"") | AC9: =IFERROR(__xludf.DUMMYFUNCTION("""COMPUTED_VALUE"""),"") | AD9: =IFERROR(__xludf.DUMMYFUNCTION("""COMPUTED_VALUE"""),"") | AE9: =IFERROR(__xludf.DUMMYFUNCTION("""COMPUTED_VALUE"""),"")
Z10: =IFERROR(__xludf.DUMMYFUNCTION("""COMPUTED_VALUE"""),"") | AA10: =IFERROR(__xludf.DUMMYFUNCTION("""COMPUTED_VALUE"""),"") | AB10: =IFERROR(__xludf.DUMMYFUNCTION("""COMPUTED_VALUE"""),"") | AC10: =IFERROR(__xludf.DUMMYFUNCTION("""COMPUTED_VALUE"""),"") | AD10: =IFERROR(__xludf.DUMMYFUNCTION("""COMPUTED_VALUE"""),"") | AE10: =IFERROR(__xludf.DUMMYFUNCTION("""COMPUTED_VALUE"""),"")
Z11: =IFERROR(__xludf.DUMMYFUNCTION("""COMPUTED_VALUE"""),"") | AA11: =IFERROR(__xludf.DUMMYFUNCTION("""COMPUTED_VALUE"""),"") | AB11: =IFERROR(__xludf.DUMMYFUNCTION("""COMPUTED_VALUE"""),"") | AC11: =IFERROR(__xludf.DUMMYFUNCTION("""COMPUTED_VALUE"""),"") | AD11: =IFERROR(__xludf.DUMMYFUNCTION("""COMPUTED_VALUE"""),"") | AE11: =IFERROR(__xludf.DUMMYFUNCTION("""COMPUTED_VALUE"""),"")
Z12: =IFERROR(__xludf.DUMMYFUNCTION("""COMPUTED_VALUE"""),"") | AA12: =IFERROR(__xludf.DUMMYFUNCTION("""COMPUTED_VALUE"""),"") | AB12: =IFERROR(__xludf.DUMMYFUNCTION("""COMPUTED_VALUE"""),"") | AC12: =IFERROR(__xludf.DUMMYFUNCTION("""COMPUTED_VALUE"""),"") | AD12: =IFERROR(__xludf.DUMMYFUNCTION("""COMPUTED_VALUE"""),"") | AE12: =IFERROR(__xludf.DUMMYFUNCTION("""COMPUTED_VALUE"""),"")
Z13: =IFERROR(__xludf.DUMMYFUNCTION("""COMPUTED_VALUE"""),"") | AA13: =IFERROR(__xludf.DUMMYFUNCTION("""COMPUTED_VALUE"""),"") | AB13: =IFERROR(__xludf.DUMMYFUNCTION("""COMPUTED_VALUE"""),"") | AC13: =IFERROR(__xludf.DUMMYFUNCTION("""COMPUTED_VALUE"""),"") | AD13: =IFERROR(__xludf.DUMMYFUNCTION("""COMPUTED_VALUE"""),"") | AE13: =IFERROR(__xludf.DUMMYFUNCTION("""COMPUTED_VALUE"""),"")
Z14: =IFERROR(__xludf.DUMMYFUNCTION("""COMPUTED_VALUE"""),"") | AA14: =IFERROR(__xludf.DUMMYFUNCTION("""COMPUTED_VALUE"""),"") | AB14: =IFERROR(__xludf.DUMMYFUNCTION("""COMPUTED_VALUE"""),"") | AC14: =IFERROR(__xludf.DUMMYFUNCTION("""COMPUTED_VALUE"""),"") | AD14: =IFERROR(__xludf.DUMMYFUNCTION("""COMPUTED_VALUE"""),"") | AE14: =IFERROR(__xludf.DUMMYFUNCTION("""COMPUTED_VALUE"""),"")
Z15: =IFERROR(__xludf.DUMMYFUNCTION("""COMPUTED_VALUE"""),"") | AA15: =IFERROR(__xludf.DUMMYFUNCTION("""COMPUTED_VALUE"""),"") | AB15: =IFERROR(__xludf.DUMMYFUNCTION("""COMPUTED_VALUE"""),"") | AC15: =IFERROR(__xludf.DUMMYFUNCTION("""COMPUTED_VALUE"""),"") | AD15: =IFERROR(__xludf.DUMMYFUNCTION("""COMPUTED_VALUE"""),"") | AE15: =IFERROR(__xludf.DUMMYFUNCTION("""COMPUTED_VALUE"""),"")
Z16: =IFERROR(__xludf.DUMMYFUNCTION("""COMPUTED_VALUE"""),"") | AA16: =IFERROR(__xludf.DUMMYFUNCTION("""COMPUTED_VALUE"""),"") | AB16: =IFERROR(__xludf.DUMMYFUNCTION("""COMPUTED_VALUE"""),"") | AC16: =IFERROR(__xludf.DUMMYFUNCTION("""COMPUTED_VALUE"""),"") | AD16: =IFERROR(__xludf.DUMMYFUNCTION("""COMPUTED_VALUE"""),"") | AE16: =IFERROR(__xludf.DUMMYFUNCTION("""COMPUTED_VALUE"""),"")
Z17: =IFERROR(__xludf.DUMMYFUNCTION("""COMPUTED_VALUE"""),"") | AA17: =IFERROR(__xludf.DUMMYFUNCTION("""COMPUTED_VALUE"""),"") | AB17: =IFERROR(__xludf.DUMMYFUNCTION("""COMPUTED_VALUE"""),"") | AC17: =IFERROR(__xludf.DUMMYFUNCTION("""COMPUTED_VALUE"""),"") | AD17: =IFERROR(__xludf.DUMMYFUNCTION("""COMPUTED_VALUE"""),"") | AE17: =IFERROR(__xludf.DUMMYFUNCTION("""COMPUTED_VALUE"""),"")
Z18: =IFERROR(__xludf.DUMMYFUNCTION("""COMPUTED_VALUE"""),"") | AA18: =IFERROR(__xludf.DUMMYFUNCTION("""COMPUTED_VALUE"""),"") | AB18: =IFERROR(__xludf.DUMMYFUNCTION("""COMPUTED_VALUE"""),"") | AC18: =IFERROR(__xludf.DUMMYFUNCTION("""COMPUTED_VALUE"""),"") | AD18: =IFERROR(__xludf.DUMMYFUNCTION("""COMPUTED_VALUE"""),"") | AE18: =IFERROR(__xludf.DUMMYFUNCTION("""COMPUTED_VALUE"""),"")
... Z1210: =IFERROR(__xludf.DUMMYFUNCTION("""COMPUTED_VALUE"""),"") | AA1210: =IFERROR(__xludf.DUMMYFUNCTION("""COMPUTED_VALUE"""),"") | AB1210: =IFERROR(__xludf.DUMMYFUNCTION("""COMPUTED_VALUE"""),"") | AC1210: =IFERROR(__xludf.DUMMYFUNCTION("""COMPUTED_VALUE"""),"") | AD1210: =IFERROR(__xludf.DUMMYFUNCTION("""COMPUTED_VALUE"""),"") | AE1210: =IFERROR(__xludf.DUMMYFUNCTION("""COMPUTED_VALUE"""),"")

Sheet PERF_W20
E1: DAMAGE FAILED | T1: PERSON RESPONSIBLE | X1: =COUNTIF(X4:X650,"<>") -> 468 | Y1: ACCURACY
B2: DATE | C2: Sessions | D2: {={"LINK SESSION"; IF(C3:C650 = "", "", "https://agent-admin.paveapi.com/inspectionView/" & C3:C650 & "?activeTab=past-sessions")}} -> LINK SESSION | E2: Left Side | H2: Front Side | K2: Right Side | N2: Back Side | Q2: Other Side | T2: Inspect | U2: Check | V2: Cross-Check/Admin | W2: RE-CHECK & NOTE | X2: Reason | Y2: Inspect | AA2: Check | AC2: Cross-Check/Admin | AE2: Total Damage | AG2: AUDITOR
E3: Inspect | F3: Check | G3: Cross-Check/Admin | H3: Inspect | I3: Check | J3: Cross-Check/Admin | K3: Inspect | L3: Check | M3: Cross-Check/Admin | N3: Inspect | O3: Check | P3: Cross-Check/Admin | Q3: Inspect | R3: Check | S3: Cross-Check/Admin | Y3: {={"Mistakes";IF((T4:T650 <> "") * (T4:T650 <> "developer") * (X4:X650 <> ""), IF(ISNUMBER(MATCH(X4:X650, {"ALL Miss Damage"; "ALL Wrong Damage"; "Inspector + CC/AD Miss Damage"; "Inspector + CC/AD Wrong damage"; "Inspector + Checker Miss Damage"; "Inspector + Checker Wrong damage"; "Inspector Miss Damage"; "Inspector Wrong damage"; "Other"}, 0)), N(E4:E650) + N(H4:H650) + N(K4:K650) + N(N4:N650) + N(Q4:Q650), 0), "")}} -> Mistakes | Z3: =IFERROR(__xludf.DUMMYFUNCTION("{""%"";ARRAYFORMULA(IF((T4:T650 = """") + (X4:X650 = """"), """", IF(T4:T650 = ""developer"", """", IFERROR(IF(REGEXMATCH(LOWER($X$4:$X650), ""miss damage""), 1 - Y4:Y650 / ((($AE$4:$AE650 + $AF$4:$AF650 + ABS($AE$4:$AE650 - $AF$4:$AF650)) / 2) + Y4:Y650)"&", 1 - Y4:Y650 / (($AE$4:$AE650 + $AF$4:$AF650 + ABS($AE$4:$AE650 - $AF$4:$AF650)) / 2)), 1))))}"),"%") -> % | AA3: {={"Mistakes"; IF((U4:U650 = "") + (X4:X650 = ""), "", IF(ISNUMBER(MATCH(X4:X650, {"ALL Miss Damage"; "ALL Wrong Damage"; "Checker Miss Damage"; "Checker Wrong damage"; "Checker + CC/AD Miss Damage"; "Checker + CC/AD Wrong damage"; "Inspector + Checker Miss Damage"; "Inspector + Checker Wrong damage"; "Other"}, 0)), N(F4:F650) + N(I4:I650) + N(L4:L650) + N(O4:O650) + N(R4:R650), 0))}} -> Mistakes | AB3: =IFERROR(__xludf.DUMMYFUNCTION("{""%"";ARRAYFORMULA(IF((U4:U650 = """") + (X4:X650 = """"), """", IFERROR(IF(REGEXMATCH(LOWER($X$4:$X650), ""miss damage""), 1 - AA4:AA650 / ((($AE$4:$AE650 + $AF$4:$AF650 + ABS($AE$4:$AE650 - $AF$4:$AF650)) / 2) + AA4:AA650), 1 - AA4:AA650 / (($AE$4:$AE6"&"50 + $AF$4:$AF650 + ABS($AE$4:$AE650 - $AF$4:$AF650)) / 2)), 1)))}"),"%") -> % | AC3: {={"Mistakes"; IF((V4:V650 = "") + (X4:X650 = ""), "", IF(ISNUMBER(MATCH(X4:X650, {"ALL Miss Damage"; "ALL Wrong Damage"; "CC/AD Miss Damage"; "CC/AD Wrong damage"; "Checker + CC/AD Miss Damage"; "Checker + CC/AD Wrong damage" ; "Inspector + CC/AD Miss Damage"; "Inspector + CC/AD Wrong damage"; "Other"}, 0)), N(G4:G650) + N(J4:J650) + N(M4:M650) + N(P4:P650) + N(S4:S650), 0))}} -> Mistakes | AD3: =IFERROR(__xludf.DUMMYFUNCTION("{""%"";ARRAYFORMULA(IF((V4:V650 = """") + (X4:X650 = """"), """", IFERROR(IF(REGEXMATCH(LOWER($X$4:$X650), ""miss damage""), 1 - AC4:AC650 / ((($AE$4:$AE650 + $AF$4:$AF650 + ABS($AE$4:$AE650 - $AF$4:$AF650)) / 2) + AC4:AC650), 1 - AC4:AC650 / (($AE$4:$AE6"&"50 + $AF$4:$AF650 + ABS($AE$4:$AE650 - $AF$4:$AF650)) / 2)), 1)))}"),"%") -> % | AE3: BEFORE | AF3: FINAL
B4: 46153 | C4: AMWT-IZZK98BHX8 | D4: https://agent-admin.paveapi.com/inspectionView/AMWT-IZZK98BHX8?activeTab=past-sessions | F4: 1 | L4: 1 | O4: 3 | T4: developer | U4: an.nguyen | W4: View 4: (14) Damage OLD đã sửa chữa View 8: (2, 3, 6) Damage OLD đã sửa chữa View 7: (20) Damage NEW xác định sai | X4: Checker Wrong damage | Z4: =IFERROR(__xludf.DUMMYFUNCTION("""COMPUTED_VALUE"""),"") | AA4: 5 | AB4: =IFERROR(__xludf.DUMMYFUNCTION("""COMPUTED_VALUE"""),0.8913043478260869) -> 0.89130435 | AD4: =IFERROR(__xludf.DUMMYFUNCTION("""COMPUTED_VALUE"""),"") | AE4: 46 | AF4: 14
B5: 46153 | C5: AMWT-MKGKOJFNIY | D5: https://agent-admin.paveapi.com/inspectionView/AMWT-MKGKOJFNIY?activeTab=past-sessions | T5: developer | U5: kim.huynh | V5: danh.huynh | X5: None | Z5: =IFERROR(__xludf.DUMMYFUNCTION("""COMPUTED_VALUE"""),"") | AA5: 0 | AB5: =IFERROR(__xludf.DUMMYFUNCTION("""COMPUTED_VALUE"""),1.0) -> 1 | AC5: 0 | AD5: =IFERROR(__xludf.DUMMYFUNCTION("""COMPUTED_VALUE"""),1.0) -> 1 | AE5: 14 | AF5: 10
B6: 46153 | C6: AMWT-UW1ZEONGE9 | D6: https://agent-admin.paveapi.com/inspectionView/AMWT-UW1ZEONGE9?activeTab=past-sessions | T6: developer | U6: son.bui | V6: danh.huynh | X6: None | Z6: =IFERROR(__xludf.DUMMYFUNCTION("""COMPUTED_VALUE"""),"") | AA6: 0 | AB6: =IFERROR(__xludf.DUMMYFUNCTION("""COMPUTED_VALUE"""),1.0) -> 1 | AC6: 0 | AD6: =IFERROR(__xludf.DUMMYFUNCTION("""COMPUTED_VALUE"""),1.0) -> 1 | AE6: 11 | AF6: 9
B7: 46153 | C7: AMWT-C4RJDG2OSA | D7: https://agent-admin.paveapi.com/inspectionView/AMWT-C4RJDG2OSA?activeTab=past-sessions | T7: huy.tran | U7: thanhha.tran | X7: None | Y7: 0 | Z7: =IFERROR(__xludf.DUMMYFUNCTION("""COMPUTED_VALUE"""),1.0) -> 1 | AA7: 0 | AB7: =IFERROR(__xludf.DUMMYFUNCTION("""COMPUTED_VALUE"""),1.0) -> 1 | AD7: =IFERROR(__xludf.DUMMYFUNCTION("""COMPUTED_VALUE"""),"") | AE7: 3 | AF7: 2
B8: 46153 | C8: AMWT-HKX2NVABEU | D8: https://agent-admin.paveapi.com/inspectionView/AMWT-HKX2NVABEU?activeTab=past-sessions | T8: thuy.ngodiem | U8: thanhha.tran | V8: cuong.pham | W8: Xóa damage ID trước đánh nghi ngờ | X8: None | Y8: 0 | Z8: =IFERROR(__xludf.DUMMYFUNCTION("""COMPUTED_VALUE"""),1.0) -> 1 | AA8: 0 | AB8: =IFERROR(__xludf.DUMMYFUNCTION("""COMPUTED_VALUE"""),1.0) -> 1 | AC8: 0 | AD8: =IFERROR(__xludf.DUMMYFUNCTION("""COMPUTED_VALUE"""),1.0) -> 1 | AE8: 2 | AF8: 0
B9: 46153 | C9: AMWT-XRQNZPENHF | D9: https://agent-admin.paveapi.com/inspectionView/AMWT-XRQNZPENHF?activeTab=past-sessions | T9: duy.nk | U9: nhi.le | X9: None | Y9: 0 | Z9: =IFERROR(__xludf.DUMMYFUNCTION("""COMPUTED_VALUE"""),1.0) -> 1 | AA9: 0 | AB9: =IFERROR(__xludf.DUMMYFUNCTION("""COMPUTED_VALUE"""),1.0) -> 1 | AD9: =IFERROR(__xludf.DUMMYFUNCTION("""COMPUTED_VALUE"""),"") | AE9: 32 | AF9: 9
B10: 46153 | C10: AMWT-UORN9VRMOC | D10: https://agent-admin.paveapi.com/inspectionView/AMWT-UORN9VRMOC?activeTab=past-sessions | T10: tho.nh | U10: an.nguyen | V10: sang.tran | W10: Xóa damage ID trước đánh nghi ngờ | X10: None | Y10: 0 | Z10: =IFERROR(__xludf.DUMMYFUNCTION("""COMPUTED_VALUE"""),1.0) -> 1 | AA10: 0 | AB10: =IFERROR(__xludf.DUMMYFUNCTION("""COMPUTED_VALUE"""),1.0) -> 1 | AC10: 0 | AD10: =IFERROR(__xludf.DUMMYFUNCTION("""COMPUTED_VALUE"""),1.0) -> 1 | AE10: 10 | AF10: 6
B11: 46153 | C11: AMWT-D7CU8TCF5Z | D11: https://agent-admin.paveapi.com/inspectionView/AMWT-D7CU8TCF5Z?activeTab=past-sessions | O11: 1 | T11: developer | U11: que.nguyenthihong | W11: View 8: (4) Damage OLD đã sửa chữa | X11: Checker Wrong damage | Z11: =IFERROR(__xludf.DUMMYFUNCTION("""COMPUTED_VALUE"""),"") | AA11: 1 | AB11: =IFERROR(__xludf.DUMMYFUNCTION("""COMPUTED_VALUE"""),0.9166666666666666) -> 0.91666667 | AD11: =IFERROR(__xludf.DUMMYFUNCTION("""COMPUTED_VALUE"""),"") | AE11: 12 | AF11: 4
B12: 46153 | C12: AMWT-LQYYGFMDI0 | D12: https://agent-admin.paveapi.com/inspectionView/AMWT-LQYYGFMDI0?activeTab=past-sessions | T12: developer | U12: nhu.le | V12: huyhien.nguyen | W12: View 7: (1) Damage OLD kích thước nhỏ -> skip ok | X12: None | Z12: =IFERROR(__xludf.DUMMYFUNCTION("""COMPUTED_VALUE"""),"") | AA12: 0 | AB12: =IFERROR(__xludf.DUMMYFUNCTION("""COMPUTED_VALUE"""),1.0) -> 1 | AC12: 0 | AD12: =IFERROR(__xludf.DUMMYFUNCTION("""COMPUTED_VALUE"""),1.0) -> 1 | AE12: 5 | AF12: 2
B13: 46154 | C13: AMWT-06O0KM5HY9 | D13: https://agent-admin.paveapi.com/inspectionView/AMWT-06O0KM5HY9?activeTab=past-sessions | T13: developer | U13: huy.tran | X13: None | Z13: =IFERROR(__xludf.DUMMYFUNCTION("""COMPUTED_VALUE"""),"") | AA13: 0 | AB13: =IFERROR(__xludf.DUMMYFUNCTION("""COMPUTED_VALUE"""),1.0) -> 1 | AD13: =IFERROR(__xludf.DUMMYFUNCTION("""COMPUTED_VALUE"""),"") | AE13: 2 | AF13: 2
B14: 46154 | C14: AMWT-F3ZN6GY5IO | D14: https://agent-admin.paveapi.com/inspectionView/AMWT-F3ZN6GY5IO?activeTab=past-sessions | T14: developer | U14: ngan.huynhtuyet | V14: tong.nguyen | W14: Xóa damage ID trước đánh nghi ngờ | X14: None | Z14: =IFERROR(__xludf.DUMMYFUNCTION("""COMPUTED_VALUE"""),"") | AA14: 0 | AB14: =IFERROR(__xludf.DUMMYFUNCTION("""COMPUTED_VALUE"""),1.0) -> 1 | AC14: 0 | AD14: =IFERROR(__xludf.DUMMYFUNCTION("""COMPUTED_VALUE"""),1.0) -> 1 | AE14: 2 | AF14: 1
B15: 46154 | C15: AMWT-VBXLEAI2GP | D15: https://agent-admin.paveapi.com/inspectionView/AMWT-VBXLEAI2GP?activeTab=past-sessions | F15: 1 | L15: 1 | O15: 1 | T15: developer | U15: nam.nguyendinh | W15: View 4: (9) Damage OLD kích thước nhỏ View 7: (5) Damage OLD kích thước nhỏ View 8: (3) Damage OLD kích thước nhỏ | X15: Checker Wrong damage | Z15: =IFERROR(__xludf.DUMMYFUNCTION("""COMPUTED_VALUE"""),"") | AA15: 3 | AB15: =IFERROR(__xludf.DUMMYFUNCTION("""COMPUTED_VALUE"""),0.8571428571428572) -> 0.85714286 | AD15: =IFERROR(__xludf.DUMMYFUNCTION("""COMPUTED_VALUE"""),"") | AE15: 21 | AF15: 10
B16: 46154 | C16: AMRR-HFMYLBSUCM | D16: https://agent-admin.paveapi.com/inspectionView/AMRR-HFMYLBSUCM?activeTab=past-sessions | T16: developer | U16: thao.phan | V16: danh.huynh | X16: None | Z16: =IFERROR(__xludf.DUMMYFUNCTION("""COMPUTED_VALUE"""),"") | AA16: 0 | AB16: =IFERROR(__xludf.DUMMYFUNCTION("""COMPUTED_VALUE"""),1.0) -> 1 | AC16: 0 | AD16: =IFERROR(__xludf.DUMMYFUNCTION("""COMPUTED_VALUE"""),1.0) -> 1 | AE16: 10 | AF16: 7
B17: 46154 | C17: AMWT-EA2OIU0MPB | D17: https://agent-admin.paveapi.com/inspectionView/AMWT-EA2OIU0MPB?activeTab=past-sessions | I17: 1 | O17: 1 | T17: developer | U17: nhi.le | W17: View 5: (1) Damage OLD xác định sai View 8: (2) Damage OLD xác định sai | X17: Checker Wrong damage | Z17: =IFERROR(__xludf.DUMMYFUNCTION("""COMPUTED_VALUE"""),"") | AA17: 2 | AB17: =IFERROR(__xludf.DUMMYFUNCTION("""COMPUTED_VALUE"""),0.9130434782608696) -> 0.91304348 | AD17: =IFERROR(__xludf.DUMMYFUNCTION("""COMPUTED_VALUE"""),"") | AE17: 23 | AF17: 23
B18: 46154 | C18: AMWT-XGITTHQWMY | D18: https://agent-admin.paveapi.com/inspectionView/AMWT-XGITTHQWMY?activeTab=past-sessions | T18: developer | U18: tho.nh | V18: danh.huynh | X18: None | Z18: =IFERROR(__xludf.DUMMYFUNCTION("""COMPUTED_VALUE"""),"") | AA18: 0 | AB18: =IFERROR(__xludf.DUMMYFUNCTION("""COMPUTED_VALUE"""),1.0) -> 1 | AC18: 0 | AD18: =IFERROR(__xludf.DUMMYFUNCTION("""COMPUTED_VALUE"""),1.0) -> 1 | AE18: 24 | AF18: 21
B19: 46154 | C19: AMWT-BOHVMSMU0R | D19: https://agent-admin.paveapi.com/inspectionView/AMWT-BOHVMSMU0R?activeTab=past-sessions | T19: developer | U19: son.bui | X19: None | Z19: =IFERROR(__xludf.DUMMYFUNCTION("""COMPUTED_VALUE"""),"") | AA19: 0 | AB19: =IFERROR(__xludf.DUMMYFUNCTION("""COMPUTED_VALUE"""),1.0) -> 1 | AD19: =IFERROR(__xludf.DUMMYFUNCTION("""COMPUTED_VALUE"""),"") | AE19: 18 | AF19: 14
B20: 46154 | C20: AMWT-IWCNM0XMGN | D20: https://agent-admin.paveapi.com/inspectionView/AMWT-IWCNM0XMGN?activeTab=past-sessions | T20: developer | U20: luu.nguyendinh | V20: danh.huynh | W20: Xóa damage ID trước đánh nghi ngờ | X20: None | Z20: =IFERROR(__xludf.DUMMYFUNCTION("""COMPUTED_VALUE"""),"") | AA20: 0 | AB20: =IFERROR(__xludf.DUMMYFUNCTION("""COMPUTED_VALUE"""),1.0) -> 1 | AC20: 0 | AD20: =IFERROR(__xludf.DUMMYFUNCTION("""COMPUTED_VALUE"""),1.0) -> 1 | AE20: 14 | AF20: 12
B21: 46154 | C21: AMWT-3YIUPGJMKR | D21: https://agent-admin.paveapi.com/inspectionView/AMWT-3YIUPGJMKR?activeTab=past-sessions | H21: 1 | I21: 1 | K21: 1 | L21: 1 | T21: vi.votuan | U21: kien.nguyen | W21: View 5: (2) Damage NEW xác định sai View 7: (3) Damage NEW xác định sai | X21: Inspector + Checker Wrong damage | Y21: 2 | Z21: =IFERROR(__xludf.DUMMYFUNCTION("""COMPUTED_VALUE"""),0.6) -> 0.6 | AA21: 2 | AB21: =IFERROR(__xludf.DUMMYFUNCTION("""COMPUTED_VALUE"""),0.6) -> 0.6 | AD21: =IFERROR(__xludf.DUMMYFUNCTION("""COMPUTED_VALUE"""),"") | AE21: 5 | AF21: 4
B22: 46154 | C22: AMUO-YSKGX5S8QU | D22: https://agent-admin.paveapi.com/inspectionView/AMUO-YSKGX5S8QU?activeTab=past-sessions | T22: phong.phantrung | U22: duy.nk | V22: tong.nguyen | X22: None | Y22: 0 | Z22: =IFERROR(__xludf.DUMMYFUNCTION("""COMPUTED_VALUE"""),1.0) -> 1 | AA22: 0 | AB22: =IFERROR(__xludf.DUMMYFUNCTION("""COMPUTED_VALUE"""),1.0) -> 1 | AC22: 0 | AD22: =IFERROR(__xludf.DUMMYFUNCTION("""COMPUTED_VALUE"""),1.0) -> 1 | AE22: 4 | AF22: 1
B23: 46154 | C23: AMWT-JFRVOZENDZ | D23: https://agent-admin.paveapi.com/inspectionView/AMWT-JFRVOZENDZ?activeTab=past-sessions | T23: danh.phamcong | U23: quang.phamdoduy | X23: None | Y23: 0 | Z23: =IFERROR(__xludf.DUMMYFUNCTION("""COMPUTED_VALUE"""),1.0) -> 1 | AA23: 0 | AB23: =IFERROR(__xludf.DUMMYFUNCTION("""COMPUTED_VALUE"""),1.0) -> 1 | AD23: =IFERROR(__xludf.DUMMYFUNCTION("""COMPUTED_VALUE"""),"") | AE23: 18 | AF23: 17
B24: 46154 | C24: AMWT-ZLPMAONCMN | D24: https://agent-admin.paveapi.com/inspectionView/AMWT-ZLPMAONCMN?activeTab=past-sessions | T24: thuy.ngodiem | U24: tam.nguyenmaikhanh | V24: thong.nhat | W24: Xóa damage ID trước đánh nghi ngờ | X24: None | Y24: 0 | Z24: =IFERROR(__xludf.DUMMYFUNCTION("""COMPUTED_VALUE"""),1.0) -> 1 | AA24: 0 | AB24: =IFERROR(__xludf.DUMMYFUNCTION("""COMPUTED_VALUE"""),1.0) -> 1 | AC24: 0 | AD24: =IFERROR(__xludf.DUMMYFUNCTION("""COMPUTED_VALUE"""),1.0) -> 1 | AE24: 18 | AF24: 15
B25: 46154 | C25: AMWT-WF3JDKQCX1 | D25: https://agent-admin.paveapi.com/inspectionView/AMWT-WF3JDKQCX1?activeTab=past-sessions | T25: dinhtu.tran | U25: quang.phamdoduy | W25: Hình tối + sửa xấu -> sp | X25: None | Y25: 0 | Z25: =IFERROR(__xludf.DUMMYFUNCTION("""COMPUTED_VALUE"""),1.0) -> 1 | AA25: 0 | AB25: =IFERROR(__xludf.DUMMYFUNCTION("""COMPUTED_VALUE"""),1.0) -> 1 | AD25: =IFERROR(__xludf.DUMMYFUNCTION("""COMPUTED_VALUE"""),"") | AE25: 12 | AF25: 12
B26: 46154 | C26: AMWT-2JETA15LXZ | D26: https://agent-admin.paveapi.com/inspectionView/AMWT-2JETA15LXZ?activeTab=past-sessions | T26: developer | U26: quang.phamdoduy | V26: hien.nhu | X26: None | Z26: =IFERROR(__xludf.DUMMYFUNCTION("""COMPUTED_VALUE"""),"") | AA26: 0 | AB26: =IFERROR(__xludf.DUMMYFUNCTION("""COMPUTED_VALUE"""),1.0) -> 1 | AC26: 0 | AD26: =IFERROR(__xludf.DUMMYFUNCTION("""COMPUTED_VALUE"""),1.0) -> 1 | AE26: 12 | AF26: 10
B27: 46154 | C27: AMWT-URCX2MK1CT | D27: https://agent-admin.paveapi.com/inspectionView/AMWT-URCX2MK1CT?activeTab=past-sessions | I27: 1 | T27: developer | U27: anh.nguyen | W27: View 5: (3) Damage OLD xác định sai | X27: Checker Wrong damage | Z27: =IFERROR(__xludf.DUMMYFUNCTION("""COMPUTED_VALUE"""),"") | AA27: 1 | AB27: =IFERROR(__xludf.DUMMYFUNCTION("""COMPUTED_VALUE"""),0.75) -> 0.75 | AD27: =IFERROR(__xludf.DUMMYFUNCTION("""COMPUTED_VALUE"""),"") | AE27: 4 | AF27: 4
B28: 46154 | C28: AMWT-77NMRGHZOK | D28: https://agent-admin.paveapi.com/inspectionView/AMWT-77NMRGHZOK?activeTab=past-sessions | T28: developer | U28: vu.nguyen | V28: huyhien.nguyen | X28: None | Z28: =IFERROR(__xludf.DUMMYFUNCTION("""COMPUTED_VALUE"""),"") | AA28: 0 | AB28: =IFERROR(__xludf.DUMMYFUNCTION("""COMPUTED_VALUE"""),1.0) -> 1 | AC28: 0 | AD28: =IFERROR(__xludf.DUMMYFUNCTION("""COMPUTED_VALUE"""),1.0) -> 1 | AE28: 4 | AF28: 2
B29: 46154 | C29: AMWT-GIJQEVY73C | D29: https://agent-admin.paveapi.com/inspectionView/AMWT-GIJQEVY73C?activeTab=past-sessions | O29: 2 | T29: developer | U29: nam.nguyendinh | W29: View 8: (3) Damage OLD xác định sai View 8: BADGE - MISSING_MAJOR | X29: Checker Miss Damage | Z29: =IFERROR(__xludf.DUMMYFUNCTION("""COMPUTED_VALUE"""),"") | AA29: 2 | AB29: =IFERROR(__xludf.DUMMYFUNCTION("""COMPUTED_VALUE"""),0.7142857142857143) -> 0.71428571 | AD29: =IFERROR(__xludf.DUMMYFUNCTION("""COMPUTED_VALUE"""),"") | AE29: 5 | AF29: 3
B30: 46154 | C30: AMWT-ZMZWVMQIKE | D30: https://agent-admin.paveapi.com/inspectionView/AMWT-ZMZWVMQIKE?activeTab=past-sessions | T30: anh.le | U30: nam.nguyendinh | V30: huyhien.nguyen | X30: None | Y30: 0 | Z30: =IFERROR(__xludf.DUMMYFUNCTION("""COMPUTED_VALUE"""),1.0) -> 1 | AA30: 0 | AB30: =IFERROR(__xludf.DUMMYFUNCTION("""COMPUTED_VALUE"""),1.0) -> 1 | AC30: 0 | AD30: =IFERROR(__xludf.DUMMYFUNCTION("""COMPUTED_VALUE"""),1.0) -> 1 | AE30: 3 | AF30: 2
B31: 46154 | C31: AMWT-BWBEHP0X3F | D31: https://agent-admin.paveapi.com/inspectionView/AMWT-BWBEHP0X3F?activeTab=past-sessions | L31: 2 | T31: developer | U31: anh.nguyen | W31: View 7: (3, 4) Damage NEW xác định sai | X31: Checker Wrong damage | Z31: =IFERROR(__xludf.DUMMYFUNCTION("""COMPUTED_VALUE"""),"") | AA31: 2 | AB31: =IFERROR(__xludf.DUMMYFUNCTION("""COMPUTED_VALUE"""),0.8) -> 0.8 | AD31: =IFERROR(__xludf.DUMMYFUNCTION("""COMPUTED_VALUE"""),"") | AE31: 10 | AF31: 10
B32: 46154 | C32: AMWT-IMTSQGKNGM | D32: https://agent-admin.paveapi.com/inspectionView/AMWT-IMTSQGKNGM?activeTab=past-sessions | T32: developer | U32: uyen.tran | V32: nhat.ngo | X32: None | Z32: =IFERROR(__xludf.DUMMYFUNCTION("""COMPUTED_VALUE"""),"") | AA32: 0 | AB32: =IFERROR(__xludf.DUMMYFUNCTION("""COMPUTED_VALUE"""),1.0) -> 1 | AC32: 0 | AD32: =IFERROR(__xludf.DUMMYFUNCTION("""COMPUTED_VALUE"""),1.0) -> 1 | AE32: 12 | AF32: 8
B33: 46154 | C33: DIL1-N9RGCBWVV5 | D33: https://agent-admin.paveapi.com/inspectionView/DIL1-N9RGCBWVV5?activeTab=past-sessions | N33: 1 | O33: 1 | T33: tuong.nhambon | U33: duy.nguyenhuynhquoc | W33: View 8: (1) Damage OLD xác định sai | X33: Inspector + Checker Wrong damage | Y33: 1 | Z33: =IFERROR(__xludf.DUMMYFUNCTION("""COMPUTED_VALUE"""),0.8571428571428572) -> 0.85714286 | AA33: 1 | AB33: =IFERROR(__xludf.DUMMYFUNCTION("""COMPUTED_VALUE"""),0.8571428571428572) -> 0.85714286 | AD33: =IFERROR(__xludf.DUMMYFUNCTION("""COMPUTED_VALUE"""),"") | AE33: 7 | AF33: 7
B34: 46154 | C34: DIL1-UKO8ICTQ6K | D34: https://agent-admin.paveapi.com/inspectionView/DIL1-UKO8ICTQ6K?activeTab=past-sessions | T34: thuy.ngodiem | U34: anh.nguyen | V34: anh.dao | W34: View 8: Xóa damage ID trước đánh nghi ngờ | X34: None | Y34: 0 | Z34: =IFERROR(__xludf.DUMMYFUNCTION("""COMPUTED_VALUE"""),1.0) -> 1 | AA34: 0 | AB34: =IFERROR(__xludf.DUMMYFUNCTION("""COMPUTED_VALUE"""),1.0) -> 1 | AC34: 0 | AD34: =IFERROR(__xludf.DUMMYFUNCTION("""COMPUTED_VALUE"""),1.0) -> 1 | AE34: 7 | AF34: 6
B35: 46155 | C35: AMWT-AQQPAZUF0B | D35: https://agent-admin.paveapi.com/inspectionView/AMWT-AQQPAZUF0B?activeTab=past-sessions | T35: developer | U35: vi.votuan | X35: None | Z35: =IFERROR(__xludf.DUMMYFUNCTION("""COMPUTED_VALUE"""),"") | AA35: 0 | AB35: =IFERROR(__xludf.DUMMYFUNCTION("""COMPUTED_VALUE"""),1.0) -> 1 | AD35: =IFERROR(__xludf.DUMMYFUNCTION("""COMPUTED_VALUE"""),"") | AE35: 8 | AF35: 7
B36: 46155 | C36: AMWT-A0THZEUPMO | D36: https://agent-admin.paveapi.com/inspectionView/AMWT-A0THZEUPMO?activeTab=past-sessions | T36: developer | U36: phong.phantrung | V36: tong.nguyen | X36: None | Z36: =IFERROR(__xludf.DUMMYFUNCTION("""COMPUTED_VALUE"""),"") | AA36: 0 | AB36: =IFERROR(__xludf.DUMMYFUNCTION("""COMPUTED_VALUE"""),1.0) -> 1 | AC36: 0 | AD36: =IFERROR(__xludf.DUMMYFUNCTION("""COMPUTED_VALUE"""),1.0) -> 1 | AE36: 7 | AF36: 7
B37: 46155 | C37: AMWT-NMIZ10H7ME | D37: https://agent-admin.paveapi.com/inspectionView/AMWT-NMIZ10H7ME?activeTab=past-sessions | T37: developer | U37: nhu.le | V37: huyhien.nguyen | W37: Xóa damage ID trước đánh nghi ngờ | X37: None | Z37: =IFERROR(__xludf.DUMMYFUNCTION("""COMPUTED_VALUE"""),"") | AA37: 0 | AB37: =IFERROR(__xludf.DUMMYFUNCTION("""COMPUTED_VALUE"""),1.0) -> 1 | AC37: 0 | AD37: =IFERROR(__xludf.DUMMYFUNCTION("""COMPUTED_VALUE"""),1.0) -> 1 | AE37: 7 | AF37: 6
B38: 46155 | C38: AMUO-V0E5QMOIXH | D38: https://agent-admin.paveapi.com/inspectionView/AMUO-V0E5QMOIXH?activeTab=past-sessions | T38: duy.nk | U38: truc.luquang | X38: None | Y38: 0 | Z38: =IFERROR(__xludf.DUMMYFUNCTION("""COMPUTED_VALUE"""),1.0) -> 1 | AA38: 0 | AB38: =IFERROR(__xludf.DUMMYFUNCTION("""COMPUTED_VALUE"""),1.0) -> 1 | AD38: =IFERROR(__xludf.DUMMYFUNCTION("""COMPUTED_VALUE"""),"") | AE38: 4 | AF38: 4
B39: 46155 | C39: AMUO-LNUFMAMQ9A | D39: https://agent-admin.paveapi.com/inspectionView/AMUO-LNUFMAMQ9A?activeTab=past-sessions | T39: thien.ht | U39: phong.phantrung | V39: huyhien.nguyen | W39: Xóa damage ID trước đánh nghi ngờ | X39: None | Y39: 0 | Z39: =IFERROR(__xludf.DUMMYFUNCTION("""COMPUTED_VALUE"""),1.0) -> 1 | AA39: 0 | AB39: =IFERROR(__xludf.DUMMYFUNCTION("""COMPUTED_VALUE"""),1.0) -> 1 | AC39: 0 | AD39: =IFERROR(__xludf.DUMMYFUNCTION("""COMPUTED_VALUE"""),1.0) -> 1 | AE39: 4 | AF39: 3
B40: 46155 | C40: AMWT-PCLLZEPASH | D40: https://agent-admin.paveapi.com/inspectionView/AMWT-PCLLZEPASH?activeTab=past-sessions | T40: giau.nguyen | U40: quang.phamdoduy | X40: None | Y40: 0 | Z40: =IFERROR(__xludf.DUMMYFUNCTION("""COMPUTED_VALUE"""),1.0) -> 1 | AA40: 0 | AB40: =IFERROR(__xludf.DUMMYFUNCTION("""COMPUTED_VALUE"""),1.0) -> 1 | AD40: =IFERROR(__xludf.DUMMYFUNCTION("""COMPUTED_VALUE"""),"") | AE40: 12 | AF40: 12
B41: 46155 | C41: AMWT-8ZLW44QYML | D41: https://agent-admin.paveapi.com/inspectionView/AMWT-8ZLW44QYML?activeTab=past-sessions | T41: developer | U41: tuong.nhambon | V41: thong.nhat | X41: None | Z41: =IFERROR(__xludf.DUMMYFUNCTION("""COMPUTED_VALUE"""),"") | AA41: 0 | AB41: =IFERROR(__xludf.DUMMYFUNCTION("""COMPUTED_VALUE"""),1.0) -> 1 | AC41: 0 | AD41: =IFERROR(__xludf.DUMMYFUNCTION("""COMPUTED_VALUE"""),1.0) -> 1 | AE41: 12 | AF41: 11
B42: 46155 | C42: AMWT-Y8UQCP2CR1 | D42: https://agent-admin.paveapi.com/inspectionView/AMWT-Y8UQCP2CR1?activeTab=past-sessions | T42: anh.le | U42: anh.trantuan | X42: None | Y42: 0 | Z42: =IFERROR(__xludf.DUMMYFUNCTION("""COMPUTED_VALUE"""),1.0) -> 1 | AA42: 0 | AB42: =IFERROR(__xludf.DUMMYFUNCTION("""COMPUTED_VALUE"""),1.0) -> 1 | AD42: =IFERROR(__xludf.DUMMYFUNCTION("""COMPUTED_VALUE"""),"") | AE42: 43 | AF42: 43
B43: 46155 | C43: AMWT-IPLF4R7TO0 | D43: https://agent-admin.paveapi.com/inspectionView/AMWT-IPLF4R7TO0?activeTab=past-sessions | T43: developer | U43: duy.nk | V43: thinh.nguyen | W43: Xóa damage ID trước đánh nghi ngờ | X43: None | Z43: =IFERROR(__xludf.DUMMYFUNCTION("""COMPUTED_VALUE"""),"") | AA43: 0 | AB43: =IFERROR(__xludf.DUMMYFUNCTION("""COMPUTED_VALUE"""),1.0) -> 1 | AC43: 0 | AD43: =IFERROR(__xludf.DUMMYFUNCTION("""COMPUTED_VALUE"""),1.0) -> 1 | AE43: 43 | AF43: 38
B44: 46155 | C44: AMWT-DUBNV7LAAK | D44: https://agent-admin.paveapi.com/inspectionView/AMWT-DUBNV7LAAK?activeTab=past-sessions | T44: nguyen.nguyentran | U44: duy.nk | X44: None | Y44: 0 | Z44: =IFERROR(__xludf.DUMMYFUNCTION("""COMPUTED_VALUE"""),1.0) -> 1 | AA44: 0 | AB44: =IFERROR(__xludf.DUMMYFUNCTION("""COMPUTED_VALUE"""),1.0) -> 1 | AD44: =IFERROR(__xludf.DUMMYFUNCTION("""COMPUTED_VALUE"""),"") | AE44: 4 | AF44: 4
B45: 46155 | C45: AMWT-GIESVIGY4B | D45: https://agent-admin.paveapi.com/inspectionView/AMWT-GIESVIGY4B?activeTab=past-sessions | T45: developer | U45: kim.hoanglap | V45: danh.huynh | X45: None | Z45: =IFERROR(__xludf.DUMMYFUNCTION("""COMPUTED_VALUE"""),"") | AA45: 0 | AB45: =IFERROR(__xludf.DUMMYFUNCTION("""COMPUTED_VALUE"""),1.0) -> 1 | AC45: 0 | AD45: =IFERROR(__xludf.DUMMYFUNCTION("""COMPUTED_VALUE"""),1.0) -> 1 | AE45: 4 | AF45: 3
B46: 46155 | C46: AMWT-7QUFWMRE0U | D46: https://agent-admin.paveapi.com/inspectionView/AMWT-7QUFWMRE0U?activeTab=past-sessions | T46: thai.ps | U46: duy.le | X46: None | Y46: 0 | Z46: =IFERROR(__xludf.DUMMYFUNCTION("""COMPUTED_VALUE"""),1.0) -> 1 | AA46: 0 | AB46: =IFERROR(__xludf.DUMMYFUNCTION("""COMPUTED_VALUE"""),1.0) -> 1 | AD46: =IFERROR(__xludf.DUMMYFUNCTION("""COMPUTED_VALUE"""),"") | AE46: 7 | AF46: 7
B47: 46155 | C47: AMWT-IILAYIZXUD | D47: https://agent-admin.paveapi.com/inspectionView/AMWT-IILAYIZXUD?activeTab=past-sessions | M47: 1 | T47: duy.le | U47: duy.bui | V47: huyhien.nguyen | W47: View 7: (1) Damage OLD xóa sai damage | X47: CC/AD Wrong damage | Y47: 0 | Z47: =IFERROR(__xludf.DUMMYFUNCTION("""COMPUTED_VALUE"""),1.0) -> 1 | AA47: 0 | AB47: =IFERROR(__xludf.DUMMYFUNCTION("""COMPUTED_VALUE"""),1.0) -> 1 | AC47: 1 | AD47: =IFERROR(__xludf.DUMMYFUNCTION("""COMPUTED_VALUE"""),0.875) -> 0.875 | AE47: 8 | AF47: 6
B48: 46155 | C48: AMWT-BLW3ZSYSWE | D48: https://agent-admin.paveapi.com/inspectionView/AMWT-BLW3ZSYSWE?activeTab=past-sessions | I48: 1 | O48: 1 | T48: developer | U48: phu.nguyenhoang | W48: View 5: (2) Damage OLD kích thước nhỏ View 8: (1) Damage OLD kích thước nhỏ | X48: Checker Wrong damage | Z48: =IFERROR(__xludf.DUMMYFUNCTION("""COMPUTED_VALUE"""),"") | AA48: 2 | AB48: =IFERROR(__xludf.DUMMYFUNCTION("""COMPUTED_VALUE"""),0.8333333333333334) -> 0.83333333 | AD48: =IFERROR(__xludf.DUMMYFUNCTION("""COMPUTED_VALUE"""),"") | AE48: 12 | AF48: 12
B49: 46155 | C49: AMWT-ZRPOYRNVNQ | D49: https://agent-admin.paveapi.com/inspectionView/AMWT-ZRPOYRNVNQ?activeTab=past-sessions | T49: developer | U49: huy.tran | X49: None | Z49: =IFERROR(__xludf.DUMMYFUNCTION("""COMPUTED_VALUE"""),"") | AA49: 0 | AB49: =IFERROR(__xludf.DUMMYFUNCTION("""COMPUTED_VALUE"""),1.0) -> 1 | AD49: =IFERROR(__xludf.DUMMYFUNCTION("""COMPUTED_VALUE"""),"") | AE49: 12 | AF49: 10
B50: 46155 | C50: AMWT-XLGKQ11BBZ | D50: https://agent-admin.paveapi.com/inspectionView/AMWT-XLGKQ11BBZ?activeTab=past-sessions | T50: developer | U50: quang.phamdoduy | X50: None | Z50: =IFERROR(__xludf.DUMMYFUNCTION("""COMPUTED_VALUE"""),"") | AA50: 0 | AB50: =IFERROR(__xludf.DUMMYFUNCTION("""COMPUTED_VALUE"""),1.0) -> 1 | AD50: =IFERROR(__xludf.DUMMYFUNCTION("""COMPUTED_VALUE"""),"") | AE50: 2 | AF50: 1
B51: 46155 | C51: AMWT-XKVYN3ODOZ | D51: https://agent-admin.paveapi.com/inspectionView/AMWT-XKVYN3ODOZ?activeTab=past-sessions | T51: developer | U51: tuong.nhambon | V51: thong.nhat | W51: Xóa damage ID trước đánh nghi ngờ | X51: None | Z51: =IFERROR(__xludf.DUMMYFUNCTION("""COMPUTED_VALUE"""),"") | AA51: 0 | AB51: =IFERROR(__xludf.DUMMYFUNCTION("""COMPUTED_VALUE"""),1.0) -> 1 | AC51: 0 | AD51: =IFERROR(__xludf.DUMMYFUNCTION("""COMPUTED_VALUE"""),1.0) -> 1 | AE51: 4 | AF51: 0
B52: 46155 | C52: AMWT-SOEHXOQFQZ | D52: https://agent-admin.paveapi.com/inspectionView/AMWT-SOEHXOQFQZ?activeTab=past-sessions | F52: 2 | T52: developer | U52: nhu.khong | W52: View 4: (1, 2) Damage OLD đã sửa chữa | X52: Checker Wrong damage | Z52: =IFERROR(__xludf.DUMMYFUNCTION("""COMPUTED_VALUE"""),"") | AA52: 2 | AB52: =IFERROR(__xludf.DUMMYFUNCTION("""COMPUTED_VALUE"""),0.6666666666666667) -> 0.66666667 | AD52: =IFERROR(__xludf.DUMMYFUNCTION("""COMPUTED_VALUE"""),"") | AE52: 6 | AF52: 6
B53: 46155 | C53: AMWT-C0JDLPLOBK | D53: https://agent-admin.paveapi.com/inspectionView/AMWT-C0JDLPLOBK?activeTab=past-sessions | T53: phu.nguyenhoang | U53: thuy.ngodiem | V53: nhat.ngo | X53: None | Y53: 0 | Z53: =IFERROR(__xludf.DUMMYFUNCTION("""COMPUTED_VALUE"""),1.0) -> 1 | AA53: 0 | AB53: =IFERROR(__xludf.DUMMYFUNCTION("""COMPUTED_VALUE"""),1.0) -> 1 | AC53: 0 | AD53: =IFERROR(__xludf.DUMMYFUNCTION("""COMPUTED_VALUE"""),1.0) -> 1 | AE53: 6 | AF53: 4
B54: 46155 | C54: AMWT-MFKBSEO3EQ | D54: https://agent-admin.paveapi.com/inspectionView/AMWT-MFKBSEO3EQ?activeTab=past-sessions | T54: developer | U54: uyen.tran | X54: None | Z54: =IFERROR(__xludf.DUMMYFUNCTION("""COMPUTED_VALUE"""),"") | AA54: 0 | AB54: =IFERROR(__xludf.DUMMYFUNCTION("""COMPUTED_VALUE"""),1.0) -> 1 | AD54: =IFERROR(__xludf.DUMMYFUNCTION("""COMPUTED_VALUE"""),"") | AE54: 14 | AF54: 14
B55: 46155 | C55: AMWT-U3QFQIHPXY | D55: https://agent-admin.paveapi.com/inspectionView/AMWT-U3QFQIHPXY?activeTab=past-sessions | M55: 1 | T55: developer | U55: ngoc.truong | V55: thong.nhat | W55: View 5: (3) Damage OLD xóa sai damage | X55: CC/AD Wrong damage | Z55: =IFERROR(__xludf.DUMMYFUNCTION("""COMPUTED_VALUE"""),"") | AA55: 0 | AB55: =IFERROR(__xludf.DUMMYFUNCTION("""COMPUTED_VALUE"""),1.0) -> 1 | AC55: 1 | AD55: =IFERROR(__xludf.DUMMYFUNCTION("""COMPUTED_VALUE"""),0.9285714285714286) -> 0.92857143 | AE55: 14 | AF55: 13
B56: 46155 | C56: AMWT-2FYAPVCJZQ | D56: https://agent-admin.paveapi.com/inspectionView/AMWT-2FYAPVCJZQ?activeTab=past-sessions | T56: developer | U56: ngan.huynhtuyet | V56: sang.tran | W56: Hình tối | X56: None | Z56: =IFERROR(__xludf.DUMMYFUNCTION("""COMPUTED_VALUE"""),"") | AA56: 0 | AB56: =IFERROR(__xludf.DUMMYFUNCTION("""COMPUTED_VALUE"""),1.0) -> 1 | AC56: 0 | AD56: =IFERROR(__xludf.DUMMYFUNCTION("""COMPUTED_VALUE"""),1.0) -> 1 | AE56: 13 | AF56: 13
B57: 46155 | C57: AMWT-UHXBVS5GVW | D57: https://agent-admin.paveapi.com/inspectionView/AMWT-UHXBVS5GVW?activeTab=past-sessions | T57: developer | U57: vi.votuan | W57: Hình tối | X57: None | Z57: =IFERROR(__xludf.DUMMYFUNCTION("""COMPUTED_VALUE"""),"") | AA57: 0 | AB57: =IFERROR(__xludf.DUMMYFUNCTION("""COMPUTED_VALUE"""),1.0) -> 1 | AD57: =IFERROR(__xludf.DUMMYFUNCTION("""COMPUTED_VALUE"""),"") | AE57: 13 | AF57: 13
B58: 46155 | C58: AMWT-JYQAFUPAF5 | D58: https://agent-admin.paveapi.com/inspectionView/AMWT-JYQAFUPAF5?activeTab=past-sessions | T58: developer | U58: nhi.le | V58: tong.nguyen | W58: Còn damage nhưng bị xóa từ ID AMWT-U3QFQIHPXY | X58: None | Z58: =IFERROR(__xludf.DUMMYFUNCTION("""COMPUTED_VALUE"""),"") | AA58: 0 | AB58: =IFERROR(__xludf.DUMMYFUNCTION("""COMPUTED_VALUE"""),1.0) -> 1 | AC58: 0 | AD58: =IFERROR(__xludf.DUMMYFUNCTION("""COMPUTED_VALUE"""),1.0) -> 1 | AE58: 13 | AF58: 13
B59: 46155 | C59: AMWT-BKF7DHD4SK | D59: https://agent-admin.paveapi.com/inspectionView/AMWT-BKF7DHD4SK?activeTab=past-sessions | T59: developer | U59: quang.nguyenthanh | W59: Hình tối | X59: None | Z59: =IFERROR(__xludf.DUMMYFUNCTION("""COMPUTED_VALUE"""),"") | AA59: 0 | AB59: =IFERROR(__xludf.DUMMYFUNCTION("""COMPUTED_VALUE"""),1.0) -> 1 | AD59: =IFERROR(__xludf.DUMMYFUNCTION("""COMPUTED_VALUE"""),"") | AE59: 7 | AF59: 7
B60: 46155 | C60: AMWT-MYIEQA6EF1 | D60: https://agent-admin.paveapi.com/inspectionView/AMWT-MYIEQA6EF1?activeTab=past-sessions | T60: developer | U60: giau.nguyen | V60: hien.nhu | W60: Hình tối | X60: None | Z60: =IFERROR(__xludf.DUMMYFUNCTION("""COMPUTED_VALUE"""),"") | AA60: 0 | AB60: =IFERROR(__xludf.DUMMYFUNCTION("""COMPUTED_VALUE"""),1.0) -> 1 | AC60: 0 | AD60: =IFERROR(__xludf.DUMMYFUNCTION("""COMPUTED_VALUE"""),1.0) -> 1 | AE60: 7 | AF60: 7
B61: 46155 | C61: AMWT-IQHAZF5E0K | D61: https://agent-admin.paveapi.com/inspectionView/AMWT-IQHAZF5E0K?activeTab=past-sessions | T61: developer | U61: quang.nguyenthanh | V61: sang.tran | X61: None | Z61: =IFERROR(__xludf.DUMMYFUNCTION("""COMPUTED_VALUE"""),"") | AA61: 0 | AB61: =IFERROR(__xludf.DUMMYFUNCTION("""COMPUTED_VALUE"""),1.0) -> 1 | AC61: 0 | AD61: =IFERROR(__xludf.DUMMYFUNCTION("""COMPUTED_VALUE"""),1.0) -> 1 | AE61: 7 | AF61: 5
B62: 46155 | C62: AMWT-4WCGG5RQO4 | D62: https://agent-admin.paveapi.com/inspectionView/AMWT-4WCGG5RQO4?activeTab=past-sessions | T62: developer | U62: anh.le | V62: huyhien.nguyen | X62: None | Z62: =IFERROR(__xludf.DUMMYFUNCTION("""COMPUTED_VALUE"""),"") | AA62: 0 | AB62: =IFERROR(__xludf.DUMMYFUNCTION("""COMPUTED_VALUE"""),1.0) -> 1 | AC62: 0 | AD62: =IFERROR(__xludf.DUMMYFUNCTION("""COMPUTED_VALUE"""),1.0) -> 1 | AE62: 5 | AF62: 5
B63: 46155 | C63: AMWT-YOPUZ465FX | D63: https://agent-admin.paveapi.com/inspectionView/AMWT-YOPUZ465FX?activeTab=past-sessions | T63: developer | U63: thien.ht | V63: thinh.nguyen | X63: None | Z63: =IFERROR(__xludf.DUMMYFUNCTION("""COMPUTED_VALUE"""),"") | AA63: 0 | AB63: =IFERROR(__xludf.DUMMYFUNCTION("""COMPUTED_VALUE"""),1.0) -> 1 | AC63: 0 | AD63: =IFERROR(__xludf.DUMMYFUNCTION("""COMPUTED_VALUE"""),1.0) -> 1 | AE63: 5 | AF63: 5
B64: 46155 | C64: AMWT-9RS8BIDF6A | D64: https://agent-admin.paveapi.com/inspectionView/AMWT-9RS8BIDF6A?activeTab=past-sessions | F64: 1 | O64: 1 | T64: developer | U64: hieu.cao | W64: View 4: (1) Damage NEW xác định sai View 8: (1) Damage OLD xác định sai | X64: Checker Wrong damage | Z64: =IFERROR(__xludf.DUMMYFUNCTION("""COMPUTED_VALUE"""),"") | AA64: 2 | AB64: =IFERROR(__xludf.DUMMYFUNCTION("""COMPUTED_VALUE"""),0.33333333333333337) -> 0.33333333 | AD64: =IFERROR(__xludf.DUMMYFUNCTION("""COMPUTED_VALUE"""),"") | AE64: 3 | AF64: 3
B65: 46155 | C65: AMUO-PHD7DWUYUF | D65: https://agent-admin.paveapi.com/inspectionView/AMUO-PHD7DWUYUF?activeTab=past-sessions | T65: nam.np | U65: na.phc | V65: tong.nguyen | X65: None | Y65: 0 | Z65: =IFERROR(__xludf.DUMMYFUNCTION("""COMPUTED_VALUE"""),1.0) -> 1 | AA65: 0 | AB65: =IFERROR(__xludf.DUMMYFUNCTION("""COMPUTED_VALUE"""),1.0) -> 1 | AC65: 0 | AD65: =IFERROR(__xludf.DUMMYFUNCTION("""COMPUTED_VALUE"""),1.0) -> 1 | AE65: 4 | AF65: 2
B66: 46155 | C66: AMUO-SVDWMVOGVI | D66: https://agent-admin.paveapi.com/inspectionView/AMUO-SVDWMVOGVI?activeTab=past-sessions | T66: developer | V66: ngocanh.tran | X66: None | Z66: =IFERROR(__xludf.DUMMYFUNCTION("""COMPUTED_VALUE"""),"") | AB66: =IFERROR(__xludf.DUMMYFUNCTION("""COMPUTED_VALUE"""),"") | AC66: 0 | AD66: =IFERROR(__xludf.DUMMYFUNCTION("""COMPUTED_VALUE"""),1.0) -> 1 | AE66: 2 | AF66: 2
B67: 46155 | C67: AMUO-TFV1S1KTT3 | D67: https://agent-admin.paveapi.com/inspectionView/AMUO-TFV1S1KTT3?activeTab=past-sessions | T67: tho.nh | U67: nguyen.nguyentran | V67: thinh.nguyen | X67: None | Y67: 0 | Z67: =IFERROR(__xludf.DUMMYFUNCTION("""COMPUTED_VALUE"""),1.0) -> 1 | AA67: 0 | AB67: =IFERROR(__xludf.DUMMYFUNCTION("""COMPUTED_VALUE"""),1.0) -> 1 | AC67: 0 | AD67: =IFERROR(__xludf.DUMMYFUNCTION("""COMPUTED_VALUE"""),1.0) -> 1 | AE67: 2 | AF67: 1
B68: 46155 | C68: AMFR-UKA4DX6GLV | D68: https://agent-admin.paveapi.com/inspectionView/AMFR-UKA4DX6GLV?activeTab=past-sessions | L68: 1 | T68: developer | U68: vi.votuan | W68: View 7: (5) Damage OLD đã sửa chữa | X68: Checker Wrong damage | Z68: =IFERROR(__xludf.DUMMYFUNCTION("""COMPUTED_VALUE"""),"") | AA68: 1 | AB68: =IFERROR(__xludf.DUMMYFUNCTION("""COMPUTED_VALUE"""),0.9411764705882353) -> 0.94117647 | AD68: =IFERROR(__xludf.DUMMYFUNCTION("""COMPUTED_VALUE"""),"") | AE68: 17 | AF68: 17
B69: 46155 | C69: AMFR-DPHNP00J3F | D69: https://agent-admin.paveapi.com/inspectionView/AMFR-DPHNP00J3F?activeTab=past-sessions | T69: developer | U69: duy.bui | V69: thinh.nguyen | X69: None | Z69: =IFERROR(__xludf.DUMMYFUNCTION("""COMPUTED_VALUE"""),"") | AA69: 0 | AB69: =IFERROR(__xludf.DUMMYFUNCTION("""COMPUTED_VALUE"""),1.0) -> 1 | AC69: 0 | AD69: =IFERROR(__xludf.DUMMYFUNCTION("""COMPUTED_VALUE"""),1.0) -> 1 | AE69: 17 | AF69: 16
B70: 46155 | C70: AMWK-TKR7QBR26K | D70: https://agent-admin.paveapi.com/inspectionView/AMWK-TKR7QBR26K?activeTab=past-sessions | I70: 1 | T70: developer | U70: chi.nguyen | W70: View 5: (1) Damage OLD đã sửa chữa | X70: Checker Wrong damage | Z70: =IFERROR(__xludf.DUMMYFUNCTION("""COMPUTED_VALUE"""),"") | AA70: 1 | AB70: =IFERROR(__xludf.DUMMYFUNCTION("""COMPUTED_VALUE"""),0.9473684210526316) -> 0.94736842 | AD70: =IFERROR(__xludf.DUMMYFUNCTION("""COMPUTED_VALUE"""),"") | AE70: 19 | AF70: 19
B71: 46155 | C71: AMWK-PXX5NFKFJG | D71: https://agent-admin.paveapi.com/inspectionView/AMWK-PXX5NFKFJG?activeTab=past-sessions | T71: developer | U71: anh.bui | V71: nhat.ngo | X71: None | Z71: =IFERROR(__xludf.DUMMYFUNCTION("""COMPUTED_VALUE"""),"") | AA71: 0 | AB71: =IFERROR(__xludf.DUMMYFUNCTION("""COMPUTED_VALUE"""),1.0) -> 1 | AC71: 0 | AD71: =IFERROR(__xludf.DUMMYFUNCTION("""COMPUTED_VALUE"""),1.0) -> 1 | AE71: 19 | AF71: 18
B72: 46155 | C72: AMWK-LXI1U2QTBY | D72: https://agent-admin.paveapi.com/inspectionView/AMWK-LXI1U2QTBY?activeTab=past-sessions | T72: developer | U72: giau.nguyen | X72: None | Z72: =IFERROR(__xludf.DUMMYFUNCTION("""COMPUTED_VALUE"""),"") | AA72: 0 | AB72: =IFERROR(__xludf.DUMMYFUNCTION("""COMPUTED_VALUE"""),1.0) -> 1 | AD72: =IFERROR(__xludf.DUMMYFUNCTION("""COMPUTED_VALUE"""),"") | AE72: 28 | AF72: 27
B73: 46156 | C73: AMWT-PKYCAPACGH | D73: https://agent-admin.paveapi.com/inspectionView/AMWT-PKYCAPACGH?activeTab=past-sessions | I73: 1 | T73: developer | U73: thai.ps | W73: View 5: Không update component HOUSING_LIGHT_FOG_RIGHT -> MOLDING_LIGHT_HEAD_RIGHT | X73: Checker Wrong damage | Z73: =IFERROR(__xludf.DUMMYFUNCTION("""COMPUTED_VALUE"""),"") | AA73: 1 | AB73: =IFERROR(__xludf.DUMMYFUNCTION("""COMPUTED_VALUE"""),0.967741935483871) -> 0.96774194 | AD73: =IFERROR(__xludf.DUMMYFUNCTION("""COMPUTED_VALUE"""),"") | AE73: 31 | AF73: 31
B74: 46156 | C74: AMWT-IJ5F7EFIL8 | D74: https://agent-admin.paveapi.com/inspectionView/AMWT-IJ5F7EFIL8?activeTab=past-sessions | T74: developer | U74: duy.le | V74: sang.tran | X74: None | Z74: =IFERROR(__xludf.DUMMYFUNCTION("""COMPUTED_VALUE"""),"") | AA74: 0 | AB74: =IFERROR(__xludf.DUMMYFUNCTION("""COMPUTED_VALUE"""),1.0) -> 1 | AC74: 0 | AD74: =IFERROR(__xludf.DUMMYFUNCTION("""COMPUTED_VALUE"""),1.0) -> 1 | AE74: 32 | AF74: 31
B75: 46156 | C75: AMWT-NGO4IKMBAA | D75: https://agent-admin.paveapi.com/inspectionView/AMWT-NGO4IKMBAA?activeTab=past-sessions | O75: 1 | T75: developer | U75: phu.nguyenhoang | W75: View 8: Không update component LIGHT_REAR_CENTER -> MOLDING_TAIL_LIGHT_CENTER | X75: Checker Wrong damage | Z75: =IFERROR(__xludf.DUMMYFUNCTION("""COMPUTED_VALUE"""),"") | AA75: 1 | AB75: =IFERROR(__xludf.DUMMYFUNCTION("""COMPUTED_VALUE"""),0.9722222222222222) -> 0.97222222 | AD75: =IFERROR(__xludf.DUMMYFUNCTION("""COMPUTED_VALUE"""),"") | AE75: 36 | AF75: 35
B76: 46156 | C76: AMWT-OYP9OZZFCE | D76: https://agent-admin.paveapi.com/inspectionView/AMWT-OYP9OZZFCE?activeTab=past-sessions | T76: developer | U76: hai.cao | V76: hien.nhu | X76: None | Z76: =IFERROR(__xludf.DUMMYFUNCTION("""COMPUTED_VALUE"""),"") | AA76: 0 | AB76: =IFERROR(__xludf.DUMMYFUNCTION("""COMPUTED_VALUE"""),1.0) -> 1 | AC76: 0 | AD76: =IFERROR(__xludf.DUMMYFUNCTION("""COMPUTED_VALUE"""),1.0) -> 1 | AE76: 35 | AF76: 35
B77: 46156 | C77: AMWT-IXD6GECC7M | D77: https://agent-admin.paveapi.com/inspectionView/AMWT-IXD6GECC7M?activeTab=past-sessions | F77: 3 | L77: 2 | T77: developer | U77: danh.phamcong | W77: View 4: (23, 25) Damage OLD đã sửa chữa View 4: (19) Damage OLD xác định sai View 7: (1, 7) Damage OLD đã sửa chữa | X77: Checker Wrong damage | Z77: =IFERROR(__xludf.DUMMYFUNCTION("""COMPUTED_VALUE"""),"") | AA77: 5 | AB77: =IFERROR(__xludf.DUMMYFUNCTION("""COMPUTED_VALUE"""),0.9122807017543859) -> 0.9122807 | AD77: =IFERROR(__xludf.DUMMYFUNCTION("""COMPUTED_VALUE"""),"") | AE77: 57 | AF77: 43
B78: 46156 | C78: AMWT-6PGXA8JLSQ | D78: https://agent-admin.paveapi.com/inspectionView/AMWT-6PGXA8JLSQ?activeTab=past-sessions | T78: developer | U78: thien.nguyen | V78: trinh.ho | X78: None | Z78: =IFERROR(__xludf.DUMMYFUNCTION("""COMPUTED_VALUE"""),"") | AA78: 0 | AB78: =IFERROR(__xludf.DUMMYFUNCTION("""COMPUTED_VALUE"""),1.0) -> 1 | AC78: 0 | AD78: =IFERROR(__xludf.DUMMYFUNCTION("""COMPUTED_VALUE"""),1.0) -> 1 | AE78: 46 | AF78: 34
B79: 46156 | C79: AMWT-VMFS1JXPLE | D79: https://agent-admin.paveapi.com/inspectionView/AMWT-VMFS1JXPLE?activeTab=past-sessions | T79: developer | V79: trinh.ho | X79: None | Z79: =IFERROR(__xludf.DUMMYFUNCTION("""COMPUTED_VALUE"""),"") | AB79: =IFERROR(__xludf.DUMMYFUNCTION("""COMPUTED_VALUE"""),"") | AC79: 0 | AD79: =IFERROR(__xludf.DUMMYFUNCTION("""COMPUTED_VALUE"""),1.0) -> 1 | AE79: 34 | AF79: 34
B80: 46156 | C80: AMWT-BFU9OGLNZG | D80: https://agent-admin.paveapi.com/inspectionView/AMWT-BFU9OGLNZG?activeTab=past-sessions | L80: 2 | O80: 3 | T80: developer | U80: huy.tran | W80: View 8: (2, 4, 8) Damage OLD xác định sai View 7: (6) Damage OLD đã sửa chữa View 7: TRIM_FENDER_FRONT_RIGHT - MISSING_MAJOR | X80: Checker Wrong damage | Z80: =IFERROR(__xludf.DUMMYFUNCTION("""COMPUTED_VALUE"""),"") | AA80: 5 | AB80: =IFERROR(__xludf.DUMMYFUNCTION("""COMPUTED_VALUE"""),0.782608695652174) -> 0.7826087 | AD80: =IFERROR(__xludf.DUMMYFUNCTION("""COMPUTED_VALUE"""),"") | AE80: 23 | AF80: 14
B81: 46156 | C81: AMWT-1W1IVMCHPF | D81: https://agent-admin.paveapi.com/inspectionView/AMWT-1W1IVMCHPF?activeTab=past-sessions | T81: developer | U81: thanh.dlq | V81: thong.nhat | X81: None | Z81: =IFERROR(__xludf.DUMMYFUNCTION("""COMPUTED_VALUE"""),"") | AA81: 0 | AB81: =IFERROR(__xludf.DUMMYFUNCTION("""COMPUTED_VALUE"""),1.0) -> 1 | AC81: 0 | AD81: =IFERROR(__xludf.DUMMYFUNCTION("""COMPUTED_VALUE"""),1.0) -> 1 | AE81: 16 | AF81: 10
B82: 46156 | C82: AMWT-PYRX3TCK3C | D82: https://agent-admin.paveapi.com/inspectionView/AMWT-PYRX3TCK3C?activeTab=past-sessions | T82: developer | U82: kien.nguyen | W82: Data dispute | X82: None | Z82: =IFERROR(__xludf.DUMMYFUNCTION("""COMPUTED_VALUE"""),"") | AA82: 0 | AB82: =IFERROR(__xludf.DUMMYFUNCTION("""COMPUTED_VALUE"""),1.0) -> 1 | AD82: =IFERROR(__xludf.DUMMYFUNCTION("""COMPUTED_VALUE"""),"") | AE82: 25 | AF82: 4
B83: 46156 | C83: AMWT-0GGZTMVPF4 | D83: https://agent-admin.paveapi.com/inspectionView/AMWT-0GGZTMVPF4?activeTab=past-sessions | T83: thai.ps | U83: kien.nguyen | V83: huyhien.nguyen | W83: Data dispute | X83: None | Y83: 0 | Z83: =IFERROR(__xludf.DUMMYFUNCTION("""COMPUTED_VALUE"""),1.0) -> 1 | AA83: 0 | AB83: =IFERROR(__xludf.DUMMYFUNCTION("""COMPUTED_VALUE"""),1.0) -> 1 | AC83: 0 | AD83: =IFERROR(__xludf.DUMMYFUNCTION("""COMPUTED_VALUE"""),1.0) -> 1 | AE83: 7 | AF83: 3
B84: 46156 | C84: AMUO-BENBCWAIP0 | D84: https://agent-admin.paveapi.com/inspectionView/AMUO-BENBCWAIP0?activeTab=past-sessions | T84: mai.luungoc | U84: tu.nbt | X84: None | Y84: 0 | Z84: =IFERROR(__xludf.DUMMYFUNCTION("""COMPUTED_VALUE"""),1.0) -> 1 | AA84: 0 | AB84: =IFERROR(__xludf.DUMMYFUNCTION("""COMPUTED_VALUE"""),1.0) -> 1 | AD84: =IFERROR(__xludf.DUMMYFUNCTION("""COMPUTED_VALUE"""),"") | AE84: 1 | AF84: 1
B85: 46156 | C85: AMUO-RTTDMFQBZ6 | D85: https://agent-admin.paveapi.com/inspectionView/AMUO-RTTDMFQBZ6?activeTab=past-sessions | T85: quang.phamdoduy | U85: uyen.tran | V85: hien.nhu | X85: None | Y85: 0 | Z85: =IFERROR(__xludf.DUMMYFUNCTION("""COMPUTED_VALUE"""),1.0) -> 1 | AA85: 0 | AB85: =IFERROR(__xludf.DUMMYFUNCTION("""COMPUTED_VALUE"""),1.0) -> 1 | AC85: 0 | AD85: =IFERROR(__xludf.DUMMYFUNCTION("""COMPUTED_VALUE"""),1.0) -> 1 | AE85: 2 | AF85: 0
B86: 46156 | C86: AMWT-UHGUKDW23V | D86: https://agent-admin.paveapi.com/inspectionView/AMWT-UHGUKDW23V?activeTab=past-sessions | T86: quang.phamdoduy | U86: tuong.nhambon | X86: None | Y86: 0 | Z86: =IFERROR(__xludf.DUMMYFUNCTION("""COMPUTED_VALUE"""),1.0) -> 1 | AA86: 0 | AB86: =IFERROR(__xludf.DUMMYFUNCTION("""COMPUTED_VALUE"""),1.0) -> 1 | AD86: =IFERROR(__xludf.DUMMYFUNCTION("""COMPUTED_VALUE"""),"") | AE86: 14 | AF86: 11
B87: 46156 | C87: AMWT-MWML9UGKBL | D87: https://agent-admin.paveapi.com/inspectionView/AMWT-MWML9UGKBL?activeTab=past-sessions | U87: tinh.nguyenmaiviet | V87: hien.nhu | W87: View 8: Xóa damage ID trước đánh nghi ngờ | X87: None | Z87: =IFERROR(__xludf.DUMMYFUNCTION("""COMPUTED_VALUE"""),"") | AA87: 0 | AB87: =IFERROR(__xludf.DUMMYFUNCTION("""COMPUTED_VALUE"""),1.0) -> 1 | AC87: 0 | AD87: =IFERROR(__xludf.DUMMYFUNCTION("""COMPUTED_VALUE"""),1.0) -> 1 | AE87: 11 | AF87: 7
B88: 46156 | C88: AMUO-IFSCQBYNTK | D88: https://agent-admin.paveapi.com/inspectionView/AMUO-IFSCQBYNTK?activeTab=past-sessions | T88: anh.le | U88: nguyen.nguyentran | X88: None | Y88: 0 | Z88: =IFERROR(__xludf.DUMMYFUNCTION("""COMPUTED_VALUE"""),1.0) -> 1 | AA88: 0 | AB88: =IFERROR(__xludf.DUMMYFUNCTION("""COMPUTED_VALUE"""),1.0) -> 1 | AD88: =IFERROR(__xludf.DUMMYFUNCTION("""COMPUTED_VALUE"""),"") | AE88: 11 | AF88: 11
B89: 46156 | C89: AMUO-UX1AQBEDKJ | D89: https://agent-admin.paveapi.com/inspectionView/AMUO-UX1AQBEDKJ?activeTab=past-sessions | T89: linh.ptt | U89: anh.le | V89: sang.tran | W89: View 4: Xóa damage ID trước đánh nghi ngờ | X89: None | Y89: 0 | Z89: =IFERROR(__xludf.DUMMYFUNCTION("""COMPUTED_VALUE"""),1.0) -> 1 | AA89: 0 | AB89: =IFERROR(__xludf.DUMMYFUNCTION("""COMPUTED_VALUE"""),1.0) -> 1 | AC89: 0 | AD89: =IFERROR(__xludf.DUMMYFUNCTION("""COMPUTED_VALUE"""),1.0) -> 1 | AE89: 11 | AF89: 9
B90: 46156 | C90: AMWT-ZGGWMPW5H9 | D90: https://agent-admin.paveapi.com/inspectionView/AMWT-ZGGWMPW5H9?activeTab=past-sessions | T90: developer | U90: thao.phan | X90: None | Z90: =IFERROR(__xludf.DUMMYFUNCTION("""COMPUTED_VALUE"""),"") | AA90: 0 | AB90: =IFERROR(__xludf.DUMMYFUNCTION("""COMPUTED_VALUE"""),1.0) -> 1 | AD90: =IFERROR(__xludf.DUMMYFUNCTION("""COMPUTED_VALUE"""),"") | AE90: 18 | AF90: 14
B91: 46156 | C91: AMWT-1DVTRUU04D | D91: https://agent-admin.paveapi.com/inspectionView/AMWT-1DVTRUU04D?activeTab=past-sessions | U91: vi.votuan | V91: huyhien.nguyen | W91: View 7: Xóa damage ID trước đánh nghi ngờ | X91: None | Z91: =IFERROR(__xludf.DUMMYFUNCTION("""COMPUTED_VALUE"""),"") | AA91: 0 | AB91: =IFERROR(__xludf.DUMMYFUNCTION("""COMPUTED_VALUE"""),1.0) -> 1 | AC91: 0 | AD91: =IFERROR(__xludf.DUMMYFUNCTION("""COMPUTED_VALUE"""),1.0) -> 1 | AE91: 14 | AF91: 13
B92: 46156 | C92: AMWT-SSDAEGRM5V | D92: https://agent-admin.paveapi.com/inspectionView/AMWT-SSDAEGRM5V?activeTab=past-sessions | T92: developer | U92: anh.nguyen | X92: None | Z92: =IFERROR(__xludf.DUMMYFUNCTION("""COMPUTED_VALUE"""),"") | AA92: 0 | AB92: =IFERROR(__xludf.DUMMYFUNCTION("""COMPUTED_VALUE"""),1.0) -> 1 | AD92: =IFERROR(__xludf.DUMMYFUNCTION("""COMPUTED_VALUE"""),"") | AE92: 3 | AF92: 1
B93: 46156 | C93: AMWT-149I1NVUOS | D93: https://agent-admin.paveapi.com/inspectionView/AMWT-149I1NVUOS?activeTab=past-sessions | U93: cuong.nguyenthanhthe | V93: nhat.ngo | X93: None | Z93: =IFERROR(__xludf.DUMMYFUNCTION("""COMPUTED_VALUE"""),"") | AA93: 0 | AB93: =IFERROR(__xludf.DUMMYFUNCTION("""COMPUTED_VALUE"""),1.0) -> 1 | AC93: 0 | AD93: =IFERROR(__xludf.DUMMYFUNCTION("""COMPUTED_VALUE"""),1.0) -> 1 | AE93: 1 | AF93: 0
B94: 46156 | C94: AMWT-5LGC42MPQG | D94: https://agent-admin.paveapi.com/inspectionView/AMWT-5LGC42MPQG?activeTab=past-sessions | T94: developer | U94: tuan.tran | X94: None | Z94: =IFERROR(__xludf.DUMMYFUNCTION("""COMPUTED_VALUE"""),"") | AA94: 0 | AB94: =IFERROR(__xludf.DUMMYFUNCTION("""COMPUTED_VALUE"""),1.0) -> 1 | AD94: =IFERROR(__xludf.DUMMYFUNCTION("""COMPUTED_VALUE"""),"") | AE94: 16 | AF94: 16
B95: 46156 | C95: AMWT-GFJNG3SYDV | D95: https://agent-admin.paveapi.com/inspectionView/AMWT-GFJNG3SYDV?activeTab=past-sessions | U95: hien.phamthi | V95: phuong.nguyen | X95: None | Z95: =IFERROR(__xludf.DUMMYFUNCTION("""COMPUTED_VALUE"""),"") | AA95: 0 | AB95: =IFERROR(__xludf.DUMMYFUNCTION("""COMPUTED_VALUE"""),1.0) -> 1 | AC95: 0 | AD95: =IFERROR(__xludf.DUMMYFUNCTION("""COMPUTED_VALUE"""),1.0) -> 1 | AE95: 18 | AF95: 14
B96: 46157 | C96: AMWT-6NXYWHR569 | D96: https://agent-admin.paveapi.com/inspectionView/AMWT-6NXYWHR569?activeTab=past-sessions | T96: thanh.dlq | U96: huy.tran | X96: None | Y96: 0 | Z96: =IFERROR(__xludf.DUMMYFUNCTION("""COMPUTED_VALUE"""),1.0) -> 1 | AA96: 0 | AB96: =IFERROR(__xludf.DUMMYFUNCTION("""COMPUTED_VALUE"""),1.0) -> 1 | AD96: =IFERROR(__xludf.DUMMYFUNCTION("""COMPUTED_VALUE"""),"") | AE96: 2 | AF96: 2
B97: 46157 | C97: AMWT-IUNBBONUAL | D97: https://agent-admin.paveapi.com/inspectionView/AMWT-IUNBBONUAL?activeTab=past-sessions | T97: danh.phamcong | U97: thang.pham | V97: nhat.ngo | X97: None | Y97: 0 | Z97: =IFERROR(__xludf.DUMMYFUNCTION("""COMPUTED_VALUE"""),1.0) -> 1 | AA97: 0 | AB97: =IFERROR(__xludf.DUMMYFUNCTION("""COMPUTED_VALUE"""),1.0) -> 1 | AC97: 0 | AD97: =IFERROR(__xludf.DUMMYFUNCTION("""COMPUTED_VALUE"""),1.0) -> 1 | AE97: 2 | AF97: 2
B98: 46157 | C98: AMWT-GEOEVEC5Q0 | D98: https://agent-admin.paveapi.com/inspectionView/AMWT-GEOEVEC5Q0?activeTab=past-sessions | T98: tuong.nhambon | U98: hai.cao | X98: None | Y98: 0 | Z98: =IFERROR(__xludf.DUMMYFUNCTION("""COMPUTED_VALUE"""),1.0) -> 1 | AA98: 0 | AB98: =IFERROR(__xludf.DUMMYFUNCTION("""COMPUTED_VALUE"""),1.0) -> 1 | AD98: =IFERROR(__xludf.DUMMYFUNCTION("""COMPUTED_VALUE"""),"") | AE98: 2 | AF98: 1
B99: 46157 | C99: AMWT-TY5QATDYKC | D99: https://agent-admin.paveapi.com/inspectionView/AMWT-TY5QATDYKC?activeTab=past-sessions | U99: duy.bui | V99: sang.tran | X99: None | Z99: =IFERROR(__xludf.DUMMYFUNCTION("""COMPUTED_VALUE"""),"") | AA99: 0 | AB99: =IFERROR(__xludf.DUMMYFUNCTION("""COMPUTED_VALUE"""),1.0) -> 1 | AC99: 0 | AD99: =IFERROR(__xludf.DUMMYFUNCTION("""COMPUTED_VALUE"""),1.0) -> 1 | AE99: 14 | AF99: 13
B100: 46157 | C100: AMWT-UPJTORJZTK | D100: https://agent-admin.paveapi.com/inspectionView/AMWT-UPJTORJZTK?activeTab=past-sessions | U100: kien.nguyen | V100: huyhien.nguyen | X100: None | Z100: =IFERROR(__xludf.DUMMYFUNCTION("""COMPUTED_VALUE"""),"") | AA100: 0 | AB100: =IFERROR(__xludf.DUMMYFUNCTION("""COMPUTED_VALUE"""),1.0) -> 1 | AC100: 0 | AD100: =IFERROR(__xludf.DUMMYFUNCTION("""COMPUTED_VALUE"""),1.0) -> 1 | AE100: 13 | AF100: 10
...

Sheet PERF_W21
E1: DAMAGE FAILED | T1: PERSON RESPONSIBLE | X1: =COUNTIF(X4:X637,"<>") -> 595 | Y1: ACCURACY
A2: Date | C2: Sessions | D2: {={"LINK SESSION"; IF(C3:C637 = "", "", "https://agent-admin.paveapi.com/inspectionView/" & C3:C637 & "?activeTab=past-sessions")}} -> LINK SESSION | E2: Left Side | H2: Front Side | K2: Right Side | N2: Back Side | Q2: Other Side | T2: Inspect | U2: Check | V2: Cross-Check/Admin | W2: RE-CHECK & NOTE | X2: Reason | Y2: Inspect | AA2: Check | AC2: Cross-Check/Admin | AE2: Total Damage | AG2: AUDITOR
E3: Inspect | F3: Check | G3: Cross-Check/Admin | H3: Inspect | I3: Check | J3: Cross-Check/Admin | K3: Inspect | L3: Check | M3: Cross-Check/Admin | N3: Inspect | O3: Check | P3: Cross-Check/Admin | Q3: Inspect | R3: Check | S3: Cross-Check/Admin | Y3: {={"Mistakes";IF((T4:T637 <> "") * (T4:T637 <> "developer") * (X4:X637 <> ""), IF(ISNUMBER(MATCH(X4:X637, {"ALL Miss Damage"; "ALL Wrong Damage"; "Inspector + CC/AD Miss Damage"; "Inspector + CC/AD Wrong damage"; "Inspector + Checker Miss Damage"; "Inspector + Checker Wrong damage"; "Inspector Miss Damage"; "Inspector Wrong damage"; "Other"}, 0)), N(E4:E637) + N(H4:H637) + N(K4:K637) + N(N4:N637) + N(Q4:Q637), 0), "")}} -> Mistakes | Z3: =IFERROR(__xludf.DUMMYFUNCTION("{""%"";ARRAYFORMULA(IF((T4:T637 = """") + (X4:X637 = """"), """", IF(T4:T637 = ""developer"", """", IFERROR(IF(REGEXMATCH(LOWER($X$4:$X637), ""miss damage""), 1 - Y4:Y637 / ((($AE$4:$AE637 + $AF$4:$AF637 + ABS($AE$4:$AE637 - $AF$4:$AF637)) / 2) + Y4:Y637)"&", 1 - Y4:Y637 / (($AE$4:$AE637 + $AF$4:$AF637 + ABS($AE$4:$AE637 - $AF$4:$AF637)) / 2)), 1))))}"),"%") -> % | AA3: {={"Mistakes"; IF((U4:U637 = "") + (X4:X637 = ""), "", IF(ISNUMBER(MATCH(X4:X637, {"ALL Miss Damage"; "ALL Wrong Damage"; "Checker Miss Damage"; "Checker Wrong damage"; "Checker + CC/AD Miss Damage"; "Checker + CC/AD Wrong damage"; "Inspector + Checker Miss Damage"; "Inspector + Checker Wrong damage"; "Other"}, 0)), N(F4:F637) + N(I4:I637) + N(L4:L637) + N(O4:O637) + N(R4:R637), 0))}} -> Mistakes | AB3: =IFERROR(__xludf.DUMMYFUNCTION("{""%"";ARRAYFORMULA(IF((U4:U637 = """") + (X4:X637 = """"), """", IFERROR(IF(REGEXMATCH(LOWER($X$4:$X637), ""miss damage""), 1 - AA4:AA637 / ((($AE$4:$AE637 + $AF$4:$AF637 + ABS($AE$4:$AE637 - $AF$4:$AF637)) / 2) + AA4:AA637), 1 - AA4:AA637 / (($AE$4:$AE6"&"37 + $AF$4:$AF637 + ABS($AE$4:$AE637 - $AF$4:$AF637)) / 2)), 1)))}"),"%") -> % | AC3: {={"Mistakes"; IF((V4:V637 = "") + (X4:X637 = ""), "", IF(ISNUMBER(MATCH(X4:X637, {"ALL Miss Damage"; "ALL Wrong Damage"; "CC/AD Miss Damage"; "CC/AD Wrong damage"; "Checker + CC/AD Miss Damage"; "Checker + CC/AD Wrong damage" ; "Inspector + CC/AD Miss Damage"; "Inspector + CC/AD Wrong damage"; "Other"}, 0)), N(G4:G637) + N(J4:J637) + N(M4:M637) + N(P4:P637) + N(S4:S637), 0))}} -> Mistakes | AD3: =IFERROR(__xludf.DUMMYFUNCTION("{""%"";ARRAYFORMULA(IF((V4:V637 = """") + (X4:X637 = """"), """", IFERROR(IF(REGEXMATCH(LOWER($X$4:$X637), ""miss damage""), 1 - AC4:AC637 / ((($AE$4:$AE637 + $AF$4:$AF637 + ABS($AE$4:$AE637 - $AF$4:$AF637)) / 2) + AC4:AC637), 1 - AC4:AC637 / (($AE$4:$AE6"&"37 + $AF$4:$AF637 + ABS($AE$4:$AE637 - $AF$4:$AF637)) / 2)), 1)))}"),"%") -> % | AE3: BEFORE | AF3: FINAL
A4: 0518-1hrs_NA | B4: 46160 | C4: AMRR-SPLRKWP9RR | D4: https://agent-admin.paveapi.com/inspectionView/AMRR-SPLRKWP9RR?activeTab=past-sessions | T4: developer | U4: thao.phan | X4: None | Z4: =IFERROR(__xludf.DUMMYFUNCTION("""COMPUTED_VALUE"""),"") | AA4: 0 | AB4: =IFERROR(__xludf.DUMMYFUNCTION("""COMPUTED_VALUE"""),1.0) -> 1 | AD4: =IFERROR(__xludf.DUMMYFUNCTION("""COMPUTED_VALUE"""),"") | AE4: 22 | AF4: 1
B5: 46160 | C5: AMRR-KFGSCQYIFQ | D5: https://agent-admin.paveapi.com/inspectionView/AMRR-KFGSCQYIFQ?activeTab=past-sessions | T5: developer | U5: nam.nguyenthanh | V5: thinh.nguyen | X5: None | Z5: =IFERROR(__xludf.DUMMYFUNCTION("""COMPUTED_VALUE"""),"") | AA5: 0 | AB5: =IFERROR(__xludf.DUMMYFUNCTION("""COMPUTED_VALUE"""),1.0) -> 1 | AC5: 0 | AD5: =IFERROR(__xludf.DUMMYFUNCTION("""COMPUTED_VALUE"""),1.0) -> 1 | AE5: 1 | AF5: 0
B6: 46160 | C6: AMWT-3NI15UB4OX | D6: https://agent-admin.paveapi.com/inspectionView/AMWT-3NI15UB4OX?activeTab=past-sessions | T6: nguyen.nguyentran | U6: thien.ht | X6: None | Y6: 0 | Z6: =IFERROR(__xludf.DUMMYFUNCTION("""COMPUTED_VALUE"""),1.0) -> 1 | AA6: 0 | AB6: =IFERROR(__xludf.DUMMYFUNCTION("""COMPUTED_VALUE"""),1.0) -> 1 | AD6: =IFERROR(__xludf.DUMMYFUNCTION("""COMPUTED_VALUE"""),"") | AE6: 4 | AF6: 2
B7: 46160 | C7: AMWT-C8965Z65N3 | D7: https://agent-admin.paveapi.com/inspectionView/AMWT-C8965Z65N3?activeTab=past-sessions | M7: 1 | T7: nguyen.nguyentran | U7: kien.nguyen | V7: huyhien.nguyen | W7: View 7: (1) Damage OLD còn damage nên giữ | X7: CC/AD Wrong damage | Y7: 0 | Z7: =IFERROR(__xludf.DUMMYFUNCTION("""COMPUTED_VALUE"""),1.0) -> 1 | AA7: 0 | AB7: =IFERROR(__xludf.DUMMYFUNCTION("""COMPUTED_VALUE"""),1.0) -> 1 | AC7: 1 | AD7: =IFERROR(__xludf.DUMMYFUNCTION("""COMPUTED_VALUE"""),0.5) -> 0.5 | AE7: 2 | AF7: 1
B8: 46160 | C8: AMWT-7XRF9OQSB8 | D8: https://agent-admin.paveapi.com/inspectionView/AMWT-7XRF9OQSB8?activeTab=past-sessions | T8: duy.nk | U8: nhu.le | X8: None | Y8: 0 | Z8: =IFERROR(__xludf.DUMMYFUNCTION("""COMPUTED_VALUE"""),1.0) -> 1 | AA8: 0 | AB8: =IFERROR(__xludf.DUMMYFUNCTION("""COMPUTED_VALUE"""),1.0) -> 1 | AD8: =IFERROR(__xludf.DUMMYFUNCTION("""COMPUTED_VALUE"""),"") | AE8: 6 | AF8: 4
B9: 46160 | C9: AMWT-NLA8Y7K4VQ | D9: https://agent-admin.paveapi.com/inspectionView/AMWT-NLA8Y7K4VQ?activeTab=past-sessions | T9: tho.nh | U9: phong.phantrung | V9: phuong.nguyen | X9: None | Y9: 0 | Z9: =IFERROR(__xludf.DUMMYFUNCTION("""COMPUTED_VALUE"""),1.0) -> 1 | AA9: 0 | AB9: =IFERROR(__xludf.DUMMYFUNCTION("""COMPUTED_VALUE"""),1.0) -> 1 | AC9: 0 | AD9: =IFERROR(__xludf.DUMMYFUNCTION("""COMPUTED_VALUE"""),1.0) -> 1 | AE9: 4 | AF9: 3
B10: 46160 | C10: AMWT-DRO9WHAWDT | D10: https://agent-admin.paveapi.com/inspectionView/AMWT-DRO9WHAWDT?activeTab=past-sessions | F10: 2 | T10: developer | U10: hoang.nguyentuyen | W10: View 4 (5, 6) Damage OLD kích thước nhỏ | X10: Checker Wrong damage | Z10: =IFERROR(__xludf.DUMMYFUNCTION("""COMPUTED_VALUE"""),"") | AA10: 2 | AB10: =IFERROR(__xludf.DUMMYFUNCTION("""COMPUTED_VALUE"""),0.75) -> 0.75 | AD10: =IFERROR(__xludf.DUMMYFUNCTION("""COMPUTED_VALUE"""),"") | AE10: 8 | AF10: 6
B11: 46160 | C11: AMWT-DJSUVCEAIA | D11: https://agent-admin.paveapi.com/inspectionView/AMWT-DJSUVCEAIA?activeTab=past-sessions | T11: developer | U11: huy.tran | V11: danh.huynh | X11: None | Z11: =IFERROR(__xludf.DUMMYFUNCTION("""COMPUTED_VALUE"""),"") | AA11: 0 | AB11: =IFERROR(__xludf.DUMMYFUNCTION("""COMPUTED_VALUE"""),1.0) -> 1 | AC11: 0 | AD11: =IFERROR(__xludf.DUMMYFUNCTION("""COMPUTED_VALUE"""),1.0) -> 1 | AE11: 6 | AF11: 2
B12: 46160 | C12: AMWT-3WGEVP26ND | D12: https://agent-admin.paveapi.com/inspectionView/AMWT-3WGEVP26ND?activeTab=past-sessions | L12: 12 | T12: developer | U12: nguyen.nguyentran | W12: View 7: (1->9, 14 ->16) Damage OLD đã sửa chữa | X12: Checker Wrong damage | Z12: =IFERROR(__xludf.DUMMYFUNCTION("""COMPUTED_VALUE"""),"") | AA12: 12 | AB12: =IFERROR(__xludf.DUMMYFUNCTION("""COMPUTED_VALUE"""),0.6923076923076923) -> 0.69230769 | AD12: =IFERROR(__xludf.DUMMYFUNCTION("""COMPUTED_VALUE"""),"") | AE12: 39 | AF12: 23
B13: 46160 | C13: AMWT-Y8AFQZI95U | D13: https://agent-admin.paveapi.com/inspectionView/AMWT-Y8AFQZI95U?activeTab=past-sessions | T13: developer | U13: luu.nguyendinh | V13: tong.nguyen | X13: None | Z13: =IFERROR(__xludf.DUMMYFUNCTION("""COMPUTED_VALUE"""),"") | AA13: 0 | AB13: =IFERROR(__xludf.DUMMYFUNCTION("""COMPUTED_VALUE"""),1.0) -> 1 | AC13: 0 | AD13: =IFERROR(__xludf.DUMMYFUNCTION("""COMPUTED_VALUE"""),1.0) -> 1 | AE13: 23 | AF13: 11
B14: 46160 | C14: AMWT-K4QXNEMCQM | D14: https://agent-admin.paveapi.com/inspectionView/AMWT-K4QXNEMCQM?activeTab=past-sessions | L14: 1 | T14: developer | U14: nam.nguyenthanh | V14: thinh.nguyen | X14: None | Z14: =IFERROR(__xludf.DUMMYFUNCTION("""COMPUTED_VALUE"""),"") | AA14: 0 | AB14: =IFERROR(__xludf.DUMMYFUNCTION("""COMPUTED_VALUE"""),1.0) -> 1 | AC14: 0 | AD14: =IFERROR(__xludf.DUMMYFUNCTION("""COMPUTED_VALUE"""),1.0) -> 1 | AE14: 11 | AF14: 11
B15: 46160 | C15: AMWT-OXMZ5JFMHE | D15: https://agent-admin.paveapi.com/inspectionView/AMWT-OXMZ5JFMHE?activeTab=past-sessions | L15: 1 | T15: developer | U15: kim.hoanglap | W15: View 7: Remove (3): Không rõ | X15: Checker Wrong damage | Z15: =IFERROR(__xludf.DUMMYFUNCTION("""COMPUTED_VALUE"""),"") | AA15: 1 | AB15: =IFERROR(__xludf.DUMMYFUNCTION("""COMPUTED_VALUE"""),0.8) -> 0.8 | AD15: =IFERROR(__xludf.DUMMYFUNCTION("""COMPUTED_VALUE"""),"") | AE15: 5 | AF15: 5
B16: 46160 | C16: AMWT-UAP6DMFU7W | D16: https://agent-admin.paveapi.com/inspectionView/AMWT-UAP6DMFU7W?activeTab=past-sessions | M16: 1 | T16: developer | U16: phong.phantrung | V16: tong.nguyen | W16: View 7: Remove (3): Không rõ | X16: CC/AD Wrong damage | Z16: =IFERROR(__xludf.DUMMYFUNCTION("""COMPUTED_VALUE"""),"") | AA16: 0 | AB16: =IFERROR(__xludf.DUMMYFUNCTION("""COMPUTED_VALUE"""),1.0) -> 1 | AC16: 1 | AD16: =IFERROR(__xludf.DUMMYFUNCTION("""COMPUTED_VALUE"""),0.8) -> 0.8 | AE16: 5 | AF16: 5
B17: 46160 | C17: AMWT-PBSUZRQGJ2 | D17: https://agent-admin.paveapi.com/inspectionView/AMWT-PBSUZRQGJ2?activeTab=past-sessions | T17: developer | U17: thai.ps | V17: huyhien.nguyen | X17: None | Z17: =IFERROR(__xludf.DUMMYFUNCTION("""COMPUTED_VALUE"""),"") | AA17: 0 | AB17: =IFERROR(__xludf.DUMMYFUNCTION("""COMPUTED_VALUE"""),1.0) -> 1 | AC17: 0 | AD17: =IFERROR(__xludf.DUMMYFUNCTION("""COMPUTED_VALUE"""),1.0) -> 1 | AE17: 6 | AF17: 1
B18: 46160 | C18: AMWT-CLUBELHGWI | D18: https://agent-admin.paveapi.com/inspectionView/AMWT-CLUBELHGWI?activeTab=past-sessions | T18: developer | U18: duy.bui | V18: thinh.nguyen | X18: None | Z18: =IFERROR(__xludf.DUMMYFUNCTION("""COMPUTED_VALUE"""),"") | AA18: 0 | AB18: =IFERROR(__xludf.DUMMYFUNCTION("""COMPUTED_VALUE"""),1.0) -> 1 | AC18: 0 | AD18: =IFERROR(__xludf.DUMMYFUNCTION("""COMPUTED_VALUE"""),1.0) -> 1 | AE18: 35 | AF18: 10
B19: 46160 | C19: AMWT-1GEMNZE9PH | D19: https://agent-admin.paveapi.com/inspectionView/AMWT-1GEMNZE9PH?activeTab=past-sessions | T19: developer | U19: thien.ht | V19: thinh.nguyen | X19: None | Z19: =IFERROR(__xludf.DUMMYFUNCTION("""COMPUTED_VALUE"""),"") | AA19: 0 | AB19: =IFERROR(__xludf.DUMMYFUNCTION("""COMPUTED_VALUE"""),1.0) -> 1 | AC19: 0 | AD19: =IFERROR(__xludf.DUMMYFUNCTION("""COMPUTED_VALUE"""),1.0) -> 1 | AE19: 10 | AF19: 10
B20: 46160 | C20: AMWT-DATG8FMQMH | D20: https://agent-admin.paveapi.com/inspectionView/AMWT-DATG8FMQMH?activeTab=past-sessions | T20: developer | U20: nam.nguyenthanh | V20: thinh.nguyen | W20: View 7: Xóa damage ID trước đánh nghi ngờ | X20: None | Z20: =IFERROR(__xludf.DUMMYFUNCTION("""COMPUTED_VALUE"""),"") | AA20: 0 | AB20: =IFERROR(__xludf.DUMMYFUNCTION("""COMPUTED_VALUE"""),1.0) -> 1 | AC20: 0 | AD20: =IFERROR(__xludf.DUMMYFUNCTION("""COMPUTED_VALUE"""),1.0) -> 1 | AE20: 10 | AF20: 9
B21: 46160 | C21: AMWT-LUQYHWL2PJ | D21: https://agent-admin.paveapi.com/inspectionView/AMWT-LUQYHWL2PJ?activeTab=past-sessions | T21: developer | U21: truong.nguyen | V21: sang.tran | W21: View 4, 7: Xóa damage ID trước đánh nghi ngờ | X21: None | Z21: =IFERROR(__xludf.DUMMYFUNCTION("""COMPUTED_VALUE"""),"") | AA21: 0 | AB21: =IFERROR(__xludf.DUMMYFUNCTION("""COMPUTED_VALUE"""),1.0) -> 1 | AC21: 0 | AD21: =IFERROR(__xludf.DUMMYFUNCTION("""COMPUTED_VALUE"""),1.0) -> 1 | AE21: 9 | AF21: 7
A22: 0518-1hrs_EU | B22: 46160 | C22: AMWK-0LETVBHI69 | D22: https://agent-admin.paveapi.com/inspectionView/AMWK-0LETVBHI69?activeTab=past-sessions | T22: developer | U22: kiet.voanh | X22: None | Z22: =IFERROR(__xludf.DUMMYFUNCTION("""COMPUTED_VALUE"""),"") | AA22: 0 | AB22: =IFERROR(__xludf.DUMMYFUNCTION("""COMPUTED_VALUE"""),1.0) -> 1 | AD22: =IFERROR(__xludf.DUMMYFUNCTION("""COMPUTED_VALUE"""),"") | AE22: 8 | AF22: 5
B23: 46160 | C23: AMWK-2E5SLC65BK | D23: https://agent-admin.paveapi.com/inspectionView/AMWK-2E5SLC65BK?activeTab=past-sessions | T23: developer | U23: uyen.tran | V23: thong.nhat | X23: None | Z23: =IFERROR(__xludf.DUMMYFUNCTION("""COMPUTED_VALUE"""),"") | AA23: 0 | AB23: =IFERROR(__xludf.DUMMYFUNCTION("""COMPUTED_VALUE"""),1.0) -> 1 | AC23: 0 | AD23: =IFERROR(__xludf.DUMMYFUNCTION("""COMPUTED_VALUE"""),1.0) -> 1 | AE23: 5 | AF23: 4
A24: 0519-1hrs_NA | B24: 46161 | C24: AMWT-PHOWOY9XWL | D24: https://agent-admin.paveapi.com/inspectionView/AMWT-PHOWOY9XWL?activeTab=past-sessions | T24: developer | U24: my.nguyen | W24: View 5: (1) Không update component | X24: Checker Wrong damage | Z24: =IFERROR(__xludf.DUMMYFUNCTION("""COMPUTED_VALUE"""),"") | AA24: 0 | AB24: =IFERROR(__xludf.DUMMYFUNCTION("""COMPUTED_VALUE"""),1.0) -> 1 | AD24: =IFERROR(__xludf.DUMMYFUNCTION("""COMPUTED_VALUE"""),"") | AE24: 29 | AF24: 24
B25: 46161 | C25: AMWT-HZGK1F7EOC | D25: https://agent-admin.paveapi.com/inspectionView/AMWT-HZGK1F7EOC?activeTab=past-sessions | T25: kim.hoanglap | U25: na.phc | V25: phuong.nguyen | X25: None | Y25: 0 | Z25: =IFERROR(__xludf.DUMMYFUNCTION("""COMPUTED_VALUE"""),1.0) -> 1 | AA25: 0 | AB25: =IFERROR(__xludf.DUMMYFUNCTION("""COMPUTED_VALUE"""),1.0) -> 1 | AC25: 0 | AD25: =IFERROR(__xludf.DUMMYFUNCTION("""COMPUTED_VALUE"""),1.0) -> 1 | AE25: 24 | AF25: 23
B26: 46161 | C26: AMWT-RRI5HAYGDE | D26: https://agent-admin.paveapi.com/inspectionView/AMWT-RRI5HAYGDE?activeTab=past-sessions | T26: developer | U26: ngan.huynhtuyet | W26: View 8: (1) Damage OLD xác định sai ( Hình tối không thấy damage -> xóa) | X26: Checker Wrong damage | Z26: =IFERROR(__xludf.DUMMYFUNCTION("""COMPUTED_VALUE"""),"") | AA26: 0 | AB26: =IFERROR(__xludf.DUMMYFUNCTION("""COMPUTED_VALUE"""),1.0) -> 1 | AD26: =IFERROR(__xludf.DUMMYFUNCTION("""COMPUTED_VALUE"""),"") | AE26: 8 | AF26: 8
B27: 46161 | C27: AMWT-S67ALEAAXE | D27: https://agent-admin.paveapi.com/inspectionView/AMWT-S67ALEAAXE?activeTab=past-sessions | T27: developer | U27: kien.nguyen | V27: sang.tran | X27: None | Z27: =IFERROR(__xludf.DUMMYFUNCTION("""COMPUTED_VALUE"""),"") | AA27: 0 | AB27: =IFERROR(__xludf.DUMMYFUNCTION("""COMPUTED_VALUE"""),1.0) -> 1 | AC27: 0 | AD27: =IFERROR(__xludf.DUMMYFUNCTION("""COMPUTED_VALUE"""),1.0) -> 1 | AE27: 8 | AF27: 7
B28: 46161 | C28: AMWT-5BXQC3PMIY | D28: https://agent-admin.paveapi.com/inspectionView/AMWT-5BXQC3PMIY?activeTab=past-sessions | T28: developer | U28: triet.le | W28: View 5: (1) Damage OLD đã sửa chữa ( rj major sửa lại medium) View 7: (3, 4) Damage OLD đã sửa chữa View 7: (9) Damage OLD xác định sai | X28: Checker Wrong damage | Z28: =IFERROR(__xludf.DUMMYFUNCTION("""COMPUTED_VALUE"""),"") | AA28: 0 | AB28: =IFERROR(__xludf.DUMMYFUNCTION("""COMPUTED_VALUE"""),1.0) -> 1 | AD28: =IFERROR(__xludf.DUMMYFUNCTION("""COMPUTED_VALUE"""),"") | AE28: 15 | AF28: 8
B29: 46161 | C29: AMWT-4QZQJIIW09 | D29: https://agent-admin.paveapi.com/inspectionView/AMWT-4QZQJIIW09?activeTab=past-sessions | T29: developer | U29: linh.ptt | V29: nhat.ngo | X29: None | Z29: =IFERROR(__xludf.DUMMYFUNCTION("""COMPUTED_VALUE"""),"") | AA29: 0 | AB29: =IFERROR(__xludf.DUMMYFUNCTION("""COMPUTED_VALUE"""),1.0) -> 1 | AC29: 0 | AD29: =IFERROR(__xludf.DUMMYFUNCTION("""COMPUTED_VALUE"""),1.0) -> 1 | AE29: 8 | AF29: 4
B30: 46161 | C30: AMWT-YLJ9QDNJCC | D30: https://agent-admin.paveapi.com/inspectionView/AMWT-YLJ9QDNJCC?activeTab=past-sessions | T30: developer | U30: thanh.dlq | X30: None | Z30: =IFERROR(__xludf.DUMMYFUNCTION("""COMPUTED_VALUE"""),"") | AA30: 0 | AB30: =IFERROR(__xludf.DUMMYFUNCTION("""COMPUTED_VALUE"""),1.0) -> 1 | AD30: =IFERROR(__xludf.DUMMYFUNCTION("""COMPUTED_VALUE"""),"") | AE30: 3 | AF30: 3
B31: 46161 | C31: AMWT-8J36TSYU0W | D31: https://agent-admin.paveapi.com/inspectionView/AMWT-8J36TSYU0W?activeTab=past-sessions | T31: developer | U31: quang.phamdoduy | V31: trinh.ho | W31: View 7: Xóa damage ID trước đánh nghi ngờ | X31: None | Z31: =IFERROR(__xludf.DUMMYFUNCTION("""COMPUTED_VALUE"""),"") | AA31: 0 | AB31: =IFERROR(__xludf.DUMMYFUNCTION("""COMPUTED_VALUE"""),1.0) -> 1 | AC31: 0 | AD31: =IFERROR(__xludf.DUMMYFUNCTION("""COMPUTED_VALUE"""),1.0) -> 1 | AE31: 3 | AF31: 2
B32: 46161 | C32: AMWT-YZRMEABRWQ | D32: https://agent-admin.paveapi.com/inspectionView/AMWT-YZRMEABRWQ?activeTab=past-sessions | T32: developer | U32: hoa.nguyenthi | X32: None | Z32: =IFERROR(__xludf.DUMMYFUNCTION("""COMPUTED_VALUE"""),"") | AA32: 0 | AB32: =IFERROR(__xludf.DUMMYFUNCTION("""COMPUTED_VALUE"""),1.0) -> 1 | AD32: =IFERROR(__xludf.DUMMYFUNCTION("""COMPUTED_VALUE"""),"") | AE32: 13 | AF32: 11
B33: 46161 | C33: AMWT-KTZTTMVOYX | D33: https://agent-admin.paveapi.com/inspectionView/AMWT-KTZTTMVOYX?activeTab=past-sessions | T33: developer | U33: tuong.nhambon | V33: hien.nhu | X33: None | Z33: =IFERROR(__xludf.DUMMYFUNCTION("""COMPUTED_VALUE"""),"") | AA33: 0 | AB33: =IFERROR(__xludf.DUMMYFUNCTION("""COMPUTED_VALUE"""),1.0) -> 1 | AC33: 0 | AD33: =IFERROR(__xludf.DUMMYFUNCTION("""COMPUTED_VALUE"""),1.0) -> 1 | AE33: 11 | AF33: 9
B34: 46161 | C34: AMWT-FFMLJOCVM3 | D34: https://agent-admin.paveapi.com/inspectionView/AMWT-FFMLJOCVM3?activeTab=past-sessions | F34: 1 | I34: 1 | T34: developer | U34: anh.nguyen | W34: View 5: (1) Damage OLD đã sửa chữa View 4: (3) Damage OLD xác định sai | X34: Checker Wrong damage | Z34: =IFERROR(__xludf.DUMMYFUNCTION("""COMPUTED_VALUE"""),"") | AA34: 2 | AB34: =IFERROR(__xludf.DUMMYFUNCTION("""COMPUTED_VALUE"""),0.7142857142857143) -> 0.71428571 | AD34: =IFERROR(__xludf.DUMMYFUNCTION("""COMPUTED_VALUE"""),"") | AE34: 7 | AF34: 5
B35: 46161 | C35: AMWT-9HXXOGDEVU | D35: https://agent-admin.paveapi.com/inspectionView/AMWT-9HXXOGDEVU?activeTab=past-sessions | T35: developer | U35: kiet.voanh | V35: hien.nhu | X35: None | Z35: =IFERROR(__xludf.DUMMYFUNCTION("""COMPUTED_VALUE"""),"") | AA35: 0 | AB35: =IFERROR(__xludf.DUMMYFUNCTION("""COMPUTED_VALUE"""),1.0) -> 1 | AC35: 0 | AD35: =IFERROR(__xludf.DUMMYFUNCTION("""COMPUTED_VALUE"""),1.0) -> 1 | AE35: 5 | AF35: 3
B36: 46161 | C36: AMUO-AUMBGZEHQX | D36: https://agent-admin.paveapi.com/inspectionView/AMUO-AUMBGZEHQX?activeTab=past-sessions | T36: thai.ps | U36: triet.le | X36: None | Y36: 0 | Z36: =IFERROR(__xludf.DUMMYFUNCTION("""COMPUTED_VALUE"""),1.0) -> 1 | AA36: 0 | AB36: =IFERROR(__xludf.DUMMYFUNCTION("""COMPUTED_VALUE"""),1.0) -> 1 | AD36: =IFERROR(__xludf.DUMMYFUNCTION("""COMPUTED_VALUE"""),"") | AE36: 5 | AF36: 5
B37: 46161 | C37: AMUO-PCIVOKBCKP | D37: https://agent-admin.paveapi.com/inspectionView/AMUO-PCIVOKBCKP?activeTab=past-sessions | T37: tho.nh | U37: triet.le | V37: thinh.nguyen | W37: View 8: Xóa damage ID trước đánh nghi ngờ | X37: None | Y37: 0 | Z37: =IFERROR(__xludf.DUMMYFUNCTION("""COMPUTED_VALUE"""),1.0) -> 1 | AA37: 0 | AB37: =IFERROR(__xludf.DUMMYFUNCTION("""COMPUTED_VALUE"""),1.0) -> 1 | AC37: 0 | AD37: =IFERROR(__xludf.DUMMYFUNCTION("""COMPUTED_VALUE"""),1.0) -> 1 | AE37: 5 | AF37: 4
B38: 46161 | C38: AMWT-RKFTXDIJNI | D38: https://agent-admin.paveapi.com/inspectionView/AMWT-RKFTXDIJNI?activeTab=past-sessions | T38: thien.ht | U38: linh.thai | W38: View 4: (5, 6) Damage OLD đã sửa chữa View 7: (2) Damage OLD đã sửa chữa | X38: Inspector + Checker Wrong damage | Y38: 0 | Z38: =IFERROR(__xludf.DUMMYFUNCTION("""COMPUTED_VALUE"""),1.0) -> 1 | AA38: 0 | AB38: =IFERROR(__xludf.DUMMYFUNCTION("""COMPUTED_VALUE"""),1.0) -> 1 | AD38: =IFERROR(__xludf.DUMMYFUNCTION("""COMPUTED_VALUE"""),"") | AE38: 38 | AF38: 18
B39: 46161 | C39: AMWT-CAZLAXFSR9 | D39: https://agent-admin.paveapi.com/inspectionView/AMWT-CAZLAXFSR9?activeTab=past-sessions | T39: phong.phantrung | U39: nguyen.nguyentran | V39: sang.tran | X39: None | Y39: 0 | Z39: =IFERROR(__xludf.DUMMYFUNCTION("""COMPUTED_VALUE"""),1.0) -> 1 | AA39: 0 | AB39: =IFERROR(__xludf.DUMMYFUNCTION("""COMPUTED_VALUE"""),1.0) -> 1 | AC39: 0 | AD39: =IFERROR(__xludf.DUMMYFUNCTION("""COMPUTED_VALUE"""),1.0) -> 1 | AE39: 18 | AF39: 14
B40: 46161 | C40: AMWT-AFYGEKZIBN | D40: https://agent-admin.paveapi.com/inspectionView/AMWT-AFYGEKZIBN?activeTab=past-sessions | T40: developer | U40: anh.nguyen | W40: sửa xấu -> sp | X40: None | Z40: =IFERROR(__xludf.DUMMYFUNCTION("""COMPUTED_VALUE"""),"") | AA40: 0 | AB40: =IFERROR(__xludf.DUMMYFUNCTION("""COMPUTED_VALUE"""),1.0) -> 1 | AD40: =IFERROR(__xludf.DUMMYFUNCTION("""COMPUTED_VALUE"""),"") | AE40: 16 | AF40: 4
B41: 46161 | C41: AMWT-2VFP7TKS1G | D41: https://agent-admin.paveapi.com/inspectionView/AMWT-2VFP7TKS1G?activeTab=past-sessions | T41: developer | U41: tuong.nhambon | V41: thong.nhat | X41: None | Z41: =IFERROR(__xludf.DUMMYFUNCTION("""COMPUTED_VALUE"""),"") | AA41: 0 | AB41: =IFERROR(__xludf.DUMMYFUNCTION("""COMPUTED_VALUE"""),1.0) -> 1 | AC41: 0 | AD41: =IFERROR(__xludf.DUMMYFUNCTION("""COMPUTED_VALUE"""),1.0) -> 1 | AE41: 4 | AF41: 0
B42: 46161 | C42: AMWT-DEULBSMVKU | D42: https://agent-admin.paveapi.com/inspectionView/AMWT-DEULBSMVKU?activeTab=past-sessions | T42: developer | U42: tuong.nhambon | X42: None | Z42: =IFERROR(__xludf.DUMMYFUNCTION("""COMPUTED_VALUE"""),"") | AA42: 0 | AB42: =IFERROR(__xludf.DUMMYFUNCTION("""COMPUTED_VALUE"""),1.0) -> 1 | AD42: =IFERROR(__xludf.DUMMYFUNCTION("""COMPUTED_VALUE"""),"") | AE42: 21 | AF42: 20
B43: 46161 | C43: AMWT-QGZEJD2PZI | D43: https://agent-admin.paveapi.com/inspectionView/AMWT-QGZEJD2PZI?activeTab=past-sessions | T43: developer | U43: thuy.ngodiem | V43: hien.nhu | X43: None | Z43: =IFERROR(__xludf.DUMMYFUNCTION("""COMPUTED_VALUE"""),"") | AA43: 0 | AB43: =IFERROR(__xludf.DUMMYFUNCTION("""COMPUTED_VALUE"""),1.0) -> 1 | AC43: 0 | AD43: =IFERROR(__xludf.DUMMYFUNCTION("""COMPUTED_VALUE"""),1.0) -> 1 | AE43: 20 | AF43: 19
B44: 46161 | C44: AMWT-KVXALMRDVA | D44: https://agent-admin.paveapi.com/inspectionView/AMWT-KVXALMRDVA?activeTab=past-sessions | T44: developer | U44: thai.ps | X44: None | Z44: =IFERROR(__xludf.DUMMYFUNCTION("""COMPUTED_VALUE"""),"") | AA44: 0 | AB44: =IFERROR(__xludf.DUMMYFUNCTION("""COMPUTED_VALUE"""),1.0) -> 1 | AD44: =IFERROR(__xludf.DUMMYFUNCTION("""COMPUTED_VALUE"""),"") | AE44: 14 | AF44: 13
B45: 46161 | C45: AMWT-GHSBYKLKDX | D45: https://agent-admin.paveapi.com/inspectionView/AMWT-GHSBYKLKDX?activeTab=past-sessions | L45: 2 | T45: developer | U45: son.bui | V45: tong.nguyen | X45: Checker Wrong damage | Z45: =IFERROR(__xludf.DUMMYFUNCTION("""COMPUTED_VALUE"""),"") | AA45: 2 | AB45: =IFERROR(__xludf.DUMMYFUNCTION("""COMPUTED_VALUE"""),0.8461538461538461) -> 0.84615385 | AC45: 0 | AD45: =IFERROR(__xludf.DUMMYFUNCTION("""COMPUTED_VALUE"""),1.0) -> 1 | AE45: 13 | AF45: 9
A46: 0519-1hrs_EU | B46: 46161 | C46: AMFR-FI5VOY04WG | D46: https://agent-admin.paveapi.com/inspectionView/AMFR-FI5VOY04WG?activeTab=past-sessions | I46: 1 | T46: developer | U46: thai.ps | X46: Checker Wrong damage | Z46: =IFERROR(__xludf.DUMMYFUNCTION("""COMPUTED_VALUE"""),"") | AA46: 1 | AB46: =IFERROR(__xludf.DUMMYFUNCTION("""COMPUTED_VALUE"""),0.9583333333333334) -> 0.95833333 | AD46: =IFERROR(__xludf.DUMMYFUNCTION("""COMPUTED_VALUE"""),"") | AE46: 24 | AF46: 13
B47: 46161 | C47: AMFR-DUYRYNR4RA | D47: https://agent-admin.paveapi.com/inspectionView/AMFR-DUYRYNR4RA?activeTab=past-sessions | T47: developer | U47: phong.phantrung | V47: tong.nguyen | X47: None | Z47: =IFERROR(__xludf.DUMMYFUNCTION("""COMPUTED_VALUE"""),"") | AA47: 0 | AB47: =IFERROR(__xludf.DUMMYFUNCTION("""COMPUTED_VALUE"""),1.0) -> 1 | AC47: 0 | AD47: =IFERROR(__xludf.DUMMYFUNCTION("""COMPUTED_VALUE"""),1.0) -> 1 | AE47: 15 | AF47: 8
A48: 0520-1hrs_NA | B48: 46162 | C48: AMRR-OZLMNXYP6V | D48: https://agent-admin.paveapi.com/inspectionView/AMRR-OZLMNXYP6V?activeTab=past-sessions | T48: developer | U48: anh.le | X48: None | Z48: =IFERROR(__xludf.DUMMYFUNCTION("""COMPUTED_VALUE"""),"") | AA48: 0 | AB48: =IFERROR(__xludf.DUMMYFUNCTION("""COMPUTED_VALUE"""),1.0) -> 1 | AD48: =IFERROR(__xludf.DUMMYFUNCTION("""COMPUTED_VALUE"""),"") | AE48: 21 | AF48: 18
B49: 46162 | C49: AMRR-JF4KPDCGVZ | D49: https://agent-admin.paveapi.com/inspectionView/AMRR-JF4KPDCGVZ?activeTab=past-sessions | T49: developer | U49: nguyen.vudinh | V49: sang.tran | X49: None | Z49: =IFERROR(__xludf.DUMMYFUNCTION("""COMPUTED_VALUE"""),"") | AA49: 0 | AB49: =IFERROR(__xludf.DUMMYFUNCTION("""COMPUTED_VALUE"""),1.0) -> 1 | AC49: 0 | AD49: =IFERROR(__xludf.DUMMYFUNCTION("""COMPUTED_VALUE"""),1.0) -> 1 | AE49: 18 | AF49: 14
B50: 46162 | C50: AMWT-2E6VCWYOGJ | D50: https://agent-admin.paveapi.com/inspectionView/AMWT-2E6VCWYOGJ?activeTab=past-sessions | T50: developer | U50: huy.tran | X50: None | Z50: =IFERROR(__xludf.DUMMYFUNCTION("""COMPUTED_VALUE"""),"") | AA50: 0 | AB50: =IFERROR(__xludf.DUMMYFUNCTION("""COMPUTED_VALUE"""),1.0) -> 1 | AD50: =IFERROR(__xludf.DUMMYFUNCTION("""COMPUTED_VALUE"""),"") | AE50: 24 | AF50: 10
B51: 46162 | C51: AMRR-JBWYQOMIOG | D51: https://agent-admin.paveapi.com/inspectionView/AMRR-JBWYQOMIOG?activeTab=past-sessions | M51: 1 | T51: developer | U51: tuong.nhambon | V51: anh.dao | W51: View 7: (6) Damage OLD xóa sai damage | X51: CC/AD Wrong damage | Z51: =IFERROR(__xludf.DUMMYFUNCTION("""COMPUTED_VALUE"""),"") | AA51: 0 | AB51: =IFERROR(__xludf.DUMMYFUNCTION("""COMPUTED_VALUE"""),1.0) -> 1 | AC51: 1 | AD51: =IFERROR(__xludf.DUMMYFUNCTION("""COMPUTED_VALUE"""),0.9) -> 0.9 | AE51: 10 | AF51: 9
B52: 46162 | C52: AMWT-5IHMOJN3KV | D52: https://agent-admin.paveapi.com/inspectionView/AMWT-5IHMOJN3KV?activeTab=past-sessions | T52: developer | U52: giau.nguyen | X52: None | Z52: =IFERROR(__xludf.DUMMYFUNCTION("""COMPUTED_VALUE"""),"") | AA52: 0 | AB52: =IFERROR(__xludf.DUMMYFUNCTION("""COMPUTED_VALUE"""),1.0) -> 1 | AD52: =IFERROR(__xludf.DUMMYFUNCTION("""COMPUTED_VALUE"""),"") | AE52: 63 | AF52: 41
B53: 46162 | C53: AMWT-XFA6A1GZR5 | D53: https://agent-admin.paveapi.com/inspectionView/AMWT-XFA6A1GZR5?activeTab=past-sessions | T53: developer | U53: cuong.nguyenthanhthe | V53: trinh.ho | X53: None | Z53: =IFERROR(__xludf.DUMMYFUNCTION("""COMPUTED_VALUE"""),"") | AA53: 0 | AB53: =IFERROR(__xludf.DUMMYFUNCTION("""COMPUTED_VALUE"""),1.0) -> 1 | AC53: 0 | AD53: =IFERROR(__xludf.DUMMYFUNCTION("""COMPUTED_VALUE"""),1.0) -> 1 | AE53: 41 | AF53: 35
B54: 46162 | C54: AMWT-H78D2SZZMW | D54: https://agent-admin.paveapi.com/inspectionView/AMWT-H78D2SZZMW?activeTab=past-sessions | T54: developer | U54: khang.nguyen | X54: None | Z54: =IFERROR(__xludf.DUMMYFUNCTION("""COMPUTED_VALUE"""),"") | AA54: 0 | AB54: =IFERROR(__xludf.DUMMYFUNCTION("""COMPUTED_VALUE"""),1.0) -> 1 | AD54: =IFERROR(__xludf.DUMMYFUNCTION("""COMPUTED_VALUE"""),"") | AE54: 30 | AF54: 28
B55: 46162 | C55: AMWT-IBDQJLFAIS | D55: https://agent-admin.paveapi.com/inspectionView/AMWT-IBDQJLFAIS?activeTab=past-sessions | T55: developer | U55: thai.ps | V55: thinh.nguyen | X55: None | Z55: =IFERROR(__xludf.DUMMYFUNCTION("""COMPUTED_VALUE"""),"") | AA55: 0 | AB55: =IFERROR(__xludf.DUMMYFUNCTION("""COMPUTED_VALUE"""),1.0) -> 1 | AC55: 0 | AD55: =IFERROR(__xludf.DUMMYFUNCTION("""COMPUTED_VALUE"""),1.0) -> 1 | AE55: 28 | AF55: 26
B56: 46162 | C56: AMWT-QCLG8NKTBB | D56: https://agent-admin.paveapi.com/inspectionView/AMWT-QCLG8NKTBB?activeTab=past-sessions | I56: 3 | T56: developer | U56: huy.tran | W56: View 5: (3, 4, 5) Damage OLD đã sửa chữa | X56: Checker Wrong damage | Z56: =IFERROR(__xludf.DUMMYFUNCTION("""COMPUTED_VALUE"""),"") | AA56: 3 | AB56: =IFERROR(__xludf.DUMMYFUNCTION("""COMPUTED_VALUE"""),0.7692307692307692) -> 0.76923077 | AD56: =IFERROR(__xludf.DUMMYFUNCTION("""COMPUTED_VALUE"""),"") | AE56: 13 | AF56: 12
B57: 46162 | C57: AMWT-4HWNJ9UOBS | D57: https://agent-admin.paveapi.com/inspectionView/AMWT-4HWNJ9UOBS?activeTab=past-sessions | T57: developer | U57: thai.ps | V57: huyhien.nguyen | X57: None | Z57: =IFERROR(__xludf.DUMMYFUNCTION("""COMPUTED_VALUE"""),"") | AA57: 0 | AB57: =IFERROR(__xludf.DUMMYFUNCTION("""COMPUTED_VALUE"""),1.0) -> 1 | AC57: 0 | AD57: =IFERROR(__xludf.DUMMYFUNCTION("""COMPUTED_VALUE"""),1.0) -> 1 | AE57: 12 | AF57: 7
B58: 46162 | C58: AMWT-O9BZSUEMNR | D58: https://agent-admin.paveapi.com/inspectionView/AMWT-O9BZSUEMNR?activeTab=past-sessions | T58: developer | U58: duy.nguyenquoc | X58: None | Z58: =IFERROR(__xludf.DUMMYFUNCTION("""COMPUTED_VALUE"""),"") | AA58: 0 | AB58: =IFERROR(__xludf.DUMMYFUNCTION("""COMPUTED_VALUE"""),1.0) -> 1 | AD58: =IFERROR(__xludf.DUMMYFUNCTION("""COMPUTED_VALUE"""),"") | AE58: 35 | AF58: 12
B59: 46162 | C59: AMWT-AUTEPJ6QEI | D59: https://agent-admin.paveapi.com/inspectionView/AMWT-AUTEPJ6QEI?activeTab=past-sessions | T59: developer | U59: huy.tran | V59: anh.dao | X59: None | Z59: =IFERROR(__xludf.DUMMYFUNCTION("""COMPUTED_VALUE"""),"") | AA59: 0 | AB59: =IFERROR(__xludf.DUMMYFUNCTION("""COMPUTED_VALUE"""),1.0) -> 1 | AC59: 0 | AD59: =IFERROR(__xludf.DUMMYFUNCTION("""COMPUTED_VALUE"""),1.0) -> 1 | AE59: 14 | AF59: 12
B60: 46162 | C60: AMWT-AZQTMPVVSF | D60: https://agent-admin.paveapi.com/inspectionView/AMWT-AZQTMPVVSF?activeTab=past-sessions | T60: developer | U60: truong.nguyen | X60: None | Z60: =IFERROR(__xludf.DUMMYFUNCTION("""COMPUTED_VALUE"""),"") | AA60: 0 | AB60: =IFERROR(__xludf.DUMMYFUNCTION("""COMPUTED_VALUE"""),1.0) -> 1 | AD60: =IFERROR(__xludf.DUMMYFUNCTION("""COMPUTED_VALUE"""),"") | AE60: 4 | AF60: 4
B61: 46162 | C61: AMWT-W6K3ENBLAB | D61: https://agent-admin.paveapi.com/inspectionView/AMWT-W6K3ENBLAB?activeTab=past-sessions | T61: developer | U61: tram.mai | V61: tong.nguyen | W61: View 4: Xóa damage ID trước đánh nghi ngờ | X61: None | Z61: =IFERROR(__xludf.DUMMYFUNCTION("""COMPUTED_VALUE"""),"") | AA61: 0 | AB61: =IFERROR(__xludf.DUMMYFUNCTION("""COMPUTED_VALUE"""),1.0) -> 1 | AC61: 0 | AD61: =IFERROR(__xludf.DUMMYFUNCTION("""COMPUTED_VALUE"""),1.0) -> 1 | AE61: 4 | AF61: 3
B62: 46162 | C62: AMWT-0PNYYZGQVQ | D62: https://agent-admin.paveapi.com/inspectionView/AMWT-0PNYYZGQVQ?activeTab=past-sessions | L62: 1 | T62: developer | U62: bao.vo | W62: View 7: (1) Damage OLD kích thước nhỏ | X62: Checker Wrong damage | Z62: =IFERROR(__xludf.DUMMYFUNCTION("""COMPUTED_VALUE"""),"") | AA62: 1 | AB62: =IFERROR(__xludf.DUMMYFUNCTION("""COMPUTED_VALUE"""),0.8) -> 0.8 | AD62: =IFERROR(__xludf.DUMMYFUNCTION("""COMPUTED_VALUE"""),"") | AE62: 5 | AF62: 5
B63: 46162 | C63: AMWT-RPSSG99U5S | D63: https://agent-admin.paveapi.com/inspectionView/AMWT-RPSSG99U5S?activeTab=past-sessions | T63: developer | U63: thao.phan | V63: tram.tranngoc | X63: None | Z63: =IFERROR(__xludf.DUMMYFUNCTION("""COMPUTED_VALUE"""),"") | AA63: 0 | AB63: =IFERROR(__xludf.DUMMYFUNCTION("""COMPUTED_VALUE"""),1.0) -> 1 | AC63: 0 | AD63: =IFERROR(__xludf.DUMMYFUNCTION("""COMPUTED_VALUE"""),1.0) -> 1 | AE63: 5 | AF63: 4
B64: 46162 | C64: AMUO-4VS5Q2CSH5 | D64: https://agent-admin.paveapi.com/inspectionView/AMUO-4VS5Q2CSH5?activeTab=past-sessions | T64: developer | U64: huyhien.nguyen | X64: None | Z64: =IFERROR(__xludf.DUMMYFUNCTION("""COMPUTED_VALUE"""),"") | AA64: 0 | AB64: =IFERROR(__xludf.DUMMYFUNCTION("""COMPUTED_VALUE"""),1.0) -> 1 | AD64: =IFERROR(__xludf.DUMMYFUNCTION("""COMPUTED_VALUE"""),"") | AE64: 8 | AF64: 6
B65: 46162 | C65: AMUO-47UJ7TJVZR | D65: https://agent-admin.paveapi.com/inspectionView/AMUO-47UJ7TJVZR?activeTab=past-sessions | T65: developer | U65: sang.tran | W65: View 4: Xóa damage ID trước đánh nghi ngờ | X65: None | Z65: =IFERROR(__xludf.DUMMYFUNCTION("""COMPUTED_VALUE"""),"") | AA65: 0 | AB65: =IFERROR(__xludf.DUMMYFUNCTION("""COMPUTED_VALUE"""),1.0) -> 1 | AD65: =IFERROR(__xludf.DUMMYFUNCTION("""COMPUTED_VALUE"""),"") | AE65: 6 | AF65: 5
B66: 46162 | C66: AMWT-URY1XODQ5G | D66: https://agent-admin.paveapi.com/inspectionView/AMWT-URY1XODQ5G?activeTab=past-sessions | L66: 1 | T66: developer | U66: tan.pham | W66: View 7: (2, 3) Damage NEW xác định sai | X66: Checker Wrong damage | Z66: =IFERROR(__xludf.DUMMYFUNCTION("""COMPUTED_VALUE"""),"") | AA66: 1 | AB66: =IFERROR(__xludf.DUMMYFUNCTION("""COMPUTED_VALUE"""),0.8571428571428572) -> 0.85714286 | AD66: =IFERROR(__xludf.DUMMYFUNCTION("""COMPUTED_VALUE"""),"") | AE66: 7 | AF66: 5
B67: 46162 | C67: AMWT-ERRCB2WK0D | D67: https://agent-admin.paveapi.com/inspectionView/AMWT-ERRCB2WK0D?activeTab=past-sessions | T67: developer | U67: nhi.huynhtranuyen | V67: nhat.ngo | X67: None | Z67: =IFERROR(__xludf.DUMMYFUNCTION("""COMPUTED_VALUE"""),"") | AA67: 0 | AB67: =IFERROR(__xludf.DUMMYFUNCTION("""COMPUTED_VALUE"""),1.0) -> 1 | AC67: 0 | AD67: =IFERROR(__xludf.DUMMYFUNCTION("""COMPUTED_VALUE"""),1.0) -> 1 | AE67: 5 | AF67: 3
B68: 46162 | C68: AMWT-XNJDJ9YQVB | D68: https://agent-admin.paveapi.com/inspectionView/AMWT-XNJDJ9YQVB?activeTab=past-sessions | T68: developer | U68: duy.nguyenquoc | W68: sửa chưa hoàn thiện + hình tối, sp | X68: None | Z68: =IFERROR(__xludf.DUMMYFUNCTION("""COMPUTED_VALUE"""),"") | AA68: 0 | AB68: =IFERROR(__xludf.DUMMYFUNCTION("""COMPUTED_VALUE"""),1.0) -> 1 | AD68: =IFERROR(__xludf.DUMMYFUNCTION("""COMPUTED_VALUE"""),"") | AE68: 50 | AF68: 38
B69: 46162 | C69: AMWT-ZUD3XDPO4E | D69: https://agent-admin.paveapi.com/inspectionView/AMWT-ZUD3XDPO4E?activeTab=past-sessions | T69: developer | U69: duc.ngominh | V69: huyhien.nguyen | X69: None | Z69: =IFERROR(__xludf.DUMMYFUNCTION("""COMPUTED_VALUE"""),"") | AA69: 0 | AB69: =IFERROR(__xludf.DUMMYFUNCTION("""COMPUTED_VALUE"""),1.0) -> 1 | AC69: 0 | AD69: =IFERROR(__xludf.DUMMYFUNCTION("""COMPUTED_VALUE"""),1.0) -> 1 | AE69: 38 | AF69: 13
B70: 46162 | C70: AMWT-ZBVCXS6YQH | D70: https://agent-admin.paveapi.com/inspectionView/AMWT-ZBVCXS6YQH?activeTab=past-sessions | T70: developer | U70: an.nguyen | X70: None | Z70: =IFERROR(__xludf.DUMMYFUNCTION("""COMPUTED_VALUE"""),"") | AA70: 0 | AB70: =IFERROR(__xludf.DUMMYFUNCTION("""COMPUTED_VALUE"""),1.0) -> 1 | AD70: =IFERROR(__xludf.DUMMYFUNCTION("""COMPUTED_VALUE"""),"") | AE70: 37 | AF70: 37
B71: 46162 | C71: AMWT-HTVEEY0R3B | D71: https://agent-admin.paveapi.com/inspectionView/AMWT-HTVEEY0R3B?activeTab=past-sessions | J71: 1 | T71: developer | U71: anh.le | V71: thinh.nguyen | W71: View 5: (10) Damage OLD xóa sai damage | X71: CC/AD Wrong damage | Z71: =IFERROR(__xludf.DUMMYFUNCTION("""COMPUTED_VALUE"""),"") | AA71: 0 | AB71: =IFERROR(__xludf.DUMMYFUNCTION("""COMPUTED_VALUE"""),1.0) -> 1 | AC71: 1 | AD71: =IFERROR(__xludf.DUMMYFUNCTION("""COMPUTED_VALUE"""),0.9722222222222222) -> 0.97222222 | AE71: 36 | AF71: 35
B72: 46162 | C72: AMWT-Z8QWJ3XFWG | D72: https://agent-admin.paveapi.com/inspectionView/AMWT-Z8QWJ3XFWG?activeTab=past-sessions | T72: developer | U72: an.nguyen | X72: None | Z72: =IFERROR(__xludf.DUMMYFUNCTION("""COMPUTED_VALUE"""),"") | AA72: 0 | AB72: =IFERROR(__xludf.DUMMYFUNCTION("""COMPUTED_VALUE"""),1.0) -> 1 | AD72: =IFERROR(__xludf.DUMMYFUNCTION("""COMPUTED_VALUE"""),"") | AE72: 29 | AF72: 7
B73: 46162 | C73: AMWT-Z4O99EH73A | D73: https://agent-admin.paveapi.com/inspectionView/AMWT-Z4O99EH73A?activeTab=past-sessions | T73: developer | U73: linh.thai | V73: sang.tran | X73: None | Z73: =IFERROR(__xludf.DUMMYFUNCTION("""COMPUTED_VALUE"""),"") | AA73: 0 | AB73: =IFERROR(__xludf.DUMMYFUNCTION("""COMPUTED_VALUE"""),1.0) -> 1 | AC73: 0 | AD73: =IFERROR(__xludf.DUMMYFUNCTION("""COMPUTED_VALUE"""),1.0) -> 1 | AE73: 7 | AF73: 6
B74: 46162 | C74: AMWT-SZWRFBIE6C | D74: https://agent-admin.paveapi.com/inspectionView/AMWT-SZWRFBIE6C?activeTab=past-sessions | T74: developer | U74: duy.nguyenquoc | X74: None | Z74: =IFERROR(__xludf.DUMMYFUNCTION("""COMPUTED_VALUE"""),"") | AA74: 0 | AB74: =IFERROR(__xludf.DUMMYFUNCTION("""COMPUTED_VALUE"""),1.0) -> 1 | AD74: =IFERROR(__xludf.DUMMYFUNCTION("""COMPUTED_VALUE"""),"") | AE74: 19 | AF74: 17
B75: 46162 | C75: AMWT-ATTIMAVAH5 | D75: https://agent-admin.paveapi.com/inspectionView/AMWT-ATTIMAVAH5?activeTab=past-sessions | T75: developer | U75: tinh.nguyenmaiviet | V75: trinh.ho | W75: View 7, 8: Xóa damage ID trước đánh nghi ngờ | X75: None | Z75: =IFERROR(__xludf.DUMMYFUNCTION("""COMPUTED_VALUE"""),"") | AA75: 0 | AB75: =IFERROR(__xludf.DUMMYFUNCTION("""COMPUTED_VALUE"""),1.0) -> 1 | AC75: 0 | AD75: =IFERROR(__xludf.DUMMYFUNCTION("""COMPUTED_VALUE"""),1.0) -> 1 | AE75: 17 | AF75: 13
B76: 46162 | C76: AMDE-9DKNISMVYV | D76: https://agent-admin.paveapi.com/inspectionView/AMDE-9DKNISMVYV?activeTab=past-sessions | T76: developer | U76: y.anhongkim | X76: None | Z76: =IFERROR(__xludf.DUMMYFUNCTION("""COMPUTED_VALUE"""),"") | AA76: 0 | AB76: =IFERROR(__xludf.DUMMYFUNCTION("""COMPUTED_VALUE"""),1.0) -> 1 | AD76: =IFERROR(__xludf.DUMMYFUNCTION("""COMPUTED_VALUE"""),"") | AE76: 4 | AF76: 4
A77: 0520-1hrs_EU | B77: 46162 | C77: AMWK-04GQCS5Q1M | D77: https://agent-admin.paveapi.com/inspectionView/AMWK-04GQCS5Q1M?activeTab=past-sessions | T77: developer | U77: thanhha.tran | W77: View 4: (7, 25) Damage OLD đã sửa chữa View 5: (5) Damage OLD đã sửa chữa View 7: (3) Damage OLD đã sửa chữa | X77: Checker Wrong damage | Z77: =IFERROR(__xludf.DUMMYFUNCTION("""COMPUTED_VALUE"""),"") | AA77: 0 | AB77: =IFERROR(__xludf.DUMMYFUNCTION("""COMPUTED_VALUE"""),1.0) -> 1 | AD77: =IFERROR(__xludf.DUMMYFUNCTION("""COMPUTED_VALUE"""),"") | AE77: 89 | AF77: 85
B78: 46162 | C78: AMWK-UUQYCDUDIF | D78: https://agent-admin.paveapi.com/inspectionView/AMWK-UUQYCDUDIF?activeTab=past-sessions | T78: developer | U78: ngan.luongthi | V78: thong.nhat | X78: None | Z78: =IFERROR(__xludf.DUMMYFUNCTION("""COMPUTED_VALUE"""),"") | AA78: 0 | AB78: =IFERROR(__xludf.DUMMYFUNCTION("""COMPUTED_VALUE"""),1.0) -> 1 | AC78: 0 | AD78: =IFERROR(__xludf.DUMMYFUNCTION("""COMPUTED_VALUE"""),1.0) -> 1 | AE78: 85 | AF78: 82
A79: 0521-1hrs_NA | B79: 46163 | C79: AMWT-KWQIWL3WAS | D79: https://agent-admin.paveapi.com/inspectionView/AMWT-KWQIWL3WAS?activeTab=past-sessions | T79: developer | U79: uyen.tran | X79: None | Z79: =IFERROR(__xludf.DUMMYFUNCTION("""COMPUTED_VALUE"""),"") | AA79: 0 | AB79: =IFERROR(__xludf.DUMMYFUNCTION("""COMPUTED_VALUE"""),1.0) -> 1 | AD79: =IFERROR(__xludf.DUMMYFUNCTION("""COMPUTED_VALUE"""),"") | AE79: 2 | AF79: 2
B80: 46163 | C80: AMWT-UZJV0CJTI5 | D80: https://agent-admin.paveapi.com/inspectionView/AMWT-UZJV0CJTI5?activeTab=past-sessions | T80: developer | U80: tinh.nguyenmaiviet | V80: anh.dao | W80: View 7: Xóa damage ID trước đánh nghi ngờ | X80: None | Z80: =IFERROR(__xludf.DUMMYFUNCTION("""COMPUTED_VALUE"""),"") | AA80: 0 | AB80: =IFERROR(__xludf.DUMMYFUNCTION("""COMPUTED_VALUE"""),1.0) -> 1 | AC80: 0 | AD80: =IFERROR(__xludf.DUMMYFUNCTION("""COMPUTED_VALUE"""),1.0) -> 1 | AE80: 2 | AF80: 1
B81: 46163 | C81: AMWT-WYUPJGTSH3 | D81: https://agent-admin.paveapi.com/inspectionView/AMWT-WYUPJGTSH3?activeTab=past-sessions | T81: developer | U81: nhu.nguyen | X81: None | Z81: =IFERROR(__xludf.DUMMYFUNCTION("""COMPUTED_VALUE"""),"") | AA81: 0 | AB81: =IFERROR(__xludf.DUMMYFUNCTION("""COMPUTED_VALUE"""),1.0) -> 1 | AD81: =IFERROR(__xludf.DUMMYFUNCTION("""COMPUTED_VALUE"""),"") | AE81: 24 | AF81: 21
B82: 46163 | C82: AMWT-OWB8UWYMNX | D82: https://agent-admin.paveapi.com/inspectionView/AMWT-OWB8UWYMNX?activeTab=past-sessions | T82: developer | U82: phong.nguyen | V82: hai.nguyen | W82: View 8: Xóa damage ID trước đánh nghi ngờ | X82: None | Z82: =IFERROR(__xludf.DUMMYFUNCTION("""COMPUTED_VALUE"""),"") | AA82: 0 | AB82: =IFERROR(__xludf.DUMMYFUNCTION("""COMPUTED_VALUE"""),1.0) -> 1 | AC82: 0 | AD82: =IFERROR(__xludf.DUMMYFUNCTION("""COMPUTED_VALUE"""),1.0) -> 1 | AE82: 21 | AF82: 19
B83: 46163 | C83: AMWT-CSWBNCY762 | D83: https://agent-admin.paveapi.com/inspectionView/AMWT-CSWBNCY762?activeTab=past-sessions | L83: 1 | T83: developer | U83: linh.ptt | W83: View 7: (2) Damage OLD đã sửa chữa | X83: Checker Wrong damage | Z83: =IFERROR(__xludf.DUMMYFUNCTION("""COMPUTED_VALUE"""),"") | AA83: 1 | AB83: =IFERROR(__xludf.DUMMYFUNCTION("""COMPUTED_VALUE"""),0.9411764705882353) -> 0.94117647 | AD83: =IFERROR(__xludf.DUMMYFUNCTION("""COMPUTED_VALUE"""),"") | AE83: 17 | AF83: 17
B84: 46163 | C84: AMWT-ESXPOXFXSZ | D84: https://agent-admin.paveapi.com/inspectionView/AMWT-ESXPOXFXSZ?activeTab=past-sessions | T84: developer | U84: an.nguyen | V84: huyhien.nguyen | X84: None | Z84: =IFERROR(__xludf.DUMMYFUNCTION("""COMPUTED_VALUE"""),"") | AA84: 0 | AB84: =IFERROR(__xludf.DUMMYFUNCTION("""COMPUTED_VALUE"""),1.0) -> 1 | AC84: 0 | AD84: =IFERROR(__xludf.DUMMYFUNCTION("""COMPUTED_VALUE"""),1.0) -> 1 | AE84: 17 | AF84: 13
B85: 46163 | C85: AMWT-AEQXHX1IUZ | D85: https://agent-admin.paveapi.com/inspectionView/AMWT-AEQXHX1IUZ?activeTab=past-sessions | T85: developer | U85: duy.bui | X85: None | Z85: =IFERROR(__xludf.DUMMYFUNCTION("""COMPUTED_VALUE"""),"") | AA85: 0 | AB85: =IFERROR(__xludf.DUMMYFUNCTION("""COMPUTED_VALUE"""),1.0) -> 1 | AD85: =IFERROR(__xludf.DUMMYFUNCTION("""COMPUTED_VALUE"""),"") | AE85: 5 | AF85: 3
B86: 46163 | C86: AMWT-TGCSRQC0BE | D86: https://agent-admin.paveapi.com/inspectionView/AMWT-TGCSRQC0BE?activeTab=past-sessions | M86: 1 | T86: developer | U86: duy.bui | V86: sang.tran | W86: View 7: (1, 2) Damage OLD xóa sai damage | X86: Checker Wrong damage | Z86: =IFERROR(__xludf.DUMMYFUNCTION("""COMPUTED_VALUE"""),"") | AA86: 0 | AB86: =IFERROR(__xludf.DUMMYFUNCTION("""COMPUTED_VALUE"""),1.0) -> 1 | AC86: 0 | AD86: =IFERROR(__xludf.DUMMYFUNCTION("""COMPUTED_VALUE"""),1.0) -> 1 | AE86: 3 | AF86: 1
B87: 46163 | C87: AMWT-7S0Q7DP52M | D87: https://agent-admin.paveapi.com/inspectionView/AMWT-7S0Q7DP52M?activeTab=past-sessions | T87: developer | U87: linh.ptt | X87: None | Z87: =IFERROR(__xludf.DUMMYFUNCTION("""COMPUTED_VALUE"""),"") | AA87: 0 | AB87: =IFERROR(__xludf.DUMMYFUNCTION("""COMPUTED_VALUE"""),1.0) -> 1 | AD87: =IFERROR(__xludf.DUMMYFUNCTION("""COMPUTED_VALUE"""),"") | AE87: 7 | AF87: 6
B88: 46163 | C88: AMWT-FDW4BPWAFV | D88: https://agent-admin.paveapi.com/inspectionView/AMWT-FDW4BPWAFV?activeTab=past-sessions | T88: developer | U88: phong.phantrung | V88: phuong.nguyen | W88: View 7: Xóa damage ID trước đánh nghi ngờ | X88: None | Z88: =IFERROR(__xludf.DUMMYFUNCTION("""COMPUTED_VALUE"""),"") | AA88: 0 | AB88: =IFERROR(__xludf.DUMMYFUNCTION("""COMPUTED_VALUE"""),1.0) -> 1 | AC88: 0 | AD88: =IFERROR(__xludf.DUMMYFUNCTION("""COMPUTED_VALUE"""),1.0) -> 1 | AE88: 6 | AF88: 5
B89: 46163 | C89: AMWT-LF3Q3ERV4T | D89: https://agent-admin.paveapi.com/inspectionView/AMWT-LF3Q3ERV4T?activeTab=past-sessions | T89: developer | U89: giau.nguyen | X89: None | Z89: =IFERROR(__xludf.DUMMYFUNCTION("""COMPUTED_VALUE"""),"") | AA89: 0 | AB89: =IFERROR(__xludf.DUMMYFUNCTION("""COMPUTED_VALUE"""),1.0) -> 1 | AD89: =IFERROR(__xludf.DUMMYFUNCTION("""COMPUTED_VALUE"""),"") | AE89: 8 | AF89: 7
B90: 46163 | C90: AMWT-UCRAEIWALK | D90: https://agent-admin.paveapi.com/inspectionView/AMWT-UCRAEIWALK?activeTab=past-sessions | T90: developer | U90: mai.luungoc | V90: thong.nhat | W90: View 8: Xóa damage ID trước đánh nghi ngờ | X90: None | Z90: =IFERROR(__xludf.DUMMYFUNCTION("""COMPUTED_VALUE"""),"") | AA90: 0 | AB90: =IFERROR(__xludf.DUMMYFUNCTION("""COMPUTED_VALUE"""),1.0) -> 1 | AC90: 0 | AD90: =IFERROR(__xludf.DUMMYFUNCTION("""COMPUTED_VALUE"""),1.0) -> 1 | AE90: 8 | AF90: 7
B91: 46163 | C91: AMWT-WVH7WQXAFT | D91: https://agent-admin.paveapi.com/inspectionView/AMWT-WVH7WQXAFT?activeTab=past-sessions | I91: 1 | T91: developer | U91: duy.nk | W91: View 5: BROKEN_MEDIUM - BUMPER_FRONT_UNIQUE TK ID: AMWT-MWB3PFU6KX | X91: Checker Miss Damage | Z91: =IFERROR(__xludf.DUMMYFUNCTION("""COMPUTED_VALUE"""),"") | AA91: 1 | AB91: =IFERROR(__xludf.DUMMYFUNCTION("""COMPUTED_VALUE"""),0.9833333333333333) -> 0.98333333 | AD91: =IFERROR(__xludf.DUMMYFUNCTION("""COMPUTED_VALUE"""),"") | AE91: 59 | AF91: 58
B92: 46163 | C92: AMWT-MWB3PFU6KX | D92: https://agent-admin.paveapi.com/inspectionView/AMWT-MWB3PFU6KX?activeTab=past-sessions | T92: developer | U92: thao.phan | V92: nhat.ngo | X92: None | Z92: =IFERROR(__xludf.DUMMYFUNCTION("""COMPUTED_VALUE"""),"") | AA92: 0 | AB92: =IFERROR(__xludf.DUMMYFUNCTION("""COMPUTED_VALUE"""),1.0) -> 1 | AC92: 0 | AD92: =IFERROR(__xludf.DUMMYFUNCTION("""COMPUTED_VALUE"""),1.0) -> 1 | AE92: 58 | AF92: 46
B93: 46163 | C93: AMWT-IWYYZOFFFL | D93: https://agent-admin.paveapi.com/inspectionView/AMWT-IWYYZOFFFL?activeTab=past-sessions | T93: developer | U93: huy.tran | X93: None | Z93: =IFERROR(__xludf.DUMMYFUNCTION("""COMPUTED_VALUE"""),"") | AA93: 0 | AB93: =IFERROR(__xludf.DUMMYFUNCTION("""COMPUTED_VALUE"""),1.0) -> 1 | AD93: =IFERROR(__xludf.DUMMYFUNCTION("""COMPUTED_VALUE"""),"") | AE93: 0 | AF93: 1
B94: 46163 | C94: AMWT-CMOLH1RQOL | D94: https://agent-admin.paveapi.com/inspectionView/AMWT-CMOLH1RQOL?activeTab=past-sessions | T94: developer | U94: thanhha.tran | V94: tam.to | X94: None | Z94: =IFERROR(__xludf.DUMMYFUNCTION("""COMPUTED_VALUE"""),"") | AA94: 0 | AB94: =IFERROR(__xludf.DUMMYFUNCTION("""COMPUTED_VALUE"""),1.0) -> 1 | AC94: 0 | AD94: =IFERROR(__xludf.DUMMYFUNCTION("""COMPUTED_VALUE"""),1.0) -> 1 | AE94: 1 | AF94: 0
B95: 46163 | C95: AMWT-GSMMEHFALC | D95: https://agent-admin.paveapi.com/inspectionView/AMWT-GSMMEHFALC?activeTab=past-sessions | F95: 1 | T95: developer | U95: thinh.phanxuan | W95: View 4: (1) Damage OLD xác định sai | X95: Checker Wrong damage | Z95: =IFERROR(__xludf.DUMMYFUNCTION("""COMPUTED_VALUE"""),"") | AA95: 1 | AB95: =IFERROR(__xludf.DUMMYFUNCTION("""COMPUTED_VALUE"""),0.6666666666666667) -> 0.66666667 | AD95: =IFERROR(__xludf.DUMMYFUNCTION("""COMPUTED_VALUE"""),"") | AE95: 3 | AF95: 3
B96: 46163 | C96: AMWT-GPJ2MEIWGB | D96: https://agent-admin.paveapi.com/inspectionView/AMWT-GPJ2MEIWGB?activeTab=past-sessions | T96: developer | U96: khang.nguyen | V96: dung.tran | X96: None | Z96: =IFERROR(__xludf.DUMMYFUNCTION("""COMPUTED_VALUE"""),"") | AA96: 0 | AB96: =IFERROR(__xludf.DUMMYFUNCTION("""COMPUTED_VALUE"""),1.0) -> 1 | AC96: 0 | AD96: =IFERROR(__xludf.DUMMYFUNCTION("""COMPUTED_VALUE"""),1.0) -> 1 | AE96: 3 | AF96: 2
B97: 46163 | C97: AMWT-C8ELSSRAPE | D97: https://agent-admin.paveapi.com/inspectionView/AMWT-C8ELSSRAPE?activeTab=past-sessions | T97: developer | U97: ngan.luongthi | X97: None | Z97: =IFERROR(__xludf.DUMMYFUNCTION("""COMPUTED_VALUE"""),"") | AA97: 0 | AB97: =IFERROR(__xludf.DUMMYFUNCTION("""COMPUTED_VALUE"""),1.0) -> 1 | AD97: =IFERROR(__xludf.DUMMYFUNCTION("""COMPUTED_VALUE"""),"") | AE97: 3 | AF97: 5
B98: 46163 | C98: AMWT-1DDORJRZL4 | D98: https://agent-admin.paveapi.com/inspectionView/AMWT-1DDORJRZL4?activeTab=past-sessions | T98: developer | U98: huy.tran | V98: anh.dao | X98: None | Z98: =IFERROR(__xludf.DUMMYFUNCTION("""COMPUTED_VALUE"""),"") | AA98: 0 | AB98: =IFERROR(__xludf.DUMMYFUNCTION("""COMPUTED_VALUE"""),1.0) -> 1 | AC98: 0 | AD98: =IFERROR(__xludf.DUMMYFUNCTION("""COMPUTED_VALUE"""),1.0) -> 1 | AE98: 5 | AF98: 3
B99: 46163 | C99: AMWT-CDHMEV16XV | D99: https://agent-admin.paveapi.com/inspectionView/AMWT-CDHMEV16XV?activeTab=past-sessions | T99: developer | U99: duy.nguyenquoc | X99: None | Z99: =IFERROR(__xludf.DUMMYFUNCTION("""COMPUTED_VALUE"""),"") | AA99: 0 | AB99: =IFERROR(__xludf.DUMMYFUNCTION("""COMPUTED_VALUE"""),1.0) -> 1 | AD99: =IFERROR(__xludf.DUMMYFUNCTION("""COMPUTED_VALUE"""),"") | AE99: 30 | AF99: 40
B100: 46163 | C100: AMWT-PZKBXSZSJP | D100: https://agent-admin.paveapi.com/inspectionView/AMWT-PZKBXSZSJP?activeTab=past-sessions | T100: developer | U100: phu.nguyenhoang | V100: hien.nhu | X100: None | Z100: =IFERROR(__xludf.DUMMYFUNCTION("""COMPUTED_VALUE"""),"") | AA100: 0 | AB100: =IFERROR(__xludf.DUMMYFUNCTION("""COMPUTED_VALUE"""),1.0) -> 1 | AC100: 0 | AD100: =IFERROR(__xludf.DUMMYFUNCTION("""COMPUTED_VALUE"""),1.0) -> 1 | AE100: 35 | AF100: 33
...

Sheet PERF_W22
E1: DAMAGE FAILED | T1: PERSON RESPONSIBLE | Z1: ACCURACY
A2: Date | C2: Sessions | D2: {={"LINK SESSION"; IF(C3:C1862 = "", "", "https://agent-admin.paveapi.com/inspectionView/" & C3:C1862 & "?activeTab=past-sessions")}} -> LINK SESSION | E2: Left Side | H2: Front Side | K2: Right Side | N2: Back Side | Q2: Other Side | T2: Inspect | U2: Check | V2: Cross-Check/Admin | W2: RE-CHECK & NOTE | X2: Reason | Y2: Total Dmg Missing (Session) | Z2: Inspect | AB2: Check | AD2: Cross-Check/Admin | AF2: Total Damage | AH2: AUDITOR
A3: {=IF(B3:B1862="", "", TEXT(B3:B1862, "ddd"))} -> Mon | B3: 46167 | C3: LTM-OFF695J5BS | D3: https://agent-admin.paveapi.com/inspectionView/LTM-OFF695J5BS?activeTab=past-sessions | U3: hieu.cao | X3: None | AF3: 0 | AG3: 1 | AH3: anh.tran
A4: Wed | B4: 46169 | C4: AMWT-LUQUR52TIJ | D4: https://agent-admin.paveapi.com/inspectionView/AMWT-LUQUR52TIJ?activeTab=past-sessions | U4: hieu.cao | V4: huyhien.nguyen | X4: None | AF4: 25 | AG4: 23 | AH4: anh.tran
A5: Thu | B5: 46170 | C5: LTM-FUHZTZTQ7Y | D5: https://agent-admin.paveapi.com/inspectionView/LTM-FUHZTZTQ7Y?activeTab=past-sessions | U5: hieu.cao | X5: None | AF5: 0 | AG5: 2 | AH5: anh.tran
A6: Tue | B6: 46168 | C6: AMWT-HMKKWK0Z6U | D6: https://agent-admin.paveapi.com/inspectionView/AMWT-HMKKWK0Z6U?activeTab=past-sessions | U6: hieu.cao | X6: None | AF6: 16 | AG6: 15 | AH6: anh.tran
A7: Wed | B7: 46169 | C7: CRMI-ILWB9KW4AJ | D7: https://agent-admin.paveapi.com/inspectionView/CRMI-ILWB9KW4AJ?activeTab=past-sessions | U7: hieu.cao | V7: duy.huynh | AH7: anh.tran
A8: Thu | B8: 46170 | C8: AMWT-VR5MHKGSUM | D8: https://agent-admin.paveapi.com/inspectionView/AMWT-VR5MHKGSUM?activeTab=past-sessions | U8: kim.huynh | X8: None | AH8: duy.huynh
A9: Thu | B9: 46170 | C9: LTM-VKAFE0LGC9 | D9: https://agent-admin.paveapi.com/inspectionView/LTM-VKAFE0LGC9?activeTab=past-sessions | U9: kim.huynh | X9: None | AH9: duy.huynh
A10: Wed | B10: 46169 | C10: CRMI-CWXHTNKM3J | D10: https://agent-admin.paveapi.com/inspectionView/CRMI-CWXHTNKM3J?activeTab=past-sessions | U10: kim.huynh | V10: huyhien.nguyen | X10: None | AH10: duy.huynh
A11: Wed | B11: 46169 | C11: LTM-MAPQYEL8KU | D11: https://agent-admin.paveapi.com/inspectionView/LTM-MAPQYEL8KU?activeTab=past-sessions | U11: kim.huynh | X11: None | AH11: duy.huynh
A12: Tue | B12: 46168 | C12: AMWT-62XLAMMTZT | D12: https://agent-admin.paveapi.com/inspectionView/AMWT-62XLAMMTZT?activeTab=past-sessions | L12: 1 | U12: kim.huynh | W12: View 4: Missing damage Dent medium through - Door front | X12: Checker Miss Damage | Y12: 1 | AF12: 23 | AG12: 23 | AH12: tran.le
A13: Tue | B13: 46168 | C13: CRMI-KITNYLX4BY | D13: https://agent-admin.paveapi.com/inspectionView/CRMI-KITNYLX4BY?activeTab=past-sessions | I13: 2 | O13: 3 | U13: kim.huynh | W13: View 5: - Remove damage (1) - Missing damage Scratch major not through - Hood View 8: - Remove damage (1, 2) - Missing damage Oxidized - Bumper | X13: Checker Miss Damage, Checker Wrong damage | Y13: 2 | AF13: 0 | AG13: 8 | AH13: tran.le
A14: Tue | B14: 46168 | C14: CRMI-MEXMAHKEWH | D14: https://agent-admin.paveapi.com/inspectionView/CRMI-MEXMAHKEWH?activeTab=past-sessions | U14: y.nguyen | X14: None | AH14: duy.huynh
A15: Wed | B15: 46169 | C15: LTM-A8EWQCGAPA | D15: https://agent-admin.paveapi.com/inspectionView/LTM-A8EWQCGAPA?activeTab=past-sessions | U15: y.nguyen | X15: None | AH15: duy.huynh
A16: Tue | B16: 46168 | C16: AMWK-7HITTDZJJP | D16: https://agent-admin.paveapi.com/inspectionView/AMWK-7HITTDZJJP?activeTab=past-sessions | U16: y.nguyen | X16: None | AH16: duy.huynh
A17: Mon | B17: 46167 | C17: CRMT-UAP8KNZSAQ | D17: https://agent-admin.paveapi.com/inspectionView/CRMT-UAP8KNZSAQ?activeTab=past-sessions | L17: 1 | U17: y.nguyen | W17: View7: Missing dmg Dented_Medium_Not_Through Door_Front | X17: Checker Miss Damage | AF17: 7 | AG17: 7 | AH17: duy.huynh
A18: Wed | B18: 46169 | C18: AMDE-TX8144W5VX | D18: https://agent-admin.paveapi.com/inspectionView/AMDE-TX8144W5VX?activeTab=past-sessions | U18: y.nguyen | V18: anh.dao | X18: None | AH18: tran.le
A19: Wed | B19: 46169 | U19: yen.ho | X19: None | AH19: duy.huynh
A20: Tue | B20: 46168 | C20: AMDE-1TXC7KURWE | D20: https://agent-admin.paveapi.com/inspectionView/AMDE-1TXC7KURWE?activeTab=past-sessions | O20: 1 | U20: yen.ho | W20: View 8: Missing dmg Dented_Medium_Not_Through Hatchdoor_Rear_Left | X20: Checker Miss Damage | Y20: 1 | AF20: 32 | AG20: 32 | AH20: duy.huynh
A21: Tue | B21: 46168 | C21: LTM-WE1OGCP92B | D21: https://agent-admin.paveapi.com/inspectionView/LTM-WE1OGCP92B?activeTab=past-sessions | U21: yen.ho | X21: None | AH21: duy.huynh
A22: Thu | B22: 46170 | C22: AMDE-BHK1KXZRMP | D22: https://agent-admin.paveapi.com/inspectionView/AMDE-BHK1KXZRMP?activeTab=past-sessions | U22: yen.ho | AH22: duy.huynh
A23: Wed | B23: 46169 | C23: AMES-FLU7VLHPBF | D23: https://agent-admin.paveapi.com/inspectionView/AMES-FLU7VLHPBF?activeTab=past-sessions | T23: developer | U23: yen.ho | X23: None | AH23: ngocanh.tran
A24: Wed | B24: 46169 | C24: AMDE-TKBTT9T5SU | D24: https://agent-admin.paveapi.com/inspectionView/AMDE-TKBTT9T5SU?activeTab=past-sessions | T24: developer | U24: yen.ho | X24: None | AH24: ngocanh.tran
A25: Tue | B25: 46168 | C25: LTM-9EVDEQWWPN | D25: https://agent-admin.paveapi.com/inspectionView/LTM-9EVDEQWWPN?activeTab=past-sessions | F25: 1 | T25: developer | U25: tan.pham | W25: View 4: Missing damage_Scraped Medium_Bumper | X25: Checker Miss Damage | Y25: 1 | AF25: 7 | AG25: 7 | AH25: ngocanh.tran
A26: Wed | B26: 46169 | C26: AMDE-PAWJ1LC2JY | D26: https://agent-admin.paveapi.com/inspectionView/AMDE-PAWJ1LC2JY?activeTab=past-sessions | U26: tan.pham | X26: None | AH26: ngocanh.tran
A27: Mon | B27: 46167 | C27: AMWT-POKOEDI4AS | D27: https://agent-admin.paveapi.com/inspectionView/AMWT-POKOEDI4AS?activeTab=past-sessions | T27: developer | U27: tan.pham | X27: None | AH27: ngocanh.tran
A28: Thu | B28: 46170 | C28: AMDE-046JOICXV9 | D28: https://agent-admin.paveapi.com/inspectionView/AMDE-046JOICXV9?activeTab=past-sessions | U28: tan.pham
A29: Wed | B29: 46169 | C29: AMES-NCIXVTCU5Z | D29: https://agent-admin.paveapi.com/inspectionView/AMES-NCIXVTCU5Z?activeTab=past-sessions | U29: tan.pham | X29: None | AH29: tran.le
A30: Thu | B30: 46170 | C30: ICA-U6SXK9L0TJ | D30: https://agent-admin.paveapi.com/inspectionView/ICA-U6SXK9L0TJ?activeTab=past-sessions | U30: nhi.le | V30: tong.nguyen
A31: Tue | B31: 46168 | C31: AMWT-1KLWCWV6NH | D31: https://agent-admin.paveapi.com/inspectionView/AMWT-1KLWCWV6NH?activeTab=past-sessions | F31: 1 | U31: nhi.le | W31: View 4: Remove damage (1) | X31: Checker Wrong damage | AF31: 7 | AG31: 7 | AH31: tran.le
A32: Wed | B32: 46169 | C32: AMWT-NTQSKPCM0I | D32: https://agent-admin.paveapi.com/inspectionView/AMWT-NTQSKPCM0I?activeTab=past-sessions | L32: 1 | O32: 1 | U32: nhi.le | W32: View 7: Remove damage (5) View 8: Remove damage (1) | X32: Checker Wrong damage | AF32: 12 | AG32: 12 | AH32: tran.le
A33: Wed | B33: 46169 | C33: CRMI-E96KWUDECF | D33: https://agent-admin.paveapi.com/inspectionView/CRMI-E96KWUDECF?activeTab=past-sessions | I33: 2 | O33: 1 | U33: nhi.le | W33: View 5: - Remove damage (5) - Missing damage Multi scratch medium through - Bumper View 8: Remove damage (4) | X33: Checker Wrong damage, Checker Miss Damage | Y33: 1 | AF33: 0 | AG33: 21 | AH33: tran.le
A34: Thu | B34: 46170 | C34: AMWT-K76OC5JZRI | D34: https://agent-admin.paveapi.com/inspectionView/AMWT-K76OC5JZRI?activeTab=past-sessions | U34: nhi.le
A35: Tue | B35: 46168 | C35: CRMI-HSPEDHG9TR | D35: https://agent-admin.paveapi.com/inspectionView/CRMI-HSPEDHG9TR?activeTab=past-sessions | L35: 1 | R35: 1 | U35: nhi.le | W35: View 2: Wrong trans View 5: Missing damage Scrach medium not through - Bumper valance | X35: Checker Miss Damage, Other | Y35: 1 | AF35: 0 | AG35: 8 | AH35: tran.le
A36: Wed | B36: 46169 | C36: CRMI-SXZVD6RFCQ | D36: https://agent-admin.paveapi.com/inspectionView/CRMI-SXZVD6RFCQ?activeTab=past-sessions | F36: 1 | T36: developer | U36: tram.mai | W36: View 4: Missing damage_Dent Medium_Rocker | X36: Checker Miss Damage | Y36: 1 | AF36: 0 | AG36: 4 | AH36: ngocanh.tran
A37: Wed | B37: 46169 | C37: RLY2-3WJGWGTN6S | D37: https://agent-admin.paveapi.com/inspectionView/RLY2-3WJGWGTN6S?activeTab=past-sessions | I37: 1 | T37: developer | U37: tram.mai | W37: View 5: Missing damage_Dent Major_Bumper Valance | X37: Checker Miss Damage | Y37: 1 | AF37: 0 | AG37: 5 | AH37: ngocanh.tran
A38: Tue | B38: 46168 | C38: CRMI-ENZEL9WHUD | D38: https://agent-admin.paveapi.com/inspectionView/CRMI-ENZEL9WHUD?activeTab=past-sessions | T38: developer | U38: tram.mai | X38: None | AH38: ngocanh.tran
A39: Tue | B39: 46168 | C39: AMWT-S9NDFPNRNY | D39: https://agent-admin.paveapi.com/inspectionView/AMWT-S9NDFPNRNY?activeTab=past-sessions | U39: tram.mai | X39: None | AH39: ngocanh.tran
A40: Wed | B40: 46169 | C40: CRMT-MFESWKHZ1T | D40: https://agent-admin.paveapi.com/inspectionView/CRMT-MFESWKHZ1T?activeTab=past-sessions | U40: tram.mai | X40: None | AH40: ngocanh.tran
A41: Tue | B41: 46168 | C41: CRMI-Z1V80JCTBA | D41: https://agent-admin.paveapi.com/inspectionView/CRMI-Z1V80JCTBA?activeTab=past-sessions | T41: developer | U41: tram.mai | X41: None | AH41: ngocanh.tran
A42: Wed | B42: 46169 | C42: AMWT-BB7Q3MUKA8 | D42: https://agent-admin.paveapi.com/inspectionView/AMWT-BB7Q3MUKA8?activeTab=past-sessions | U42: tram.mai | V42: huyhien.nguyen, duy.huynh | X42: None | AH42: ngocanh.tran
A43: Thu | B43: 46170 | C43: AMWT-ESRCU5G33J | D43: https://agent-admin.paveapi.com/inspectionView/AMWT-ESRCU5G33J?activeTab=past-sessions | U43: tram.mai
A44: Mon | B44: 46167 | C44: CRMI-ANEIKLPCLL | D44: https://agent-admin.paveapi.com/inspectionView/CRMI-ANEIKLPCLL?activeTab=past-sessions | L44: 1 | U44: phuc.ho | W44: View 7: - Missing Dmg: Broken_Medium Rocker_Panel_Right | X44: Checker Miss Damage | AF44: 13 | AG44: 13 | AH44: duy.huynh
A45: Wed | B45: 46169 | C45: HHSI-GREBIYXFTE | D45: https://agent-admin.paveapi.com/inspectionView/HHSI-GREBIYXFTE?activeTab=past-sessions | U45: phuc.ho | X45: None | AH45: tran.le
A46: Wed | B46: 46169 | C46: CRMT-MOC8T2GQFK | D46: https://agent-admin.paveapi.com/inspectionView/CRMT-MOC8T2GQFK?activeTab=past-sessions | I46: 4 | L46: 1 | O46: 1 | U46: phuc.ho | W46: View 5: - Wrong component (5) -> Light fog - Missing damage Peeling medium - Bumper x 2 - Wrong damage (7) -> Scrape major View 7: Missing damage Dent medium not through - Fender View 8: Missing damage Scratch major not through - Trunk | X46: Checker Miss Damage, Checker Wrong damage | Y46: 4 | AF46: 0 | AG46: 25 | AH46: tran.le
A47: Tue | B47: 46168 | C47: CRMI-6SZ8LAU0YQ | D47: https://agent-admin.paveapi.com/inspectionView/CRMI-6SZ8LAU0YQ?activeTab=past-sessions | F47: 1 | I47: 1 | L47: 2 | U47: phuc.ho | W47: View 4: Remove damage (2) View 5: Missing damage Scratch medium not through - Hood View 7: - Missing damage Dent medium not through - Bumper - Missing damage Scratch medium not through - Quarter | X47: Checker Wrong damage, Checker Miss Damage | Y47: 3 | AF47: 0 | AG47: 16 | AH47: tran.le
A48: Tue | B48: 46168 | C48: AMWT-QBGNHLPJ9Y | D48: https://agent-admin.paveapi.com/inspectionView/AMWT-QBGNHLPJ9Y?activeTab=past-sessions | F48: 1 | I48: 1 | O48: 1 | U48: phuc.ho | W48: View 4: Remove damage (13) View 5: Missing damage Broken medium - Bumper View 8: Wrong component -> Molding tail light center | X48: Checker Wrong damage, Checker Miss Damage | Y48: 1 | AF48: 40 | AG48: 40 | AH48: tran.le
A49: Wed | B49: 46169 | C49: AMWK-J2LHYD7XV3 | D49: https://agent-admin.paveapi.com/inspectionView/AMWK-J2LHYD7XV3?activeTab=past-sessions | F49: 1 | T49: developer | U49: phuc.ho | W49: View 4: Remove (9) | X49: Checker Wrong damage | AF49: 18 | AG49: 18 | AH49: ngocanh.tran
A50: Tue | B50: 46168 | C50: AMWT-GZUKNBUDNC | D50: https://agent-admin.paveapi.com/inspectionView/AMWT-GZUKNBUDNC?activeTab=past-sessions | T50: developer | U50: phuc.ho | X50: None | AH50: ngocanh.tran
A51: Wed | B51: 46169 | C51: ZBV-WFXJU4LGAK | D51: https://agent-admin.paveapi.com/inspectionView/ZBV-WFXJU4LGAK?activeTab=past-sessions | O51: 1 | R51: 1 | T51: developer | U51: phuc.ho | W51: View 8: Missing damage_Dent medium through_Hatchdoor rear right View 15: Wrong Tire_Minor -> Medium | X51: Checker Miss Damage, Other | AF51: 6 | AG51: 6 | AH51: ngocanh.tran
A52: Wed | B52: 46169 | C52: AMAU-TI5WLOFDSD | D52: https://agent-admin.paveapi.com/inspectionView/AMAU-TI5WLOFDSD?activeTab=past-sessions | T52: developer | U52: binh.nguyen | X52: None | AH52: ngocanh.tran
A53: Tue | B53: 46168 | C53: CRMI-7IXQO7ONZV | D53: https://agent-admin.paveapi.com/inspectionView/CRMI-7IXQO7ONZV?activeTab=past-sessions | O53: 1 | R53: 2 | U53: binh.nguyen | W53: View 7: Remove damage (1) View 8: Remove damage (2) | X53: Checker Wrong damage | AF53: 0 | AG53: 13 | AH53: tran.le
A54: Tue | B54: 46168 | C54: AMDE-B12WOSHXPP | D54: https://agent-admin.paveapi.com/inspectionView/AMDE-B12WOSHXPP?activeTab=past-sessions | U54: binh.nguyen | X54: None | AH54: tran.le
A55: Wed | B55: 46169 | C55: RACI-DCEFA5MAEV | D55: https://agent-admin.paveapi.com/inspectionView/RACI-DCEFA5MAEV?activeTab=past-sessions | U55: binh.nguyen | X55: None | AH55: tran.le
A56: Wed | B56: 46169 | C56: LGA-0VRX9LSRKV | D56: https://agent-admin.paveapi.com/inspectionView/LGA-0VRX9LSRKV?activeTab=past-sessions | U56: binh.nguyen | X56: None | AH56: tran.le
A57: Wed | B57: 46169 | C57: AMES-H6PFPJT8QO | D57: https://agent-admin.paveapi.com/inspectionView/AMES-H6PFPJT8QO?activeTab=past-sessions | F57: 6 | L57: 6 | U57: binh.nguyen | W57: View 4: - Missing damage Dent medium seam line - Fender - Remove damage (3, 4, 5, 9, 12) View 7: - Remove damage (4, 7, 8, 10) - Missing damage Dent medium through - Quarter - Missing damage Dent medium seam line - Rocker | X57: Checker Miss Damage, Checker Wrong damage | Y57: 3 | AF57: 29 | AG57: 29 | AH57: tran.le
A58: Wed | B58: 46169 | C58: AMDE-SDE5TTYWMN | D58: https://agent-admin.paveapi.com/inspectionView/AMDE-SDE5TTYWMN?activeTab=past-sessions | U58: binh.nguyen | X58: None | AH58: tran.le
A59: Tue | B59: 46168 | C59: AMRR-BYVVCQUO79 | D59: https://agent-admin.paveapi.com/inspectionView/AMRR-BYVVCQUO79?activeTab=past-sessions | U59: binh.nguyen | X59: None | AH59: tran.le
A60: Tue | B60: 46168 | C60: AMDE-0DR8ETBBB9 | D60: https://agent-admin.paveapi.com/inspectionView/AMDE-0DR8ETBBB9?activeTab=past-sessions | I60: 1 | U60: binh.nguyen | W60: View 5: Missing damage Missing - Mud flap | X60: Checker Miss Damage | Y60: 1 | AF60: 35 | AG60: 34 | AH60: tran.le
A61: Wed | B61: 46169 | C61: AMES-QRMRMHMTVY | D61: https://agent-admin.paveapi.com/inspectionView/AMES-QRMRMHMTVY?activeTab=past-sessions | L61: 1 | U61: binh.nguyen | W61: View 7: Remove damage (5) | X61: Checker Wrong damage | AF61: 12 | AG61: 12 | AH61: tran.le
A62: Tue | B62: 46168 | C62: AMDE-AG1ELUV4PU | D62: https://agent-admin.paveapi.com/inspectionView/AMDE-AG1ELUV4PU?activeTab=past-sessions | F62: 1 | U62: binh.nguyen | W62: View 4: Remove damage (1) | X62: Checker Wrong damage | AF62: 3 | AG62: 3 | AH62: tran.le
A63: Tue | B63: 46168 | C63: AMIT-7EYAWFIQB5 | D63: https://agent-admin.paveapi.com/inspectionView/AMIT-7EYAWFIQB5?activeTab=past-sessions | T63: developer | U63: my.nguyen | X63: None | AH63: ngocanh.tran
A64: Mon | B64: 46167 | C64: AMWK-B1BNEGGHIZ | D64: https://agent-admin.paveapi.com/inspectionView/AMWK-B1BNEGGHIZ?activeTab=past-sessions | T64: developer | U64: my.nguyen | X64: None | AH64: ngocanh.tran
A65: Mon | B65: 46167 | C65: AMFR-KPOIXXEATV | D65: https://agent-admin.paveapi.com/inspectionView/AMFR-KPOIXXEATV?activeTab=past-sessions | T65: developer | U65: my.nguyen | X65: None | AH65: ngocanh.tran
A66: Wed | B66: 46169 | C66: AMDE-VXBOTWDNHH | D66: https://agent-admin.paveapi.com/inspectionView/AMDE-VXBOTWDNHH?activeTab=past-sessions | T66: developer | U66: my.nguyen | X66: None | AH66: ngocanh.tran
A67: Thu | B67: 46170 | C67: AMDE-S2KTHQXA7B | D67: https://agent-admin.paveapi.com/inspectionView/AMDE-S2KTHQXA7B?activeTab=past-sessions | U67: my.nguyen | X67: None | AH67: ngocanh.tran
A68: Tue | B68: 46168 | C68: AMDE-BXZY8N6CDL | D68: https://agent-admin.paveapi.com/inspectionView/AMDE-BXZY8N6CDL?activeTab=past-sessions | U68: my.nguyen | X68: None | AH68: ngocanh.tran
A69: Tue | B69: 46168 | C69: AMES-8IEF0T5V6K | D69: https://agent-admin.paveapi.com/inspectionView/AMES-8IEF0T5V6K?activeTab=past-sessions | O69: 1 | U69: my.nguyen | W69: View 8: Remove damage (1) | X69: Checker Wrong damage | AF69: 5 | AG69: 5 | AH69: tran.le
A70: Tue | B70: 46168 | C70: AMIT-2OBVEH620S | D70: https://agent-admin.paveapi.com/inspectionView/AMIT-2OBVEH620S?activeTab=past-sessions | U70: my.nguyen | X70: None | AH70: tran.le
A71: Wed | B71: 46169 | C71: AMAU-HTHWN9QNMZ | D71: https://agent-admin.paveapi.com/inspectionView/AMAU-HTHWN9QNMZ?activeTab=past-sessions | U71: nhu.nguyen
A72: Tue | B72: 46168 | C72: AMWK-TELFEE6D61 | D72: https://agent-admin.paveapi.com/inspectionView/AMWK-TELFEE6D61?activeTab=past-sessions | U72: nhu.nguyen
A73: Wed | B73: 46169 | C73: CRMT-VNXZC4ACED | D73: https://agent-admin.paveapi.com/inspectionView/CRMT-VNXZC4ACED?activeTab=past-sessions | U73: nhu.nguyen | V73: nhat.ngo
